Workbook

Sheet Executive Dashboard
A1: GULONG | CHANNEL REVENUE
A3: September 1–24, 2026 • Backend order-date cohorts • Week 4 covers 3 days • Values exclude VAT
A6: ALL-ORDER NET SALES | D6: FULFILLED NET REVENUE | G6: OPEN ORDER NET VALUE | J6: CANCELLED NET VALUE
A7: 4799816.2 | D7: 2091465.3 | G7: 1332416.8 | J7: 1293777
A43: ANALYST FINDINGS & NEXT ACTIONS
A45: Direct & Organic contributes 62.5% of fulfilled net revenue (₱1,307,529).
A47: Cancelled orders represent ₱1,293,777, or 27.0% of September order value. Review cancellation reasons before increasing acquisition spend.
A49: Open orders hold ₱1,332,417. Prioritize payment and fulfillment follow-up; this value is not a revenue forecast.
A51: Week 4 averages ₱169,322 per day versus ₱196,039 in Week 3 (-13.6%). Three-day coverage and weekday mix limit comparison.
A53: Week 4 has no fulfilled revenue in this snapshot. These recent order cohorts have had less time to fulfill; this is not evidence of zero eventual sales.
A55: 8 fulfilled orders are partially paid. Fulfilled revenue uses full order value and is not cash collected.
A57: Backend customer type is an operational classification (Website/Fb/Chatbot), not new versus returning customer and not the analytics acquisition channel.
A59: No advertising spend, clicks or session denominators were supplied. ROAS, CAC and visitor-to-order conversion cannot be calculated from these exports.

Sheet Source Data
A1: Channel | B1: Session campaign | C1: Order ID | D1: Order date | E1: Week | F1: Scope | G1: Customer type | H1: Customer source | I1: Order status | J1: Payment status | K1: Net sales | L1: Fulfilled net revenue | M1: Gross order value | N1: Fulfilled flag | O1: Cancelled flag | P1: Open net value | Q1: Cancelled net value | R1: Return refund net value | S1: Purchase events | T1: Quantity | U1: Brand | V1: SKU | W1: Page path + query string | X1: Source file | Y1: Source CSV row | Z1: Backend loaded at | AA1: Backend updated at | AB1: Test order
A2: Google Ads | B2: All Brand - PMax PH | C2: 39773 | D2: 46286.792 | E2: Week 3 | F2: Included | G2: Website | I2: New | J2: Unpaid | K2: 8473.13 | L2: 0 | M2: 9489.9 | N2: 0 | O2: 0 | P2: 8473.13 | Q2: 0 | R2: 0 | S2: 4 | T2: 2 | U2: YOKOHAMA | V2: YOKOHAMA 185/65/R14 BLUEARTH ES32 86H | W2: /complete-order?requestid=Mzk3NzM%3D | X2: revenue_match/google_cpc.csv | Y2: 2 | Z2: 2026-09-25 02:00:22 | AA2: 2026-09-22T10:55:00 | AB2: false
A3: Google Ads | B3: BFG Advantage Touring – PMax PH | C3: 39143 | D3: 46270.549 | E3: Week 1 | F3: Included | G3: Website | I3: Fulfilled | J3: Fully Paid | K3: 37973.21 | L3: 37973.21 | M3: 42530 | N3: 1 | O3: 0 | P3: 0 | Q3: 0 | R3: 0 | S3: 2 | T3: 4 | U3: MICHELIN | V3: MICHELIN 265/65/R17 PRIMACY SUV+ 112H | W3: /complete-order?requestid=MzkxNDM%3D | X3: revenue_match/google_cpc.csv | Y3: 3 | Z3: 2026-09-25 02:00:22 | AA3: 2026-09-10T15:28:00 | AB3: false
A4: Google Ads | B4: MICHELIN - PMAX (Traffic) | C4: 39395 | D4: 46276.733 | E4: Week 2 | F4: Included | G4: Website | I4: Fulfilled | J4: Fully Paid | K4: 7095.27 | L4: 7095.27 | M4: 7946.7 | N4: 1 | O4: 0 | P4: 0 | Q4: 0 | R4: 0 | S4: 2 | T4: 3 | U4: ARIVO | V4: ARIVO 185/55/R15 PREMIO COMFORT 6 | W4: /complete-order?requestid=MzkzOTU%3D | X4: revenue_match/google_cpc.csv | Y4: 4 | Z4: 2026-09-25 02:00:22 | AA4: 2026-09-21T14:40:00 | AB4: false
A5: Google Ads | B5: Michelin - PMax PH | C5: 39497 | D5: 46279.678 | E5: Week 2 | F5: Included | G5: Website | H5: CALL | I5: Fulfilled | J5: Fully Paid | K5: 37191.96 | L5: 37191.96 | M5: 41655 | N5: 1 | O5: 0 | P5: 0 | Q5: 0 | R5: 0 | S5: 2 | T5: 4 | U5: MICHELIN | V5: MICHELIN 235/50/R18 PRIMACY 5 97W | W5: /complete-order?requestid=Mzk0OTc= | X5: revenue_match/google_cpc.csv | Y5: 5 | Z5: 2026-09-25 02:00:22 | AA5: 2026-09-22T11:50:00 | AB5: false
A6: Google Ads | B6: Michelin - PMax PH | C6: 39507 | D6: 46279.738 | E6: Week 2 | F6: Included | G6: Website | H6: Website | I6: Pending | J6: Partial Payment | K6: 26661.61 | L6: 0 | M6: 29861 | N6: 0 | O6: 0 | P6: 26661.61 | Q6: 0 | R6: 0 | S6: 2 | T6: 4 | U6: KINTO | V6: KINTO 285/40/ZR18 X-68+ 101W | W6: /complete-order?requestid=Mzk1MDc%3D | X6: revenue_match/google_cpc.csv | Y6: 6 | Z6: 2026-09-25 02:00:22 | AA6: 2026-09-17T11:10:00 | AB6: false
A7: Google Ads | B7: BFG Advantage Touring – PMax PH | C7: 39542 | D7: 46280.605 | E7: Week 3 | F7: Included | G7: Website | H7: Website | I7: Fulfilled | J7: Fully Paid | K7: 11506.7 | L7: 11506.7 | M7: 12887.5 | N7: 1 | O7: 0 | P7: 0 | Q7: 0 | R7: 0 | S7: 2 | T7: 5 | U7: WESTLAKE | V7: WESTLAKE 185/70/R14 RP36 | W7: /complete-order?requestid=Mzk1NDI%3D | X7: revenue_match/google_cpc.csv | Y7: 7 | Z7: 2026-09-25 02:00:22 | AA7: 2026-09-24T15:02:00 | AB7: false
A8: Google Ads | B8: All Brand - PMax PH | C8: 39568 | D8: 46281.465 | E8: Week 3 | F8: Included | G8: Website | I8: New | J8: Unpaid | K8: 15083.75 | L8: 0 | M8: 16893.8 | N8: 0 | O8: 0 | P8: 15083.75 | Q8: 0 | R8: 0 | S8: 2 | T8: 4 | U8: BFGOODRICH | V8: BFGOODRICH 195/50/R16 ADVANTAGE TOURING 88V | W8: /complete-order?requestid=Mzk1Njg= | X8: revenue_match/google_cpc.csv | Y8: 8 | Z8: 2026-09-25 02:00:22 | AA8: 2026-09-16T11:15:00 | AB8: false
A9: Google Ads | B9: SRC | All Brands | PH | C9: 39570 | D9: 46281.465 | E9: Week 3 | F9: Included | G9: Website | H9: Website | I9: New | J9: Unpaid | K9: 151683.75 | L9: 0 | M9: 169885.8 | N9: 0 | O9: 0 | P9: 151683.75 | Q9: 0 | R9: 0 | S9: 2 | T9: 12 | U9: TOYO | V9: TOYO 235/60/R18 OPAT3 107H | W9: /complete-order?requestid=Mzk1NzA= | X9: revenue_match/google_cpc.csv | Y9: 9 | Z9: 2026-09-25 02:00:22 | AA9: 2026-09-16T11:25:00 | AB9: false
A10: Google Ads | B10: Michelin - PMax PH | C10: 39581 | D10: 46281.585 | E10: Week 3 | F10: Included | G10: Website | I10: New | J10: Unpaid | K10: 45707.95 | L10: 0 | M10: 51192.9 | N10: 0 | O10: 0 | P10: 45707.95 | Q10: 0 | R10: 0 | S10: 2 | T10: 2 | U10: TOYO | V10: TOYO 275/45/R21 PROXES SPORT PXSP2 110Y | W10: /complete-order?requestid=Mzk1ODE= | X10: revenue_match/google_cpc.csv | Y10: 10 | Z10: 2026-09-25 02:00:22 | AA10: 2026-09-17T10:31:00 | AB10: false
A11: Google Ads | B11: Michelin - PMax PH | C11: 39583 | D11: 46281.593 | E11: Week 3 | F11: Included | G11: Website | I11: New | J11: Unpaid | K11: 45707.95 | L11: 0 | M11: 51192.9 | N11: 0 | O11: 0 | P11: 45707.95 | Q11: 0 | R11: 0 | S11: 2 | T11: 2 | U11: TOYO | V11: TOYO 275/45/R21 PROXES SPORT PXSP2 110Y | W11: /complete-order?requestid=Mzk1ODM= | X11: revenue_match/google_cpc.csv | Y11: 11 | Z11: 2026-09-25 02:00:22 | AA11: 2026-09-17T10:31:00 | AB11: false
A12: Google Ads | B12: All Brand - PMax PH | C12: 39586 | D12: 46281.64 | E12: Week 3 | F12: Included | G12: Website | H12: CALL | I12: Fulfilled | J12: Fully Paid | K12: 42857.14 | L12: 42857.14 | M12: 48000 | N12: 1 | O12: 0 | P12: 0 | Q12: 0 | R12: 0 | S12: 2 | T12: 4 | U12: MICHELIN | V12: MICHELIN 255/45/R20 PILOT SPORT EV 105W | W12: /complete-order?requestid=Mzk1ODY= | X12: revenue_match/google_cpc.csv | Y12: 12 | Z12: 2026-09-25 02:00:22 | AA12: 2026-09-22T15:56:00 | AB12: false
A13: Google Ads | B13: BFG Advantage Touring – PMax PH | C13: 39603 | D13: 46282.358 | E13: Week 3 | F13: Included | G13: Website | I13: New | J13: Unpaid | K13: 29117.32 | L13: 0 | M13: 32611.4 | N13: 0 | O13: 0 | P13: 29117.32 | Q13: 0 | R13: 0 | S13: 2 | T13: 8 | U13: HANKOOK | V13: HANKOOK 205/55/R16 VENTUS PRIME 4 91W | W13: /complete-order?requestid=Mzk2MDM= | X13: revenue_match/google_cpc.csv | Y13: 13 | Z13: 2026-09-25 02:00:22 | AA13: 2026-09-17T10:48:00 | AB13: false
A14: Google Ads | B14: Gulongph Branding - PMax | C14: 39608 | D14: 46282.418 | E14: Week 3 | F14: Included | G14: Website | H14: Website | I14: Fulfilled | J14: Fully Paid | K14: 4941.16 | L14: 4941.16 | M14: 5534.1 | N14: 1 | O14: 0 | P14: 0 | Q14: 0 | R14: 0 | S14: 2 | T14: 2 | U14: ARIVO | V14: ARIVO 185/60/R15 PREMIO COMFORT 6 88H | W14: /complete-order?requestid=Mzk2MDg%3D | X14: revenue_match/google_cpc.csv | Y14: 14 | Z14: 2026-09-25 02:00:22 | AA14: 2026-09-21T13:29:00 | AB14: false
A15: Google Ads | B15: BFG Advantage Touring – PMax PH | C15: 39623 | D15: 46282.468 | E15: Week 3 | F15: Included | G15: Website | H15: CALL | I15: Pending | J15: Partial Payment | K15: 30008.04 | L15: 0 | M15: 33609 | N15: 0 | O15: 0 | P15: 30008.04 | Q15: 0 | R15: 0 | S15: 2 | T15: 8 | U15: HANKOOK | V15: HANKOOK 205/55/R16 VENTUS PRIME 4 91W | W15: /complete-order?requestid=Mzk2MjM= | X15: revenue_match/google_cpc.csv | Y15: 15 | Z15: 2026-09-25 02:00:22 | AA15: 2026-09-24T15:39:00 | AB15: false
A16: Google Ads | B16: BFG Advantage Touring – PMax PH | C16: 39665 | D16: 46283.524 | E16: Week 3 | F16: Included | G16: Website | H16: Website | I16: Fulfilled | J16: Fully Paid | K16: 6785.71 | L16: 6785.71 | M16: 7600 | N16: 1 | O16: 0 | P16: 0 | Q16: 0 | R16: 0 | S16: 2 | T16: 2 | U16: BFGOODRICH | V16: BFGOODRICH 185/55/R15 ADVANTAGE TOURING 86V | W16: /complete-order?requestid=Mzk2NjU%3D | X16: revenue_match/google_cpc.csv | Y16: 16 | Z16: 2026-09-25 02:00:22 | AA16: 2026-09-24T14:23:00 | AB16: false
A17: Google Ads | B17: BFG Advantage Touring – PMax PH | C17: 39677 | D17: 46283.717 | E17: Week 3 | F17: Included | G17: Website | H17: Website | I17: New | J17: Unpaid | K17: 4808.04 | L17: 0 | M17: 5385 | N17: 0 | O17: 0 | P17: 4808.04 | Q17: 0 | R17: 0 | S17: 2 | T17: 1 | U17: BFGOODRICH | V17: BFGOODRICH 215/45/R17 ADVANTAGE TOURING 91V | W17: /complete-order?requestid=Mzk2Nzc= | X17: revenue_match/google_cpc.csv | Y17: 17 | Z17: 2026-09-25 02:00:22 | AA17: 2026-09-21T15:58:00 | AB17: false
A18: Google Ads | B18: BFG Advantage Touring – PMax PH | C18: 39691 | D18: 46284.056 | E18: Week 3 | F18: Included | G18: Website | H18: Website | I18: Processing | J18: Fully Paid | K18: 39419.64 | L18: 0 | M18: 44150 | N18: 0 | O18: 0 | P18: 39419.64 | Q18: 0 | R18: 0 | S18: 2 | T18: 4 | U18: MICHELIN | V18: MICHELIN 255/40/ZR18 PILOT SPORT 5 99Y XL TL | W18: /complete-order?requestid=Mzk2OTE%3D | X18: revenue_match/google_cpc.csv | Y18: 18 | Z18: 2026-09-25 02:00:22 | AA18: 2026-09-23T15:18:00 | AB18: false
A19: Google Ads | B19: All Brand - PMax PH | C19: 39692 | D19: 46284.353 | E19: Week 3 | F19: Included | G19: Website | I19: Fulfilled | J19: Partial Payment | K19: 14979.64 | L19: 14979.64 | M19: 16777.2 | N19: 1 | O19: 0 | P19: 0 | Q19: 0 | R19: 0 | S19: 2 | T19: 4 | U19: BRIDGESTONE | V19: BRIDGESTONE 175/65/R14 ECOPIA EP150 82H | W19: /complete-order?requestid=Mzk2OTI%3D | X19: revenue_match/google_cpc.csv | Y19: 19 | Z19: 2026-09-25 02:00:22 | AA19: 2026-09-24T09:59:00 | AB19: false
A20: Google Ads | B20: Michelin - PMax PH | C20: 39705 | D20: 46284.667 | E20: Week 3 | F20: Included | G20: Website | H20: Website | I20: Cancelled | J20: Fully Paid | K20: 10851.25 | L20: 0 | M20: 12153.4 | N20: 0 | O20: 1 | P20: 0 | Q20: 10851.25 | R20: 0 | S20: 2 | T20: 4 | U20: BFGOODRICH | V20: BFGOODRICH 175/65/R14 ADVANTAGE TOURING 82H | W20: /complete-order?requestid=Mzk3MDU%3D | X20: revenue_match/google_cpc.csv | Y20: 20 | Z20: 2026-09-25 02:00:22 | AA20: 2026-09-22T14:02:00 | AB20: false
A21: Google Ads | B21: (cross-network) | C21: 39736 | D21: 46285.798 | E21: Week 3 | F21: Included | G21: Website | I21: Fulfilled | J21: Fully Paid | K21: 8613.66 | L21: 8613.66 | M21: 9647.3 | N21: 1 | O21: 0 | P21: 0 | Q21: 0 | R21: 0 | S21: 2 | T21: 2 | U21: YOKOHAMA | V21: YOKOHAMA 185/60/R15 BLUEARTH ES32 84H | W21: /complete-order?requestid=Mzk3MzY%3D | X21: revenue_match/google_cpc.csv | Y21: 21 | Z21: 2026-09-25 02:00:22 | AA21: 2026-09-24T14:48:00 | AB21: false
A22: Google Ads | B22: Michelin - PMax PH | C22: 39738 | D22: 46285.822 | E22: Week 3 | F22: Included | G22: Website | I22: For Return | J22: Partial Payment | K22: 10940.54 | L22: 0 | M22: 12253.4 | N22: 0 | O22: 0 | P22: 0 | Q22: 0 | R22: 10940.54 | S22: 2 | T22: 4 | U22: BFGOODRICH | V22: BFGOODRICH 175/65/R14 ADVANTAGE TOURING 82H | W22: /complete-order?requestid=Mzk3Mzg%3D | X22: revenue_match/google_cpc.csv | Y22: 22 | Z22: 2026-09-25 02:00:22 | AA22: 2026-09-23T10:01:00 | AB22: false
A23: Google Ads | B23: All Brand - PMax PH | C23: 39816 | D23: 46287.829 | E23: Week 4 | F23: Included | G23: Website | H23: Website | I23: Processing | J23: Fully Paid | K23: 19370.54 | L23: 0 | M23: 21695 | N23: 0 | O23: 0 | P23: 19370.54 | Q23: 0 | R23: 0 | S23: 2 | T23: 4 | U23: MICHELIN | V23: MICHELIN 185/55/R15 ENERGY XM2+ 86V | W23: /complete-order?requestid=Mzk4MTY%3D | X23: revenue_match/google_cpc.csv | Y23: 23 | Z23: 2026-09-25 02:00:22 | AA23: 2026-09-23T11:50:00 | AB23: false
A24: Google Ads | B24: Gulongph Branding - PMax | C24: 39835 | D24: 46288.509 | E24: Week 4 | F24: Included | G24: Website | I24: Pending | J24: Fully Paid | K24: 6370.54 | L24: 0 | M24: 7135 | N24: 0 | O24: 0 | P24: 6370.54 | Q24: 0 | R24: 0 | S24: 2 | T24: 1 | U24: YOKOHAMA | V24: YOKOHAMA 205/65/R16 BLUEARTH E70B 95H | W24: /complete-order?requestid=Mzk4MzU%3D | X24: revenue_match/google_cpc.csv | Y24: 24 | Z24: 2026-09-25 02:00:22 | AA24: 2026-09-23T12:15:00 | AB24: false
A25: Google Ads | B25: BFG Advantage Touring – PMax PH | C25: 39862 | D25: 46288.753 | E25: Week 4 | F25: Included | G25: Website | I25: Processing | J25: Fully Paid | K25: 26638.93 | L25: 0 | M25: 29835.6 | N25: 0 | O25: 0 | P25: 26638.93 | Q25: 0 | R25: 0 | S25: 2 | T25: 4 | U25: CST | V25: CST 265/60/R18 SAHARA AT 2 110T | W25: /complete-order?requestid=Mzk4NjI%3D | X25: revenue_match/google_cpc.csv | Y25: 25 | Z25: 2026-09-25 02:00:22 | AA25: 2026-09-24T12:11:00 | AB25: false
A26: Google Ads | B26: BFG Advantage Touring – PMax PH | C26: 39870 | D26: 46289.392 | E26: Week 4 | F26: Included | G26: Website | I26: Pending | J26: Partial Payment | K26: 11310.18 | L26: 0 | M26: 12667.4 | N26: 0 | O26: 0 | P26: 11310.18 | Q26: 0 | R26: 0 | S26: 2 | T26: 4 | U26: ARIVO | V26: ARIVO 205/65/R15 PREMIO COMFORT 6 94V | W26: /complete-order?requestid=Mzk4NzA= | X26: revenue_match/google_cpc.csv | Y26: 26 | Z26: 2026-09-25 02:00:22 | AA26: 2026-09-24T09:27:00 | AB26: false
A27: Google Ads | B27: Michelin - PMax PH | C27: 39877 | D27: 46289.408 | E27: Week 4 | F27: Included | G27: Website | I27: Cancelled | J27: Pending | K27: 21785.71 | L27: 0 | M27: 24400 | N27: 0 | O27: 1 | P27: 0 | Q27: 21785.71 | R27: 0 | S27: 2 | T27: 4 | U27: BFGOODRICH | V27: BFGOODRICH 225/55/R18 ADVANTAGE TOURING 98H | W27: /complete-order?requestid=Mzk4Nzc= | X27: revenue_match/google_cpc.csv | Y27: 27 | Z27: 2026-09-25 02:00:22 | AA27: 2026-09-24T10:30:00 | AB27: false
A28: Google Ads | B28: Michelin - PMax PH | C28: 39878 | D28: 46289.408 | E28: Week 4 | F28: Included | G28: Website | H28: Website | I28: Cancelled | J28: Pending | K28: 21785.71 | L28: 0 | M28: 24400 | N28: 0 | O28: 1 | P28: 0 | Q28: 21785.71 | R28: 0 | S28: 2 | T28: 4 | U28: BFGOODRICH | V28: BFGOODRICH 225/55/R18 ADVANTAGE TOURING 98H | W28: /complete-order?requestid=Mzk4Nzg= | X28: revenue_match/google_cpc.csv | Y28: 28 | Z28: 2026-09-25 02:00:22 | AA28: 2026-09-24T10:29:00 | AB28: false
A29: Google Ads | B29: BFG Advantage Touring – PMax PH | C29: 39895 | D29: 46289.543 | E29: Week 4 | F29: Included | G29: Website | I29: New | J29: Unpaid | K29: 10774.91 | L29: 0 | M29: 12067.9 | N29: 0 | O29: 0 | P29: 10774.91 | Q29: 0 | R29: 0 | S29: 2 | T29: 2 | U29: BFGOODRICH | V29: BFGOODRICH 225/50/R17 ADVANTAGE TOURING 98V | W29: /complete-order?requestid=Mzk4OTU= | X29: revenue_match/google_cpc.csv | Y29: 29 | Z29: 2026-09-25 02:00:22 | AA29: 2026-09-24T13:02:00 | AB29: false
A30: Google Ads | B30: Michelin - PMax PH | C30: 39898 | D30: 46289.612 | E30: Week 4 | F30: Included | G30: Website | H30: CHAT | I30: Processing | J30: Fully Paid | K30: 27812.14 | L30: 0 | M30: 31149.6 | N30: 0 | O30: 0 | P30: 27812.14 | Q30: 0 | R30: 0 | S30: 2 | T30: 4 | U30: YOKOHAMA | V30: YOKOHAMA 215/60/R17 GEOLANDAR CV G058 96H | W30: /complete-order?requestid=Mzk4OTg= | X30: revenue_match/google_cpc.csv | Y30: 30 | Z30: 2026-09-25 02:00:22 | AA30: 2026-09-24T14:46:00 | AB30: false
A31: Google Ads | B31: Michelin - PMax PH | C31: 39017 | D31: 46267.26 | E31: Week 1 | F31: Included | G31: Website | H31: Website | I31: Fulfilled | J31: Fully Paid | K31: 14073.04 | L31: 14073.04 | M31: 15761.8 | N31: 1 | O31: 0 | P31: 0 | Q31: 0 | R31: 0 | S31: 2 | T31: 4 | U31: BFGOODRICH | V31: BFGOODRICH 185/65/R15 ADVANTAGE TOURING 88H | W31: /complete-order?requestid=MzkwMTc%3D | X31: revenue_match/google_cpc.csv | Y31: 31 | Z31: 2026-09-25 02:00:22 | AA31: 2026-09-18T09:41:00 | AB31: false
A32: Google Ads | B32: Michelin - PMax PH | C32: 39032 | D32: 46267.513 | E32: Week 1 | F32: Included | G32: Website | H32: CALL | I32: Fulfilled | J32: Fully Paid | K32: 24990.18 | L32: 24990.18 | M32: 27989 | N32: 1 | O32: 0 | P32: 0 | Q32: 0 | R32: 0 | S32: 2 | T32: 4 | U32: YOKOHAMA | V32: YOKOHAMA 215/55/R16 BLUEARTH GT AE51 97W | W32: /complete-order?requestid=MzkwMzI%3D | X32: revenue_match/google_cpc.csv | Y32: 32 | Z32: 2026-09-25 02:00:22 | AA32: 2026-09-18T09:42:00 | AB32: false
A33: Google Ads | B33: All Brand - PMax PH | C33: 39034 | D33: 46267.556 | E33: Week 1 | F33: Included | G33: Website | I33: New | J33: Unpaid | K33: 19659.82 | L33: 0 | M33: 22019 | N33: 0 | O33: 0 | P33: 19659.82 | Q33: 0 | R33: 0 | S33: 2 | T33: 4 | U33: HANKOOK | V33: HANKOOK 205/55/R17 VENTUS PRIME 4 95V | W33: /complete-order?requestid=MzkwMzQ= | X33: revenue_match/google_cpc.csv | Y33: 33 | Z33: 2026-09-25 02:00:22 | AA33: 2026-09-02T14:15:00 | AB33: false
A34: Google Ads | B34: All Brand - PMax PH | C34: 39035 | D34: 46267.56 | E34: Week 1 | F34: Included | G34: Website | H34: Website | I34: New | J34: Unpaid | K34: 19659.82 | L34: 0 | M34: 22019 | N34: 0 | O34: 0 | P34: 19659.82 | Q34: 0 | R34: 0 | S34: 2 | T34: 4 | U34: HANKOOK | V34: HANKOOK 205/55/R17 VENTUS PRIME 4 95V | W34: /complete-order?requestid=MzkwMzU= | X34: revenue_match/google_cpc.csv | Y34: 34 | Z34: 2026-09-25 02:00:22 | AA34: 2026-09-02T14:16:00 | AB34: false
A35: Google Ads | B35: Michelin - PMax PH | C35: 39065 | D35: 46267.885 | E35: Week 1 | F35: Included | G35: Website | I35: Fulfilled | J35: Fully Paid | K35: 42234.11 | L35: 42234.11 | M35: 47302.2 | N35: 1 | O35: 0 | P35: 0 | Q35: 0 | R35: 0 | S35: 2 | T35: 4 | U35: DUNLOP | V35: DUNLOP 265/50/R20 GRANDTREK PT5 107V | W35: /complete-order?requestid=MzkwNjU%3D | X35: revenue_match/google_cpc.csv | Y35: 35 | Z35: 2026-09-25 02:00:22 | AA35: 2026-09-22T11:23:00 | AB35: false
A36: Google Ads | B36: Michelin - PMax PH | C36: 38959 | D36: 46265.788 | E36: Outside / unknown | F36: Outside period | G36: Website | H36: Website | I36: Fulfilled | J36: Fully Paid | K36: 27053.57 | L36: 27053.57 | M36: 30300 | N36: 1 | O36: 0 | P36: 0 | Q36: 0 | R36: 0 | S36: 2 | T36: 4 | U36: MICHELIN | V36: MICHELIN 195/60/R16 PRIMACY 5 93V | W36: /complete-order?requestid=Mzg5NTk= | X36: revenue_match/google_cpc.csv | Y36: 36 | Z36: 2026-09-25 02:00:22 | AA36: 2026-09-22T16:14:00 | AB36: false
A37: Google Ads | B37: Michelin - PMax PH | C37: 39158 | D37: 46271.674 | E37: Week 1 | F37: Included | G37: Website | H37: Website | I37: Fulfilled | J37: Fully Paid | K37: 4517.77 | L37: 4517.77 | M37: 5059.9 | N37: 1 | O37: 0 | P37: 0 | Q37: 0 | R37: 0 | S37: 2 | T37: 2 | U37: CST | V37: CST 155/80/R13 MARQUIS MR61 79T | W37: /complete-order?requestid=MzkxNTg%3D | X37: revenue_match/google_cpc.csv | Y37: 37 | Z37: 2026-09-25 02:00:22 | AA37: 2026-09-11T18:53:00 | AB37: false
A38: Google Ads | B38: Gulongph Branding - PMax | C38: 39164 | D38: 46271.9 | E38: Week 1 | F38: Included | G38: Website | I38: New | J38: Unpaid | K38: 45796.43 | L38: 0 | M38: 51292 | N38: 0 | O38: 0 | P38: 45796.43 | Q38: 0 | R38: 0 | S38: 2 | T38: 5 | U38: HANKOOK | V38: HANKOOK 265/50/R20 DYNAPRO AT2 XTREME RF12 111T | W38: /complete-order?requestid=MzkxNjQ%3D | X38: revenue_match/google_cpc.csv | Y38: 38 | Z38: 2026-09-25 02:00:22 | AA38: 2026-09-07T13:17:00 | AB38: false
A39: Google Ads | B39: Gulongph Branding - PMax | C39: 39166 | D39: 46271.905 | E39: Week 1 | F39: Included | G39: Website | I39: Fulfilled | J39: Fully Paid | K39: 45796.43 | L39: 45796.43 | M39: 51292 | N39: 1 | O39: 0 | P39: 0 | Q39: 0 | R39: 0 | S39: 2 | T39: 5 | U39: HANKOOK | V39: HANKOOK 265/50/R20 DYNAPRO AT2 XTREME RF12 111T | W39: /complete-order?requestid=MzkxNjY%3D | X39: revenue_match/google_cpc.csv | Y39: 39 | Z39: 2026-09-25 02:00:22 | AA39: 2026-09-10T15:23:00 | AB39: false
A40: Google Ads | B40: Michelin - PMax PH | C40: 39169 | D40: 46271.919 | E40: Week 1 | F40: Included | G40: Website | I40: Fulfilled | J40: Fully Paid | K40: 8129.46 | L40: 8129.46 | M40: 9105 | N40: 1 | O40: 0 | P40: 0 | Q40: 0 | R40: 0 | S40: 2 | T40: 2 | U40: ARIVO | V40: ARIVO 215/70/R16C TRANSITO ARZ 6-X | W40: /complete-order?requestid=MzkxNjk%3D | X40: revenue_match/google_cpc.csv | Y40: 40 | Z40: 2026-09-25 02:00:22 | AA40: 2026-09-10T15:22:00 | AB40: false
A41: Google Ads | B41: SRC | All Brands | PH | C41: 39193 | D41: 46272.476 | E41: Week 1 | F41: Included | G41: Website | H41: Website | I41: Fulfilled | J41: Fully Paid | K41: 9157.68 | L41: 9157.68 | M41: 10256.6 | N41: 1 | O41: 0 | P41: 0 | Q41: 0 | R41: 0 | S41: 2 | T41: 4 | U41: ARIVO | V41: ARIVO 175/70/R14 PREMIO COMFORT 6 84T | W41: /complete-order?requestid=MzkxOTM%3D | X41: revenue_match/google_cpc.csv | Y41: 41 | Z41: 2026-09-25 02:00:22 | AA41: 2026-09-22T09:40:00 | AB41: false
A42: Google Ads | B42: SRC | All Brands | PH | C42: 39204 | D42: 46272.588 | E42: Week 1 | F42: Included | G42: Website | H42: CHAT | I42: Fulfilled | J42: Fully Paid | K42: 21785.71 | L42: 21785.71 | M42: 24400 | N42: 1 | O42: 0 | P42: 0 | Q42: 0 | R42: 0 | S42: 2 | T42: 4 | U42: BFGOODRICH | V42: BFGOODRICH 225/55/R18 ADVANTAGE TOURING 98H | W42: /complete-order?requestid=MzkyMDQ%3D | X42: revenue_match/google_cpc.csv | Y42: 42 | Z42: 2026-09-25 02:00:22 | AA42: 2026-09-14T08:32:00 | AB42: false
A43: Google Ads | B43: BFG - PMax (Traffic) | C43: 39260 | D43: 46273.936 | E43: Week 2 | F43: Included | G43: Website | H43: Website | I43: New | J43: Unpaid | K43: 24883.93 | L43: 0 | M43: 27870 | N43: 0 | O43: 0 | P43: 24883.93 | Q43: 0 | R43: 0 | S43: 2 | T43: 4 | U43: VREDESTEIN | V43: VREDESTEIN 235/55/R17 ULTRAC VORTI I | W43: /complete-order?requestid=MzkyNjA= | X43: revenue_match/google_cpc.csv | Y43: 43 | Z43: 2026-09-25 02:00:22 | AA43: 2026-09-09T13:06:00 | AB43: false
A44: Google Ads | B44: SRC | All Brands | PH | C44: 39265 | D44: 46274.4 | E44: Week 2 | F44: Included | G44: Website | H44: Website | I44: New | J44: Unpaid | K44: 7950.54 | L44: 0 | M44: 8904.6 | N44: 0 | O44: 0 | P44: 7950.54 | Q44: 0 | R44: 0 | S44: 2 | T44: 4 | U44: BLACK ARROW | V44: BLACK ARROW 185/65/R15 SUPER DART P16 88H | W44: /complete-order?requestid=MzkyNjU= | X44: revenue_match/google_cpc.csv | Y44: 44 | Z44: 2026-09-25 02:00:22 | AA44: 2026-09-11T11:20:00 | AB44: false
A45: Google Ads | B45: Michelin - PMax PH | C45: 39301 | D45: 46274.769 | E45: Week 2 | F45: Included | G45: Website | H45: Website | I45: Fulfilled | J45: Fully Paid | K45: 31281.07 | L45: 31281.07 | M45: 35034.8 | N45: 1 | O45: 0 | P45: 0 | Q45: 0 | R45: 0 | S45: 2 | T45: 4 | U45: HANKOOK | V45: HANKOOK 255/65/R17 DYNAPRO AT2 XTREME RF12 110T | W45: /complete-order?requestid=MzkzMDE= | X45: revenue_match/google_cpc.csv | Y45: 45 | Z45: 2026-09-25 02:00:22 | AA45: 2026-09-14T11:23:00 | AB45: false
A46: Google Ads | B46: Gulongph Branding - PMax | C46: 39372 | D46: 46276.383 | E46: Week 2 | F46: Included | G46: Website | I46: Pending | J46: Fully Paid | K46: 6370.54 | L46: 0 | M46: 7135 | N46: 0 | O46: 0 | P46: 6370.54 | Q46: 0 | R46: 0 | S46: 2 | T46: 1 | U46: YOKOHAMA | V46: YOKOHAMA 205/65/R16 BLUEARTH E70B 95H | W46: /complete-order?requestid=MzkzNzI%3D | X46: revenue_match/google_cpc.csv | Y46: 46 | Z46: 2026-09-25 02:00:22 | AA46: 2026-09-11T09:12:00 | AB46: false
A47: Google Ads | B47: Michelin - PMax PH | C47: 38981 | D47: 46266.536 | E47: Week 1 | F47: Included | G47: Website | H47: Website | I47: Fulfilled | J47: Fully Paid | K47: 9504.11 | L47: 9504.11 | M47: 10644.6 | N47: 1 | O47: 0 | P47: 0 | Q47: 0 | R47: 0 | S47: 2 | T47: 4 | U47: ARIVO | V47: ARIVO 185/60/R15 PREMIO COMFORT 6 88H | W47: /complete-order?requestid=Mzg5ODE%3D | X47: revenue_match/google_cpc.csv | Y47: 47 | Z47: 2026-09-25 02:00:22 | AA47: 2026-09-22T13:17:00 | AB47: false
A48: Google Ads | B48: BFG Advantage Touring – PMax PH | C48: 38969 | D48: 46266.444 | E48: Week 1 | F48: Included | G48: Website | I48: Fulfilled | J48: Fully Paid | K48: 6201.43 | L48: 6201.43 | M48: 6945.6 | N48: 1 | O48: 0 | P48: 0 | Q48: 0 | R48: 0 | S48: 1 | T48: 2 | U48: BFGOODRICH | V48: BFGOODRICH 185/55/R16 ADVANTAGE TOURING 87H | W48: /complete-order?requestid=Mzg5Njk= | X48: revenue_match/google_cpc.csv | Y48: 48 | Z48: 2026-09-25 02:00:22 | AA48: 2026-09-18T09:38:00 | AB48: false
A49: Google Ads | B49: Michelin - PMax PH | C49: 38985 | D49: 46266.56 | E49: Week 1 | F49: Included | G49: Website | H49: CALL | I49: Fulfilled | J49: Fully Paid | K49: 57267.86 | L49: 57267.86 | M49: 64140 | N49: 1 | O49: 0 | P49: 0 | Q49: 0 | R49: 0 | S49: 1 | T49: 4 | U49: MICHELIN | V49: MICHELIN 275/60/R20 PRIMACY SUV+ 115H | W49: /complete-order?requestid=Mzg5ODU= | X49: revenue_match/google_cpc.csv | Y49: 49 | Z49: 2026-09-25 02:00:22 | AA49: 2026-09-18T09:48:00 | AB49: false
A50: Google Ads | B50: BFG Advantage Touring – PMax PH | C50: 39468 | D50: 46278.907 | E50: Week 2 | F50: Included | G50: Website | I50: Cancelled | J50: Pending | K50: 10851.25 | L50: 0 | M50: 12153.4 | N50: 0 | O50: 1 | P50: 0 | Q50: 10851.25 | R50: 0 | S50: 1 | T50: 4 | U50: BFGOODRICH | V50: BFGOODRICH 175/65/R14 ADVANTAGE TOURING 82H | W50: /complete-order?requestid=Mzk0Njg= | X50: revenue_match/google_cpc.csv | Y50: 50 | Z50: 2026-09-25 02:00:22 | AA50: 2026-09-23T16:19:00 | AB50: false
A51: Google Ads | B51: Michelin - PMax PH | C51: 39471 | D51: 46279.328 | E51: Week 2 | F51: Included | G51: Website | H51: Website | I51: Cancelled | J51: Pending | K51: 43410.71 | L51: 0 | M51: 48620 | N51: 0 | O51: 1 | P51: 0 | Q51: 43410.71 | R51: 0 | S51: 1 | T51: 4 | U51: MICHELIN | V51: MICHELIN 255/45/R20 PILOT SPORT EV 105W | W51: /complete-order?requestid=Mzk0NzE= | X51: revenue_match/google_cpc.csv | Y51: 51 | Z51: 2026-09-25 02:00:22 | AA51: 2026-09-23T16:19:00 | AB51: false
A52: Google Ads | B52: All Brand - PMax PH | C52: 39589 | D52: 46281.712 | E52: Week 3 | F52: Included | G52: Website | H52: Website | I52: Cancelled | J52: Pending | K52: 11483.39 | L52: 0 | M52: 12861.4 | N52: 0 | O52: 1 | P52: 0 | Q52: 11483.39 | R52: 0 | S52: 1 | T52: 4 | U52: ARIVO | V52: ARIVO 195/60/R16 PREMIO COMFORT 6 89H | W52: /complete-order?requestid=Mzk1ODk= | X52: revenue_match/google_cpc.csv | Y52: 52 | Z52: 2026-09-25 02:00:22 | AA52: 2026-09-23T16:17:00 | AB52: false
A53: Google Ads | B53: BFG - PMax (Traffic) | C53: 39594 | D53: 46281.844 | E53: Week 3 | F53: Included | G53: Website | H53: Website | I53: Cancelled | J53: Pending | K53: 18497.32 | L53: 0 | M53: 20717 | N53: 0 | O53: 1 | P53: 0 | Q53: 18497.32 | R53: 0 | S53: 1 | T53: 4 | U53: BFGOODRICH | V53: BFGOODRICH 215/55/R16 ADVANTAGE TOURING 97V | W53: /complete-order?requestid=Mzk1OTQ= | X53: revenue_match/google_cpc.csv | Y53: 53 | Z53: 2026-09-25 02:00:22 | AA53: 2026-09-23T16:16:00 | AB53: false
A54: Google Ads | B54: All Brand - PMax PH | C54: 39601 | D54: 46281.949 | E54: Week 3 | F54: Included | G54: Website | I54: Cancelled | J54: Pending | K54: 7353.57 | L54: 0 | M54: 8236 | N54: 0 | O54: 1 | P54: 0 | Q54: 7353.57 | R54: 0 | S54: 1 | T54: 4 | U54: WESTLAKE | V54: WESTLAKE 165/65/R14 RP18 | W54: /complete-order?requestid=Mzk2MDE= | X54: revenue_match/google_cpc.csv | Y54: 54 | Z54: 2026-09-25 02:00:22 | AA54: 2026-09-23T16:16:00 | AB54: false
A55: Google Ads | B55: BFG Advantage Touring – PMax PH | C55: 39602 | D55: 46282.04 | E55: Week 3 | F55: Included | G55: Website | I55: Cancelled | J55: Pending | K55: 22643.04 | L55: 0 | M55: 25360.2 | N55: 0 | O55: 1 | P55: 0 | Q55: 22643.04 | R55: 0 | S55: 1 | T55: 4 | U55: ARIVO | V55: ARIVO 265/60/R18 TERRAMAX ARV PRO A/T | W55: /complete-order?requestid=Mzk2MDI= | X55: revenue_match/google_cpc.csv | Y55: 55 | Z55: 2026-09-25 02:00:22 | AA55: 2026-09-17T11:32:00 | AB55: false
A56: Google Ads | B56: All Brand - PMax PH | C56: 39656 | D56: 46283.404 | E56: Week 3 | F56: Included | G56: Website | H56: Website | I56: Fulfilled | J56: Partial Payment | K56: 11168.84 | L56: 11168.84 | M56: 12509.1 | N56: 1 | O56: 0 | P56: 0 | Q56: 0 | R56: 0 | S56: 1 | T56: 2 | U56: BRIDGESTONE | V56: BRIDGESTONE 185/55/R16 TURANZA ER370 83H | W56: /complete-order?requestid=Mzk2NTY= | X56: revenue_match/google_cpc.csv | Y56: 56 | Z56: 2026-09-25 02:00:22 | AA56: 2026-09-24T10:24:00 | AB56: false
A57: Google Ads | B57: All Brand - PMax PH | C57: 39813 | D57: 46287.753 | E57: Week 4 | F57: Included | G57: Website | H57: Website | I57: Cancelled | J57: Pending | K57: 19459.82 | L57: 0 | M57: 21795 | N57: 0 | O57: 1 | P57: 0 | Q57: 19459.82 | R57: 0 | S57: 1 | T57: 4 | U57: MICHELIN | V57: MICHELIN 175/70/R14 ENERGY XM2+ 88T | W57: /complete-order?requestid=Mzk4MTM= | X57: revenue_match/google_cpc.csv | Y57: 57 | Z57: 2026-09-25 02:00:22 | AA57: 2026-09-23T16:12:00 | AB57: false
A58: Google Ads | B58: All Brand - PMax PH | C58: 39023 | D58: 46267.401 | E58: Week 1 | F58: Included | G58: Website | H58: Website | I58: Fulfilled | J58: Fully Paid | K58: 32340.36 | L58: 32340.36 | M58: 36221.2 | N58: 1 | O58: 0 | P58: 0 | Q58: 0 | R58: 0 | S58: 1 | T58: 4 | U58: WESTLAKE | V58: WESTLAKE 305/35/R24 SA57 | W58: /complete-order?requestid=MzkwMjM= | X58: revenue_match/google_cpc.csv | Y58: 58 | Z58: 2026-09-25 02:00:22 | AA58: 2026-09-22T16:15:00 | AB58: false
A59: Google Ads | B59: Michelin - PMax PH | C59: 39121 | D59: 46269.668 | E59: Week 1 | F59: Included | G59: Website | I59: Cancelled | J59: Pending | K59: 7332.32 | L59: 0 | M59: 8212.2 | N59: 0 | O59: 1 | P59: 0 | Q59: 7332.32 | R59: 0 | S59: 1 | T59: 4 | U59: FRONWAY | V59: FRONWAY 175/65/R14 ECOGREEN ONE 82V | W59: /complete-order?requestid=MzkxMjE= | X59: revenue_match/google_cpc.csv | Y59: 59 | Z59: 2026-09-25 02:00:22 | AA59: 2026-09-10T16:31:00 | AB59: false
A60: Google Ads | B60: BFG - PMax (Traffic) | C60: 39132 | D60: 46269.93 | E60: Week 1 | F60: Included | G60: Website | I60: Cancelled | J60: Pending | K60: 9103.04 | L60: 0 | M60: 10195.4 | N60: 0 | O60: 1 | P60: 0 | Q60: 9103.04 | R60: 0 | S60: 1 | T60: 4 | U60: CHENGSHAN | V60: CHENGSHAN 205/55/R16 CSC-802 91V | W60: /complete-order?requestid=MzkxMzI= | X60: revenue_match/google_cpc.csv | Y60: 60 | Z60: 2026-09-25 02:00:22 | AA60: 2026-09-23T16:24:00 | AB60: false
A61: Google Ads | B61: BFG - PMax (Traffic) | C61: 39133 | D61: 46269.965 | E61: Week 1 | F61: Included | G61: Website | I61: Cancelled | J61: Pending | K61: 11772.5 | L61: 0 | M61: 13185.2 | N61: 0 | O61: 1 | P61: 0 | Q61: 11772.5 | R61: 0 | S61: 1 | T61: 4 | U61: LAUFENN | V61: LAUFENN 185/55/R16 S FIT EQ 83V | W61: /complete-order?requestid=MzkxMzM= | X61: revenue_match/google_cpc.csv | Y61: 61 | Z61: 2026-09-25 02:00:22 | AA61: 2026-09-10T15:08:00 | AB61: false
A62: Google Ads | B62: Michelin - PMax PH | C62: 39146 | D62: 46270.656 | E62: Week 1 | F62: Included | G62: Website | H62: Website | I62: Cancelled | J62: Pending | K62: 30293.21 | L62: 0 | M62: 33928.4 | N62: 0 | O62: 1 | P62: 0 | Q62: 30293.21 | R62: 0 | S62: 1 | T62: 4 | U62: BFGOODRICH | V62: BFGOODRICH 265/50/R20 ADVANTAGE TOURING 111T | W62: /complete-order?requestid=MzkxNDY= | X62: revenue_match/google_cpc.csv | Y62: 62 | Z62: 2026-09-25 02:00:22 | AA62: 2026-09-23T16:24:00 | AB62: false
A63: Google Ads | B63: Michelin - PMax PH | C63: 39171 | D63: 46271.947 | E63: Week 1 | F63: Included | G63: Website | H63: Website | I63: Cancelled | J63: Pending | K63: 32781.25 | L63: 0 | M63: 36715 | N63: 0 | O63: 1 | P63: 0 | Q63: 32781.25 | R63: 0 | S63: 1 | T63: 4 | U63: MICHELIN | V63: MICHELIN 215/55/R17 PRIMACY 5 94V | W63: /complete-order?requestid=MzkxNzE= | X63: revenue_match/google_cpc.csv | Y63: 63 | Z63: 2026-09-25 02:00:22 | AA63: 2026-09-10T14:38:00 | AB63: false
A64: Google Ads | B64: Michelin - PMax PH | C64: 39172 | D64: 46271.989 | E64: Week 1 | F64: Included | G64: Website | I64: Fulfilled | J64: Fully Paid | K64: 8185 | L64: 8185 | M64: 9167.2 | N64: 1 | O64: 0 | P64: 0 | Q64: 0 | R64: 0 | S64: 1 | T64: 4 | U64: WESTLAKE | V64: WESTLAKE 165/70/R14 RP36 | W64: /complete-order?requestid=MzkxNzI= | X64: revenue_match/google_cpc.csv | Y64: 64 | Z64: 2026-09-25 02:00:22 | AA64: 2026-09-10T15:33:00 | AB64: false
A65: Google Ads | B65: SRC | All Brands | PH | C65: 39213 | D65: 46272.717 | E65: Week 1 | F65: Included | G65: Website | H65: Website | I65: Fulfilled | J65: Fully Paid | K65: 2419.64 | L65: 2419.64 | M65: 2710 | N65: 1 | O65: 0 | P65: 0 | Q65: 0 | R65: 0 | S65: 1 | T65: 1 | U65: DURATURN | V65: DURATURN 195/60/R15 MOZZO ECO D3 88V | W65: /complete-order?requestid=MzkyMTM= | X65: revenue_match/google_cpc.csv | Y65: 65 | Z65: 2026-09-25 02:00:22 | AA65: 2026-09-14T15:26:00 | AB65: false
A66: Google Ads | B66: SRC | All Brands | PH | C66: 39219 | D66: 46272.864 | E66: Week 1 | F66: Included | G66: Website | I66: Cancelled | J66: Pending | K66: 21633.93 | L66: 0 | M66: 24230 | N66: 0 | O66: 1 | P66: 0 | Q66: 21633.93 | R66: 0 | S66: 1 | T66: 4 | U66: MICHELIN | V66: MICHELIN 205/60/R15 ENERGY XM2+ 91V | W66: /complete-order?requestid=MzkyMTk= | X66: revenue_match/google_cpc.csv | Y66: 66 | Z66: 2026-09-25 02:00:22 | AA66: 2026-09-23T16:23:00 | AB66: false
A67: Google Ads | B67: Gulongph Branding - PMax | C67: 39368 | D67: 46276.358 | E67: Week 2 | F67: Included | G67: Website | H67: Website | I67: Fulfilled | J67: Fully Paid | K67: 9710.36 | L67: 9710.36 | M67: 10875.6 | N67: 1 | O67: 0 | P67: 0 | Q67: 0 | R67: 0 | S67: 1 | T67: 2 | U67: ATLAS | V67: ATLAS 215/55/R18 A51 95V | W67: /complete-order?requestid=MzkzNjg= | X67: revenue_match/google_cpc.csv | Y67: 67 | Z67: 2026-09-25 02:00:22 | AA67: 2026-09-19T14:41:00 | AB67: false
A68: Google Ads | B68: BFG Advantage Touring – PMax PH | C68: 39396 | D68: 46276.749 | E68: Week 2 | F68: Included | G68: Website | H68: Website | I68: Cancelled | J68: Pending | K68: 13805.71 | L68: 0 | M68: 15462.4 | N68: 0 | O68: 1 | P68: 0 | Q68: 13805.71 | R68: 0 | S68: 1 | T68: 4 | U68: YOKOHAMA | V68: YOKOHAMA 175/65/R14 BLUEARTH ES32 82T | W68: /complete-order?requestid=MzkzOTY= | X68: revenue_match/google_cpc.csv | Y68: 68 | Z68: 2026-09-25 02:00:22 | AA68: 2026-09-23T16:21:00 | AB68: false
A69: Google Ads | B69: All Brand - PMax PH | C69: 39397 | D69: 46276.847 | E69: Week 2 | F69: Included | G69: Website | H69: Website | I69: Cancelled | J69: Pending | K69: 13348.21 | L69: 0 | M69: 14950 | N69: 0 | O69: 1 | P69: 0 | Q69: 13348.21 | R69: 0 | S69: 1 | T69: 4 | U69: BFGOODRICH | V69: BFGOODRICH 185/55/R15 ADVANTAGE TOURING 86V | W69: /complete-order?requestid=MzkzOTc= | X69: revenue_match/google_cpc.csv | Y69: 69 | Z69: 2026-09-25 02:00:22 | AA69: 2026-09-23T16:21:00 | AB69: false
A70: Direct & Organic | B70: (direct) | C70: 39592 | D70: 46281.821 | E70: Week 3 | F70: Included | G70: Website | H70: Website | I70: Cancelled | J70: Pending | K70: 12025.18 | L70: 0 | M70: 13468.2 | N70: 0 | O70: 1 | P70: 0 | Q70: 12025.18 | R70: 0 | S70: 3 | T70: 2 | U70: BFGOODRICH | V70: BFGOODRICH 245/70/R16 ADVANTAGE TOURING 111T | W70: /complete-order?requestid=Mzk1OTI= | X70: direct_and_organic_revenue/direct_and_organic.csv | Y70: 2 | Z70: 2026-09-25 02:00:22 | AA70: 2026-09-23T16:17:00 | AB70: false
A71: Direct & Organic | B71: (organic) | C71: 39200 | D71: 46272.497 | E71: Week 1 | F71: Included | G71: Fb | H71: CHAT | I71: Fulfilled | J71: Fully Paid | K71: 14615.36 | L71: 14615.36 | M71: 16369.2 | N71: 1 | O71: 0 | P71: 0 | Q71: 0 | R71: 0 | S71: 2 | T71: 4 | U71: ARIVO | V71: ARIVO 215/65/R16 PREMIO COMFORT 6 98H | W71: /complete-order?requestid=MzkyMDA= | X71: direct_and_organic_revenue/direct_and_organic.csv | Y71: 3 | Z71: 2026-09-25 02:00:22 | AA71: 2026-09-23T10:58:00 | AB71: false
A72: Direct & Organic | B72: (direct) | C72: 39390 | D72: 46276.688 | E72: Week 2 | F72: Included | G72: Website | H72: Website | I72: Fulfilled | J72: Fully Paid | K72: 8540.18 | L72: 8540.18 | M72: 9565 | N72: 1 | O72: 0 | P72: 0 | Q72: 0 | R72: 0 | S72: 2 | T72: 1 | U72: DUNLOP | V72: DUNLOP 235/60/R17 SP LT30A 109T | W72: /complete-order?requestid=MzkzOTA%3D | X72: direct_and_organic_revenue/direct_and_organic.csv | Y72: 4 | Z72: 2026-09-25 02:00:22 | AA72: 2026-09-19T14:32:00 | AB72: false
A73: Direct & Organic | B73: (direct) | C73: 38990 | D73: 46266.611 | E73: Week 1 | F73: Included | G73: Fb | H73: CHAT | I73: Fulfilled | J73: Fully Paid | K73: 4114.73 | L73: 4114.73 | M73: 4608.5 | N73: 1 | O73: 0 | P73: 0 | Q73: 0 | R73: 0 | S73: 2 | T73: 2 | U73: WESTLAKE | V73: WESTLAKE 165/60/R14 RP36 | W73: /complete-order?requestid=Mzg5OTA= | X73: direct_and_organic_revenue/direct_and_organic.csv | Y73: 5 | Z73: 2026-09-25 02:00:22 | AA73: 2026-09-23T10:59:00 | AB73: false
A74: Direct & Organic | B74: (direct) | C74: 38996 | D74: 46266.717 | E74: Week 1 | F74: Included | G74: Fb | H74: CHAT | I74: Fulfilled | J74: Fully Paid | K74: 8333.21 | L74: 8333.21 | M74: 9333.2 | N74: 1 | O74: 0 | P74: 0 | Q74: 0 | R74: 0 | S74: 2 | T74: 4 | U74: WESTLAKE | V74: WESTLAKE 165/65/R13 RP36 | W74: /complete-order?requestid=Mzg5OTY= | X74: direct_and_organic_revenue/direct_and_organic.csv | Y74: 6 | Z74: 2026-09-25 02:00:22 | AA74: 2026-09-22T11:57:00 | AB74: false
A75: Direct & Organic | B75: (organic) | C75: 39401 | D75: 46277.012 | E75: Week 2 | F75: Included | G75: Website | I75: New | J75: Unpaid | K75: 12357.14 | L75: 0 | M75: 13840 | N75: 0 | O75: 0 | P75: 12357.14 | Q75: 0 | R75: 0 | S75: 2 | T75: 4 | U75: APOLLO | V75: APOLLO 185/70/R13 AMAZER XP 86H | W75: /complete-order?requestid=Mzk0MDE%3D | X75: direct_and_organic_revenue/direct_and_organic.csv | Y75: 7 | Z75: 2026-09-25 02:00:22 | AA75: 2026-09-12T11:46:00 | AB75: false
A76: Direct & Organic | B76: (organic) | C76: 39404 | D76: 46277.046 | E76: Week 2 | F76: Included | G76: Website | I76: Fulfilled | J76: Fully Paid | K76: 22825 | L76: 22825 | M76: 25564 | N76: 1 | O76: 0 | P76: 0 | Q76: 0 | R76: 0 | S76: 2 | T76: 4 | U76: YOKOHAMA | V76: YOKOHAMA 205/50/R16 ADVAN FLEVA V701 87V | W76: /complete-order?requestid=Mzk0MDQ= | X76: direct_and_organic_revenue/direct_and_organic.csv | Y76: 8 | Z76: 2026-09-25 02:00:22 | AA76: 2026-09-21T08:39:00 | AB76: false
A77: Direct & Organic | B77: (direct) | C77: 39406 | D77: 46277.347 | E77: Week 2 | F77: Included | G77: Website | I77: New | J77: Unpaid | K77: 12055.71 | L77: 0 | M77: 13502.4 | N77: 0 | O77: 0 | P77: 12055.71 | Q77: 0 | R77: 0 | S77: 2 | T77: 4 | U77: HANKOOK | V77: HANKOOK 185/65/R15 KINERGY ECO2 88T | W77: /complete-order?requestid=Mzk0MDY= | X77: direct_and_organic_revenue/direct_and_organic.csv | Y77: 9 | Z77: 2026-09-25 02:00:22 | AA77: 2026-09-14T17:09:00 | AB77: false
A78: Direct & Organic | B78: (direct) | C78: 39407 | D78: 46277.358 | E78: Week 2 | F78: Included | G78: Website | H78: Website | I78: New | J78: Unpaid | K78: 12055.71 | L78: 0 | M78: 13502.4 | N78: 0 | O78: 0 | P78: 12055.71 | Q78: 0 | R78: 0 | S78: 2 | T78: 4 | U78: HANKOOK | V78: HANKOOK 185/65/R15 KINERGY ECO2 88T | W78: /complete-order?requestid=Mzk0MDc= | X78: direct_and_organic_revenue/direct_and_organic.csv | Y78: 10 | Z78: 2026-09-25 02:00:22 | AA78: 2026-09-14T16:58:00 | AB78: false
A79: Direct & Organic | B79: (organic) | C79: 39409 | D79: 46277.397 | E79: Week 2 | F79: Included | G79: Website | I79: Fulfilled | J79: Fully Paid | K79: 19022.86 | L79: 19022.86 | M79: 21305.6 | N79: 1 | O79: 0 | P79: 0 | Q79: 0 | R79: 0 | S79: 2 | T79: 4 | U79: COMFORSER | V79: COMFORSER 235/65/R17 CF2000 H/T 108H | W79: /complete-order?requestid=Mzk0MDk%3D | X79: direct_and_organic_revenue/direct_and_organic.csv | Y79: 11 | Z79: 2026-09-25 02:00:22 | AA79: 2026-09-24T15:03:00 | AB79: false
A80: Direct & Organic | B80: (organic) | C80: 39417 | D80: 46277.497 | E80: Week 2 | F80: Included | G80: Website | H80: Website | I80: Fulfilled | J80: Fully Paid | K80: 13348.21 | L80: 13348.21 | M80: 14950 | N80: 1 | O80: 0 | P80: 0 | Q80: 0 | R80: 0 | S80: 2 | T80: 4 | U80: BFGOODRICH | V80: BFGOODRICH 185/55/R15 ADVANTAGE TOURING 86V | W80: /complete-order?requestid=Mzk0MTc= | X80: direct_and_organic_revenue/direct_and_organic.csv | Y80: 12 | Z80: 2026-09-25 02:00:22 | AA80: 2026-09-22T11:20:00 | AB80: false
A81: Direct & Organic | B81: (organic) | C81: 39433 | D81: 46277.692 | E81: Week 2 | F81: Included | G81: Website | H81: Website | I81: New | J81: Unpaid | K81: 12357.14 | L81: 0 | M81: 13840 | N81: 0 | O81: 0 | P81: 12357.14 | Q81: 0 | R81: 0 | S81: 2 | T81: 4 | U81: APOLLO | V81: APOLLO 185/70/R13 AMAZER XP 86H | W81: /complete-order?requestid=Mzk0MzM%3D | X81: direct_and_organic_revenue/direct_and_organic.csv | Y81: 13 | Z81: 2026-09-25 02:00:22 | AA81: 2026-09-14T11:23:00 | AB81: false
A82: Direct & Organic | B82: (direct) | C82: 39445 | D82: 46277.703 | E82: Week 2 | F82: Included | G82: Website | I82: Fulfilled | J82: Fully Paid | K82: 20857.14 | L82: 20857.14 | M82: 23360 | N82: 1 | O82: 0 | P82: 0 | Q82: 0 | R82: 0 | S82: 2 | T82: 5 | U82: APOLLO | V82: APOLLO 205/65/R15 ALNAC 4G 94H | W82: /complete-order?requestid=Mzk0NDU%3D | X82: direct_and_organic_revenue/direct_and_organic.csv | Y82: 14 | Z82: 2026-09-25 02:00:22 | AA82: 2026-09-22T09:22:00 | AB82: false
A83: Direct & Organic | B83: (direct) | C83: 39451 | D83: 46277.75 | E83: Week 2 | F83: Included | G83: Website | H83: Website | I83: Fulfilled | J83: Fully Paid | K83: 12384.11 | L83: 12384.11 | M83: 13870.2 | N83: 1 | O83: 0 | P83: 0 | Q83: 0 | R83: 0 | S83: 2 | T83: 4 | U83: WESTLAKE | V83: WESTLAKE 195/60/R16 RP36 | W83: /complete-order?requestid=Mzk0NTE%3D | X83: direct_and_organic_revenue/direct_and_organic.csv | Y83: 15 | Z83: 2026-09-25 02:00:22 | AA83: 2026-09-19T16:18:00 | AB83: false
A84: Direct & Organic | B84: (organic) | C84: 39455 | D84: 46277.871 | E84: Week 2 | F84: Included | G84: Website | I84: For Return | J84: Partial Payment | K84: 31301.07 | L84: 0 | M84: 35057.2 | N84: 0 | O84: 0 | P84: 0 | Q84: 0 | R84: 31301.07 | S84: 2 | T84: 4 | U84: HANKOOK | V84: HANKOOK 265/60/R18 DYNAPRO AT2 XTREME RF12 114T | W84: /complete-order?requestid=Mzk0NTU= | X84: direct_and_organic_revenue/direct_and_organic.csv | Y84: 16 | Z84: 2026-09-25 02:00:22 | AA84: 2026-09-24T14:06:00 | AB84: false
A85: Direct & Organic | B85: (direct) | C85: 39457 | D85: 46278.329 | E85: Week 2 | F85: Included | G85: Website | H85: Website | I85: Fulfilled | J85: Fully Paid | K85: 53638.39 | L85: 53638.39 | M85: 60075 | N85: 1 | O85: 0 | P85: 0 | Q85: 0 | R85: 0 | S85: 2 | T85: 4 | U85: MICHELIN | V85: MICHELIN 225/45/ZR19 PILOT SPORT 5 96Y XL TL | W85: /complete-order?requestid=Mzk0NTc%3D | X85: direct_and_organic_revenue/direct_and_organic.csv | Y85: 17 | Z85: 2026-09-25 02:00:22 | AA85: 2026-09-19T16:22:00 | AB85: false
A86: Direct & Organic | B86: (direct) | C86: 39464 | D86: 46278.611 | E86: Week 2 | F86: Included | G86: Website | I86: Fulfilled | J86: Fully Paid | K86: 4372.77 | L86: 4372.77 | M86: 4897.5 | N86: 1 | O86: 0 | P86: 0 | Q86: 0 | R86: 0 | S86: 2 | T86: 2 | U86: WESTLAKE | V86: WESTLAKE 175/55/R15 RP26 | W86: /complete-order?requestid=Mzk0NjQ= | X86: direct_and_organic_revenue/direct_and_organic.csv | Y86: 18 | Z86: 2026-09-25 02:00:22 | AA86: 2026-09-21T11:49:00 | AB86: false
A87: Direct & Organic | B87: (direct) | C87: 39476 | D87: 46279.398 | E87: Week 2 | F87: Included | G87: Website | I87: New | J87: Unpaid | K87: 4673.3 | L87: 0 | M87: 5234.1 | N87: 0 | O87: 0 | P87: 4673.3 | Q87: 0 | R87: 0 | S87: 2 | T87: 2 | U87: ARIVO | V87: ARIVO 185/60/R15 PREMIO COMFORT 6 88H | W87: /complete-order?requestid=Mzk0NzY%3D | X87: direct_and_organic_revenue/direct_and_organic.csv | Y87: 19 | Z87: 2026-09-25 02:00:22 | AA87: 2026-09-14T11:17:00 | AB87: false
A88: Direct & Organic | B88: (direct) | C88: 39477 | D88: 46279.417 | E88: Week 2 | F88: Included | G88: Website | I88: Cancelled | J88: Pending | K88: 4851.88 | L88: 0 | M88: 5434.1 | N88: 0 | O88: 1 | P88: 0 | Q88: 4851.88 | R88: 0 | S88: 2 | T88: 2 | U88: ARIVO | V88: ARIVO 185/60/R15 PREMIO COMFORT 6 88H | W88: /complete-order?requestid=Mzk0Nzc= | X88: direct_and_organic_revenue/direct_and_organic.csv | Y88: 20 | Z88: 2026-09-25 02:00:22 | AA88: 2026-09-17T13:55:00 | AB88: false
A89: Direct & Organic | B89: (direct) | C89: 39482 | D89: 46279.435 | E89: Week 2 | F89: Included | G89: Website | H89: Website | I89: Fulfilled | J89: Fully Paid | K89: 11102.32 | L89: 11102.32 | M89: 12434.6 | N89: 1 | O89: 0 | P89: 0 | Q89: 0 | R89: 0 | S89: 2 | T89: 4 | U89: ARIVO | V89: ARIVO 185/55/R16 PREMIO COMFORT 6 83V | W89: /complete-order?requestid=Mzk0ODI= | X89: direct_and_organic_revenue/direct_and_organic.csv | Y89: 21 | Z89: 2026-09-25 02:00:22 | AA89: 2026-09-22T09:22:00 | AB89: false
A90: Direct & Organic | B90: (organic) | C90: 39499 | D90: 46279.701 | E90: Week 2 | F90: Included | G90: Website | H90: Website | I90: Fulfilled | J90: Fully Paid | K90: 18901.79 | L90: 18901.79 | M90: 21170 | N90: 1 | O90: 0 | P90: 0 | Q90: 0 | R90: 0 | S90: 2 | T90: 4 | U90: MICHELIN | V90: MICHELIN 185/60/R15 ENERGY XM2+ 88H | W90: /complete-order?requestid=Mzk0OTk= | X90: direct_and_organic_revenue/direct_and_organic.csv | Y90: 22 | Z90: 2026-09-25 02:00:22 | AA90: 2026-09-16T15:08:00 | AB90: false
A91: Direct & Organic | B91: (direct) | C91: 39525 | D91: 46280.393 | E91: Week 3 | F91: Included | G91: Fb | H91: CHAT | I91: Fulfilled | J91: Fully Paid | K91: 5424.11 | L91: 5424.11 | M91: 6075 | N91: 1 | O91: 0 | P91: 0 | Q91: 0 | R91: 0 | S91: 2 | T91: 1 | U91: YOKOHAMA | V91: YOKOHAMA 185/55/R16 BLUEARTH ES32 83V | W91: /complete-order?requestid=Mzk1MjU= | X91: direct_and_organic_revenue/direct_and_organic.csv | Y91: 23 | Z91: 2026-09-25 02:00:22 | AA91: 2026-09-19T20:03:00 | AB91: false
A92: Direct & Organic | B92: (direct) | C92: 39531 | D92: 46280.424 | E92: Week 3 | F92: Included | G92: Fb | H92: CHAT | I92: Fulfilled | J92: Fully Paid | K92: 28476.43 | L92: 28476.43 | M92: 31893.6 | N92: 1 | O92: 0 | P92: 0 | Q92: 0 | R92: 0 | S92: 2 | T92: 4 | U92: DUNLOP | V92: DUNLOP 215/65/R16 ENASAVE EC300+ 98S | W92: /complete-order?requestid=Mzk1MzE= | X92: direct_and_organic_revenue/direct_and_organic.csv | Y92: 24 | Z92: 2026-09-25 02:00:22 | AA92: 2026-09-22T09:06:00 | AB92: false
A93: Direct & Organic | B93: (direct) | C93: 39555 | D93: 46280.898 | E93: Week 3 | F93: Included | G93: Website | H93: Website | I93: Fulfilled | J93: Fully Paid | K93: 4673.3 | L93: 4673.3 | M93: 5234.1 | N93: 1 | O93: 0 | P93: 0 | Q93: 0 | R93: 0 | S93: 2 | T93: 2 | U93: ARIVO | V93: ARIVO 185/60/R15 PREMIO COMFORT 6 88H | W93: /complete-order?requestid=Mzk1NTU= | X93: direct_and_organic_revenue/direct_and_organic.csv | Y93: 25 | Z93: 2026-09-25 02:00:22 | AA93: 2026-09-23T13:46:00 | AB93: false
A94: Direct & Organic | B94: (direct) | C94: 39558 | D94: 46280.944 | E94: Week 3 | F94: Included | G94: Website | I94: Fulfilled | J94: Fully Paid | K94: 14979.64 | L94: 14979.64 | M94: 16777.2 | N94: 1 | O94: 0 | P94: 0 | Q94: 0 | R94: 0 | S94: 2 | T94: 4 | U94: BRIDGESTONE | V94: BRIDGESTONE 175/65/R14 ECOPIA EP150 82H | W94: /complete-order?requestid=Mzk1NTg= | X94: direct_and_organic_revenue/direct_and_organic.csv | Y94: 26 | Z94: 2026-09-25 02:00:22 | AA94: 2026-09-21T20:10:00 | AB94: false
A95: Direct & Organic | B95: (organic) | C95: 39563 | D95: 46281.076 | E95: Week 3 | F95: Included | G95: Website | H95: Website | I95: For Refund | J95: For Refund | K95: 13700.89 | L95: 0 | M95: 15345 | N95: 0 | O95: 0 | P95: 0 | Q95: 0 | R95: 13700.89 | S95: 2 | T95: 1 | U95: BRIDGESTONE | V95: BRIDGESTONE 225/45/R19 TURANZA T001 92W | W95: /complete-order?requestid=Mzk1NjM%3D | X95: direct_and_organic_revenue/direct_and_organic.csv | Y95: 27 | Z95: 2026-09-25 02:00:22 | AA95: 2026-09-17T16:57:00 | AB95: false
A96: Direct & Organic | B96: (direct) | C96: 39571 | D96: 46281.476 | E96: Week 3 | F96: Included | G96: Website | I96: Cancelled | J96: Pending | K96: 15181.61 | L96: 0 | M96: 17003.4 | N96: 0 | O96: 1 | P96: 0 | Q96: 15181.61 | R96: 0 | S96: 2 | T96: 4 | U96: BFGOODRICH | V96: BFGOODRICH 205/65/R15 ADVANTAGE TOURING 99H | W96: /complete-order?requestid=Mzk1NzE= | X96: direct_and_organic_revenue/direct_and_organic.csv | Y96: 28 | Z96: 2026-09-25 02:00:22 | AA96: 2026-09-23T16:17:00 | AB96: false
A97: Direct & Organic | B97: (organic) | C97: 39579 | D97: 46281.517 | E97: Week 3 | F97: Included | G97: Website | I97: Fulfilled | J97: Fully Paid | K97: 29078.57 | L97: 29078.57 | M97: 32568 | N97: 1 | O97: 0 | P97: 0 | Q97: 0 | R97: 0 | S97: 2 | T97: 4 | U97: HANKOOK | V97: HANKOOK 265/65/R17 DYNAPRO AT2 XTREME RF12 112T | W97: /complete-order?requestid=Mzk1Nzk%3D | X97: direct_and_organic_revenue/direct_and_organic.csv | Y97: 29 | Z97: 2026-09-25 02:00:22 | AA97: 2026-09-21T20:23:00 | AB97: false
A98: Direct & Organic | B98: (direct) | C98: 39584 | D98: 46281.627 | E98: Week 3 | F98: Included | G98: Website | H98: Website | I98: New | J98: Unpaid | K98: 18994.46 | L98: 0 | M98: 21273.8 | N98: 0 | O98: 0 | P98: 18994.46 | Q98: 0 | R98: 0 | S98: 2 | T98: 4 | U98: BFGOODRICH | V98: BFGOODRICH 215/45/R17 ADVANTAGE TOURING 91V | W98: /complete-order?requestid=Mzk1ODQ= | X98: direct_and_organic_revenue/direct_and_organic.csv | Y98: 30 | Z98: 2026-09-25 02:00:22 | AA98: 2026-09-17T11:33:00 | AB98: false
A99: Direct & Organic | B99: (direct) | C99: 39593 | D99: 46281.828 | E99: Week 3 | F99: Included | G99: Website | H99: Website | I99: New | J99: Unpaid | K99: 15083.75 | L99: 0 | M99: 16893.8 | N99: 0 | O99: 0 | P99: 15083.75 | Q99: 0 | R99: 0 | S99: 2 | T99: 4 | U99: BFGOODRICH | V99: BFGOODRICH 195/50/R16 ADVANTAGE TOURING 88V | W99: /complete-order?requestid=Mzk1OTM= | X99: direct_and_organic_revenue/direct_and_organic.csv | Y99: 31 | Z99: 2026-09-25 02:00:22 | AA99: 2026-09-17T11:39:00 | AB99: false
A100: Direct & Organic | B100: (direct) | C100: 39600 | D100: 46281.945 | E100: Week 3 | F100: Included | G100: Website | H100: Website | I100: Fulfilled | J100: Fully Paid | K100: 22553.75 | L100: 22553.75 | M100: 25260.2 | N100: 1 | O100: 0 | P100: 0 | Q100: 0 | R100: 0 | S100: 2 | T100: 4 | U100: ARIVO | V100: ARIVO 265/60/R18 TERRAMAX ARV PRO A/T | W100: /complete-order?requestid=Mzk2MDA= | X100: direct_and_organic_revenue/direct_and_organic.csv | Y100: 32 | Z100: 2026-09-25 02:00:22 | AA100: 2026-09-21T20:21:00 | AB100: false
...

Sheet Original Google Ads
A1: Session campaign | B1: Page path + query string | C1: Ecommerce purchases
A2: All Brand - PMax PH | B2: /complete-order?requestid=Mzk3NzM%3D | C2: 4
A3: BFG Advantage Touring – PMax PH | B3: /complete-order?requestid=MzkxNDM%3D | C3: 2
A4: MICHELIN - PMAX (Traffic) | B4: /complete-order?requestid=MzkzOTU%3D | C4: 2
A5: Michelin - PMax PH | B5: /complete-order?requestid=Mzk0OTc= | C5: 2
A6: Michelin - PMax PH | B6: /complete-order?requestid=Mzk1MDc%3D | C6: 2
A7: BFG Advantage Touring – PMax PH | B7: /complete-order?requestid=Mzk1NDI%3D | C7: 2
A8: All Brand - PMax PH | B8: /complete-order?requestid=Mzk1Njg= | C8: 2
A9: SRC | All Brands | PH | B9: /complete-order?requestid=Mzk1NzA= | C9: 2
A10: Michelin - PMax PH | B10: /complete-order?requestid=Mzk1ODE= | C10: 2
A11: Michelin - PMax PH | B11: /complete-order?requestid=Mzk1ODM= | C11: 2
A12: All Brand - PMax PH | B12: /complete-order?requestid=Mzk1ODY= | C12: 2
... A69: All Brand - PMax PH | B69: /complete-order?requestid=MzkzOTc= | C69: 1

Sheet Original Direct Organic
A1: Session campaign | B1: Page path + query string | C1: Ecommerce purchases
A2: (direct) | B2: /complete-order?requestid=Mzk1OTI= | C2: 3
A3: (organic) | B3: /complete-order?requestid=MzkyMDA= | C3: 2
A4: (direct) | B4: /complete-order?requestid=MzkzOTA%3D | C4: 2
A5: (direct) | B5: /complete-order?requestid=Mzg5OTA= | C5: 2
A6: (direct) | B6: /complete-order?requestid=Mzg5OTY= | C6: 2
A7: (organic) | B7: /complete-order?requestid=Mzk0MDE%3D | C7: 2
A8: (organic) | B8: /complete-order?requestid=Mzk0MDQ= | C8: 2
A9: (direct) | B9: /complete-order?requestid=Mzk0MDY= | C9: 2
A10: (direct) | B10: /complete-order?requestid=Mzk0MDc= | C10: 2
A11: (organic) | B11: /complete-order?requestid=Mzk0MDk%3D | C11: 2
A12: (organic) | B12: /complete-order?requestid=Mzk0MTc= | C12: 2
... A172: (organic) | B172: /complete-order?requestid=MzkzODI= | C172: 1

Sheet Original Referral
A1: Session campaign | B1: Page path + query string | C1: Ecommerce purchases
A2: (referral) | B2: /complete-order?requestid=Mzk0NDg%3D | C2: 2
A3: (referral) | B3: /complete-order?requestid=Mzk0NjA= | C3: 2
A4: (referral) | B4: /complete-order?requestid=Mzk0ODU%3D | C4: 2
A5: (referral) | B5: /complete-order?requestid=Mzk0OTA%3D | C5: 2
A6: (referral) | B6: /complete-order?requestid=Mzk3MjM%3D | C6: 2
A7: (referral) | B7: /complete-order?requestid=MzkwNzU%3D | C7: 2
A8: (referral) | B8: /complete-order?requestid=MzkxMDE%3D | C8: 2
A9: (referral) | B9: /complete-order?requestid=MzkxMjU= | C9: 2
A10: (referral) | B10: /complete-order?requestid=MzkyOTM%3D | C10: 2
A11: (referral) | B11: /complete-order?requestid=MzkzNjQ%3D | C11: 2
A12: (referral) | B12: /complete-order?requestid=MzkzNjk= | C12: 2
... A29: (referral) | B29: /complete-order?requestid=MzkzOTI= | C29: 1

Sheet Backend Extract
A1: _ingest_loaded_at | B1: brand | C1: customer_source_raw | D1: customer_type_norm | E1: customer_type_raw | F1: date_updated | G1: gross_sales_amount | H1: is_excluded_test_order | I1: is_fulfilled_order | J1: is_fulfillment_success_order | K1: is_non_cancelled_order | L1: net_sales_amount | M1: order_date | N1: order_id | O1: order_status_raw | P1: payment_status_raw | Q1: quantity_int | R1: sku
A2: 2026-09-25 02:00:22 | B2: MICHELIN | C2: CALL | D2: fb | E2: Fb | F2: 2026-09-18T09:53:00 | G2: 60675 | H2: false | I2: true | J2: true | K2: true | L2: 54174.11 | M2: 2026-08-26T14:54:00 | N2: 38805 | O2: Fulfilled | P2: Fully Paid | Q2: 4 | R2: MICHELIN 225/45/ZR19 PILOT SPORT 5 96Y XL TL
A3: 2026-09-25 02:00:22 | B3: MICHELIN | C3: Website | D3: website | E3: Website | F3: 2026-09-22T16:14:00 | G3: 30300 | H3: false | I3: true | J3: true | K3: true | L3: 27053.57 | M3: 2026-08-31T18:55:00 | N3: 38959 | O3: Fulfilled | P3: Fully Paid | Q3: 4 | R3: MICHELIN 195/60/R16 PRIMACY 5 93V
A4: 2026-09-25 02:00:22 | B4: VREDESTEIN | C4: Website | D4: website | E4: Website | F4: 2026-09-07T15:52:00 | G4: 29175 | H4: false | I4: true | J4: true | K4: true | L4: 26049.11 | M4: 2026-09-01T10:13:00 | N4: 38967 | O4: Fulfilled | P4: Fully Paid | Q4: 4 | R4: VREDESTEIN 265/60/R18 PINZA AT 110H
A5: 2026-09-25 02:00:22 | B5: BFGOODRICH | D5: website | E5: Website | F5: 2026-09-18T09:38:00 | G5: 6945.6 | H5: false | I5: true | J5: true | K5: true | L5: 6201.43 | M5: 2026-09-01T10:39:00 | N5: 38969 | O5: Fulfilled | P5: Fully Paid | Q5: 2 | R5: BFGOODRICH 185/55/R16 ADVANTAGE TOURING 87H
A6: 2026-09-25 02:00:22 | B6: MICHELIN | C6: Website | D6: website | E6: Website | F6: 2026-09-18T09:42:00 | G6: 20190 | H6: false | I6: true | J6: true | K6: true | L6: 18026.79 | M6: 2026-09-01T10:49:00 | N6: 38970 | O6: Fulfilled | P6: Fully Paid | Q6: 4 | R6: MICHELIN 185/60/R14 ENERGY XM2+ 82H
A7: 2026-09-25 02:00:22 | B7: ARIVO | C7: Website | D7: website | E7: Website | F7: 2026-09-22T13:17:00 | G7: 10644.6 | H7: false | I7: true | J7: true | K7: true | L7: 9504.11 | M7: 2026-09-01T12:52:00 | N7: 38981 | O7: Fulfilled | P7: Fully Paid | Q7: 4 | R7: ARIVO 185/60/R15 PREMIO COMFORT 6 88H
A8: 2026-09-25 02:00:22 | B8: MICHELIN | C8: CALL | D8: website | E8: Website | F8: 2026-09-18T09:48:00 | G8: 64140 | H8: false | I8: true | J8: true | K8: true | L8: 57267.86 | M8: 2026-09-01T13:26:00 | N8: 38985 | O8: Fulfilled | P8: Fully Paid | Q8: 4 | R8: MICHELIN 275/60/R20 PRIMACY SUV+ 115H
A9: 2026-09-25 02:00:22 | B9: WESTLAKE | C9: CHAT | D9: fb | E9: Fb | F9: 2026-09-23T10:59:00 | G9: 4608.5 | H9: false | I9: true | J9: true | K9: true | L9: 4114.73 | M9: 2026-09-01T14:40:00 | N9: 38990 | O9: Fulfilled | P9: Fully Paid | Q9: 2 | R9: WESTLAKE 165/60/R14 RP36
A10: 2026-09-25 02:00:22 | B10: BRIDGESTONE | D10: website | E10: Website | F10: 2026-09-23T16:30:00 | G10: 4240 | H10: false | I10: false | J10: false | K10: false | L10: 3785.71 | M10: 2026-09-01T15:30:00 | N10: 38993 | O10: Cancelled | P10: Pending | Q10: 1 | R10: BRIDGESTONE 175/65/R14 ECOPIA EP150 82H
A11: 2026-09-25 02:00:22 | B11: WESTLAKE | C11: CHAT | D11: fb | E11: Fb | F11: 2026-09-22T11:57:00 | G11: 9333.2 | H11: false | I11: true | J11: true | K11: true | L11: 8333.21 | M11: 2026-09-01T17:12:00 | N11: 38996 | O11: Fulfilled | P11: Fully Paid | Q11: 4 | R11: WESTLAKE 165/65/R13 RP36
A12: 2026-09-25 02:00:22 | B12: BFGOODRICH | C12: Website | D12: website | E12: Website | F12: 2026-09-23T16:26:00 | G12: 14950 | H12: false | I12: false | J12: false | K12: false | L12: 13348.21 | M12: 2026-09-01T17:31:00 | N12: 38997 | O12: Cancelled | P12: Pending | Q12: 4 | R12: BFGOODRICH 185/55/R15 ADVANTAGE TOURING 86V
A13: 2026-09-25 02:00:22 | B13: ARIVO | D13: website | E13: Website | F13: 2026-09-10T16:35:00 | G13: 12201.8 | H13: false | I13: false | J13: false | K13: false | L13: 10894.46 | M13: 2026-09-01T20:10:00 | N13: 39004 | O13: Cancelled | P13: Pending | Q13: 4 | R13: ARIVO 195/50/R16 ULTRA ARZ5 84V
A14: 2026-09-25 02:00:22 | B14: ARIVO | D14: website | E14: Website | F14: 2026-09-18T09:40:00 | G14: 12451.8 | H14: false | I14: true | J14: true | K14: true | L14: 11117.68 | M14: 2026-09-01T20:13:00 | N14: 39005 | O14: Fulfilled | P14: Fully Paid | Q14: 4 | R14: ARIVO 195/50/R16 ULTRA ARZ5 84V
A15: 2026-09-25 02:00:22 | B15: WESTLAKE | C15: Website | D15: website | E15: Website | F15: 2026-09-23T16:26:00 | G15: 4631.2 | H15: false | I15: false | J15: false | K15: false | L15: 4135 | M15: 2026-09-01T20:27:00 | N15: 39006 | O15: Cancelled | P15: Pending | Q15: 2 | R15: WESTLAKE 185/70/R13 RP36
A16: 2026-09-25 02:00:22 | B16: CHENGSHAN | D16: website | E16: Website | F16: 2026-09-10T16:33:00 | G16: 4225.3 | H16: false | I16: false | J16: false | K16: false | L16: 3772.59 | M16: 2026-09-01T22:59:00 | N16: 39011 | O16: Cancelled | P16: Pending | Q16: 2 | R16: CHENGSHAN 175/70/R14 CSC-802 84H
A17: 2026-09-25 02:00:22 | B17: YOKOHAMA | C17: Website | D17: website | E17: Website | F17: 2026-09-23T16:26:00 | G17: 21434.8 | H17: false | I17: false | J17: false | K17: false | L17: 19138.21 | M17: 2026-09-01T23:19:00 | N17: 39012 | O17: Cancelled | P17: Pending | Q17: 4 | R17: YOKOHAMA 205/65/R15 BLUEARTH ES32 94H
A18: 2026-09-25 02:00:22 | B18: BFGOODRICH | C18: Website | D18: website | E18: Website | F18: 2026-09-14T09:54:00 | G18: 8598.9 | H18: false | I18: false | J18: false | K18: false | L18: 7677.59 | M18: 2026-09-01T23:36:00 | N18: 39014 | O18: Cancelled | P18: Fully Paid | Q18: 2 | R18: BFGOODRICH 205/65/R15 ADVANTAGE TOURING 99H
A19: 2026-09-25 02:00:22 | B19: ARIVO | C19: Website | D19: website | E19: Website | F19: 2026-09-23T16:26:00 | G19: 6730 | H19: false | I19: false | J19: false | K19: false | L19: 6008.93 | M19: 2026-09-02T01:19:00 | N19: 39015 | O19: Cancelled | P19: Pending | Q19: 2 | R19: ARIVO 205/50/R16 PREMIO SPORT 6 91W
A20: 2026-09-25 02:00:22 | B20: BFGOODRICH | C20: Website | D20: website | E20: Website | F20: 2026-09-18T09:41:00 | G20: 15761.8 | H20: false | I20: true | J20: true | K20: true | L20: 14073.04 | M20: 2026-09-02T06:14:00 | N20: 39017 | O20: Fulfilled | P20: Fully Paid | Q20: 4 | R20: BFGOODRICH 185/65/R15 ADVANTAGE TOURING 88H
A21: 2026-09-25 02:00:22 | B21: COMFORSER | D21: website | E21: Website | F21: 2026-09-23T16:25:00 | G21: 10501.4 | H21: false | I21: false | J21: false | K21: false | L21: 9376.25 | M21: 2026-09-02T07:05:00 | N21: 39018 | O21: Cancelled | P21: Pending | Q21: 4 | R21: COMFORSER 185/60/R15 CF510 84H
A22: 2026-09-25 02:00:22 | B22: BFGOODRICH | C22: Website | D22: website | E22: Website | F22: 2026-09-18T09:47:00 | G22: 12153.4 | H22: false | I22: true | J22: true | K22: true | L22: 10851.25 | M22: 2026-09-02T08:17:00 | N22: 39020 | O22: Fulfilled | P22: Fully Paid | Q22: 4 | R22: BFGOODRICH 175/65/R14 ADVANTAGE TOURING 82H
A23: 2026-09-25 02:00:22 | B23: WESTLAKE | C23: Website | D23: website | E23: Website | F23: 2026-09-22T16:15:00 | G23: 36221.2 | H23: false | I23: true | J23: true | K23: true | L23: 32340.36 | M23: 2026-09-02T09:38:00 | N23: 39023 | O23: Fulfilled | P23: Fully Paid | Q23: 4 | R23: WESTLAKE 305/35/R24 SA57
A24: 2026-09-25 02:00:22 | B24: LAUFENN | C24: CHAT | D24: website | E24: Website | F24: 2026-09-22T09:25:00 | G24: 6808.2 | H24: false | I24: true | J24: true | K24: true | L24: 6078.75 | M24: 2026-09-02T11:07:00 | N24: 39026 | O24: Fulfilled | P24: Fully Paid | Q24: 2 | R24: LAUFENN 195/60/R15 G FIT AS 88V
A25: 2026-09-25 02:00:22 | B25: YOKOHAMA | C25: CALL | D25: website | E25: Website | F25: 2026-09-18T09:42:00 | G25: 27989 | H25: false | I25: true | J25: true | K25: true | L25: 24990.18 | M25: 2026-09-02T12:19:00 | N25: 39032 | O25: Fulfilled | P25: Fully Paid | Q25: 4 | R25: YOKOHAMA 215/55/R16 BLUEARTH GT AE51 97W
A26: 2026-09-25 02:00:22 | B26: HANKOOK | D26: website | E26: Website | F26: 2026-09-02T14:15:00 | G26: 22019 | H26: false | I26: false | J26: false | K26: true | L26: 19659.82 | M26: 2026-09-02T13:21:00 | N26: 39034 | O26: New | P26: Unpaid | Q26: 4 | R26: HANKOOK 205/55/R17 VENTUS PRIME 4 95V
A27: 2026-09-25 02:00:22 | B27: HANKOOK | C27: Website | D27: website | E27: Website | F27: 2026-09-02T14:16:00 | G27: 22019 | H27: false | I27: false | J27: false | K27: true | L27: 19659.82 | M27: 2026-09-02T13:27:00 | N27: 39035 | O27: New | P27: Unpaid | Q27: 4 | R27: HANKOOK 205/55/R17 VENTUS PRIME 4 95V
A28: 2026-09-25 02:00:22 | B28: ARIVO | D28: website | E28: Website | F28: 2026-09-18T09:39:00 | G28: 2555 | H28: false | I28: true | J28: true | K28: true | L28: 2281.25 | M28: 2026-09-02T15:16:00 | N28: 39042 | O28: Fulfilled | P28: Fully Paid | Q28: 1 | R28: ARIVO 175/55/R15 PREMIO COMFORT 6
A29: 2026-09-25 02:00:22 | B29: BRIDGESTONE | C29: CALL | D29: website | E29: Website | F29: 2026-09-18T09:41:00 | G29: 17210.6 | H29: false | I29: true | J29: true | K29: true | L29: 15366.61 | M29: 2026-09-02T16:48:00 | N29: 39053 | O29: Fulfilled | P29: Fully Paid | Q29: 2 | R29: BRIDGESTONE 205/50/R17 TURANZA T005A
A30: 2026-09-25 02:00:22 | B30: BFGOODRICH | C30: Website | D30: website | E30: Website | F30: 2026-09-14T15:06:00 | G30: 21280.2 | H30: false | I30: true | J30: true | K30: true | L30: 19000.18 | M30: 2026-09-02T17:18:00 | N30: 39057 | O30: Fulfilled | P30: Fully Paid | Q30: 4 | R30: BFGOODRICH 215/55/R17 ADVANTAGE TOURING 94V
A31: 2026-09-25 02:00:22 | B31: HANKOOK | C31: Website | D31: website | E31: Website | F31: 2026-09-23T16:25:00 | G31: 21380.2 | H31: false | I31: false | J31: false | K31: false | L31: 19089.46 | M31: 2026-09-02T18:07:00 | N31: 39061 | O31: Cancelled | P31: Pending | Q31: 4 | R31: HANKOOK 215/55/R17 VENTUS PRIME 4 94W
A32: 2026-09-25 02:00:22 | B32: BRIDGESTONE | D32: website | E32: Website | F32: 2026-09-18T09:40:00 | G32: 6110 | H32: false | I32: true | J32: true | K32: true | L32: 5455.36 | M32: 2026-09-02T20:34:00 | N32: 39063 | O32: Fulfilled | P32: Fully Paid | Q32: 1 | R32: BRIDGESTONE 195/60/R16 ECOPIA EP150 89H
A33: 2026-09-25 02:00:22 | B33: DUNLOP | D33: website | E33: Website | F33: 2026-09-22T11:23:00 | G33: 47302.2 | H33: false | I33: true | J33: true | K33: true | L33: 42234.11 | M33: 2026-09-02T21:15:00 | N33: 39065 | O33: Fulfilled | P33: Fully Paid | Q33: 4 | R33: DUNLOP 265/50/R20 GRANDTREK PT5 107V
A34: 2026-09-25 02:00:22 | B34: BRIDGESTONE | C34: Website | D34: website | E34: Website | F34: 2026-09-23T16:25:00 | G34: 10750 | H34: false | I34: false | J34: false | K34: false | L34: 9598.21 | M34: 2026-09-02T21:34:00 | N34: 39066 | O34: Cancelled | P34: Pending | Q34: 1 | R34: BRIDGESTONE 265/65/R17 DUELER H/T 684 (RBT) 112S
A35: 2026-09-25 02:00:22 | B35: HANKOOK | C35: Website | D35: website | E35: Website | F35: 2026-09-04T14:42:00 | G35: 22019 | H35: false | I35: false | J35: false | K35: true | L35: 19659.82 | M35: 2026-09-02T23:57:00 | N35: 39068 | O35: New | P35: Unpaid | Q35: 4 | R35: HANKOOK 205/55/R17 VENTUS PRIME 4 95V
A36: 2026-09-25 02:00:22 | B36: BFGOODRICH | C36: Website | D36: website | E36: Website | F36: 2026-09-10T16:27:00 | G36: 14850 | H36: false | I36: false | J36: false | K36: false | L36: 13258.93 | M36: 2026-09-03T08:35:00 | N36: 39071 | O36: Cancelled | P36: Pending | Q36: 4 | R36: BFGOODRICH 185/55/R15 ADVANTAGE TOURING 86V
A37: 2026-09-25 02:00:22 | B37: MICHELIN | C37: Website | D37: website | E37: Website | F37: 2026-09-08T21:07:00 | G37: 50010 | H37: false | I37: true | J37: true | K37: true | L37: 44651.79 | M37: 2026-09-03T10:11:00 | N37: 39075 | O37: Fulfilled | P37: Fully Paid | Q37: 4 | R37: MICHELIN 235/60/R18 PILOT SPORT 4 SUV 107W
A38: 2026-09-25 02:00:22 | B38: LAUFENN | C38: Website | D38: website | E38: Website | F38: 2026-09-23T16:25:00 | G38: 21419 | H38: false | I38: false | J38: false | K38: false | L38: 19124.11 | M38: 2026-09-03T12:11:00 | N38: 39081 | O38: Cancelled | P38: Pending | Q38: 4 | R38: LAUFENN 225/65/R17 X FIT HT 102T
A39: 2026-09-25 02:00:22 | B39: BFGOODRICH | C39: Website | D39: website | E39: Website | F39: 2026-09-23T16:25:00 | G39: 15645.4 | H39: false | I39: false | J39: false | K39: false | L39: 13969.11 | M39: 2026-09-03T17:13:00 | N39: 39085 | O39: Cancelled | P39: Pending | Q39: 4 | R39: BFGOODRICH 195/55/R15 ADVANTAGE TOURING 89V
A40: 2026-09-25 02:00:22 | B40: BFGOODRICH | D40: website | E40: Website | F40: 2026-09-23T16:24:00 | G40: 17003.4 | H40: false | I40: false | J40: false | K40: false | L40: 15181.61 | M40: 2026-09-03T17:55:00 | N40: 39088 | O40: Cancelled | P40: Pending | Q40: 4 | R40: BFGOODRICH 195/60/R16 ADVANTAGE TOURING 89H
A41: 2026-09-25 02:00:22 | B41: ARIVO | C41: Website | D41: website | E41: Website | F41: 2026-09-22T09:20:00 | G41: 15519.2 | H41: false | I41: true | J41: true | K41: true | L41: 13856.43 | M41: 2026-09-03T18:50:00 | N41: 39090 | O41: Fulfilled | P41: Fully Paid | Q41: 4 | R41: ARIVO 215/65/R16 PREMIO COMFORT 6 98H
A42: 2026-09-25 02:00:22 | B42: BFGOODRICH | D42: website | E42: Website | F42: 2026-09-18T09:46:00 | G42: 11517.9 | H42: false | I42: true | J42: true | K42: true | L42: 10283.84 | M42: 2026-09-03T19:12:00 | N42: 39092 | O42: Fulfilled | P42: Fully Paid | Q42: 2 | R42: BFGOODRICH 225/60/R17 ADVANTAGE TOURING 99H
A43: 2026-09-25 02:00:22 | B43: MICHELIN | C43: Website | D43: website | E43: Website | F43: 2026-09-09T17:34:00 | G43: 19470 | H43: false | I43: true | J43: true | K43: true | L43: 17383.93 | M43: 2026-09-03T21:41:00 | N43: 39097 | O43: Fulfilled | P43: Fully Paid | Q43: 1 | R43: MICHELIN 225/55/R19 PILOT SPORT 4 SUV 99V
A44: 2026-09-25 02:00:22 | B44: MICHELIN | D44: website | E44: Website | F44: 2026-09-18T09:45:00 | G44: 36215 | H44: false | I44: true | J44: true | K44: true | L44: 32334.82 | M44: 2026-09-04T08:54:00 | N44: 39101 | O44: Fulfilled | P44: Fully Paid | Q44: 4 | R44: MICHELIN 215/55/R17 PRIMACY 5 94V
A45: 2026-09-25 02:00:22 | B45: BFGOODRICH | C45: Website | D45: website | E45: Website | F45: 2026-09-10T15:29:00 | G45: 14733.6 | H45: false | I45: true | J45: true | K45: true | L45: 13155 | M45: 2026-09-04T14:06:00 | N45: 39112 | O45: Fulfilled | P45: Partial Payment | Q45: 4 | R45: BFGOODRICH 185/60/R15 ADVANTAGE TOURING 84H
A46: 2026-09-25 02:00:22 | B46: MICHELIN | C46: Website | D46: website | E46: Website | F46: 2026-09-04T16:03:00 | G46: 40095 | H46: false | I46: false | J46: false | K46: true | L46: 35799.11 | M46: 2026-09-04T15:13:00 | N46: 39117 | O46: New | P46: Unpaid | Q46: 4 | R46: MICHELIN 225/55/R18 PRIMACY 5 102V
A47: 2026-09-25 02:00:22 | B47: FRONWAY | D47: website | E47: Website | F47: 2026-09-10T16:31:00 | G47: 8212.2 | H47: false | I47: false | J47: false | K47: false | L47: 7332.32 | M47: 2026-09-04T16:02:00 | N47: 39121 | O47: Cancelled | P47: Pending | Q47: 4 | R47: FRONWAY 175/65/R14 ECOGREEN ONE 82V
A48: 2026-09-25 02:00:22 | B48: BFGOODRICH | C48: Website | D48: website | E48: Website | F48: 2026-09-10T16:27:00 | G48: 20517 | H48: false | I48: false | J48: false | K48: false | L48: 18318.75 | M48: 2026-09-04T19:20:00 | N48: 39124 | O48: Cancelled | P48: Pending | Q48: 4 | R48: BFGOODRICH 215/55/R16 ADVANTAGE TOURING 97V
A49: 2026-09-25 02:00:22 | B49: GOODYEAR | D49: website | E49: Website | F49: 2026-09-07T13:10:00 | G49: 6665 | H49: false | I49: false | J49: false | K49: true | L49: 5950.89 | M49: 2026-09-04T20:23:00 | N49: 39125 | O49: New | P49: Unpaid | Q49: 1 | R49: GOODYEAR 205/50/R17 ASSURANCE TRIPLEMAX 2 89V
A50: 2026-09-25 02:00:22 | B50: BFGOODRICH | D50: website | E50: Website | F50: 2026-09-10T15:09:00 | G50: 17877.2 | H50: false | I50: false | J50: false | K50: false | L50: 15961.79 | M50: 2026-09-04T21:44:00 | N50: 39129 | O50: Cancelled | P50: Pending | Q50: 4 | R50: BFGOODRICH 205/65/R16 ADVANTAGE TOURING 95H
A51: 2026-09-25 02:00:22 | B51: ARIVO | D51: website | E51: Website | F51: 2026-09-10T15:08:00 | G51: 10984.5 | H51: false | I51: false | J51: false | K51: false | L51: 9807.59 | M51: 2026-09-04T22:08:00 | N51: 39131 | O51: Cancelled | P51: Pending | Q51: 2 | R51: ARIVO 235/60/R18 TERRANO ARV H/T 107H
A52: 2026-09-25 02:00:22 | B52: CHENGSHAN | D52: website | E52: Website | F52: 2026-09-23T16:24:00 | G52: 10195.4 | H52: false | I52: false | J52: false | K52: false | L52: 9103.04 | M52: 2026-09-04T22:19:00 | N52: 39132 | O52: Cancelled | P52: Pending | Q52: 4 | R52: CHENGSHAN 205/55/R16 CSC-802 91V
A53: 2026-09-25 02:00:22 | B53: LAUFENN | D53: website | E53: Website | F53: 2026-09-10T15:08:00 | G53: 13185.2 | H53: false | I53: false | J53: false | K53: false | L53: 11772.5 | M53: 2026-09-04T23:10:00 | N53: 39133 | O53: Cancelled | P53: Pending | Q53: 4 | R53: LAUFENN 185/55/R16 S FIT EQ 83V
A54: 2026-09-25 02:00:22 | B54: YOKOHAMA | D54: website | E54: Website | F54: 2026-09-18T09:45:00 | G54: 8450.4 | H54: false | I54: true | J54: true | K54: true | L54: 7545 | M54: 2026-09-04T23:17:00 | N54: 39135 | O54: Fulfilled | P54: Fully Paid | Q54: 2 | R54: YOKOHAMA 175/65/R14 BLUEARTH ES32 82T
A55: 2026-09-25 02:00:22 | B55: CHENGSHAN | D55: website | E55: Website | F55: 2026-09-18T09:45:00 | G55: 10495 | H55: false | I55: true | J55: true | K55: true | L55: 9370.54 | M55: 2026-09-04T23:45:00 | N55: 39136 | O55: Fulfilled | P55: Fully Paid | Q55: 4 | R55: CHENGSHAN 205/55/R16 CSC-802 91V
A56: 2026-09-25 02:00:22 | B56: MICHELIN | C56: CALL | D56: website | E56: Website | F56: 2026-09-18T09:47:00 | G56: 40095 | H56: false | I56: true | J56: true | K56: true | L56: 35799.11 | M56: 2026-09-05T12:13:00 | N56: 39140 | O56: Fulfilled | P56: Fully Paid | Q56: 4 | R56: MICHELIN 225/55/R18 PRIMACY 5 102V
A57: 2026-09-25 02:00:22 | B57: MICHELIN | D57: website | E57: Website | F57: 2026-09-10T15:28:00 | G57: 42530 | H57: false | I57: true | J57: true | K57: true | L57: 37973.21 | M57: 2026-09-05T13:10:00 | N57: 39143 | O57: Fulfilled | P57: Fully Paid | Q57: 4 | R57: MICHELIN 265/65/R17 PRIMACY SUV+ 112H
A58: 2026-09-25 02:00:22 | B58: BFGOODRICH | C58: Website | D58: website | E58: Website | F58: 2026-09-23T16:24:00 | G58: 33928.4 | H58: false | I58: false | J58: false | K58: false | L58: 30293.21 | M58: 2026-09-05T15:45:00 | N58: 39146 | O58: Cancelled | P58: Pending | Q58: 4 | R58: BFGOODRICH 265/50/R20 ADVANTAGE TOURING 111T
A59: 2026-09-25 02:00:22 | B59: ARIVO | C59: Website | D59: website | E59: Website | F59: 2026-09-23T16:24:00 | G59: 10683.4 | H59: false | I59: false | J59: false | K59: false | L59: 9538.75 | M59: 2026-09-05T16:37:00 | N59: 39148 | O59: Cancelled | P59: Pending | Q59: 4 | R59: ARIVO 185/55/R15 PREMIO COMFORT 6
A60: 2026-09-25 02:00:22 | B60: MICHELIN | C60: Website | D60: website | E60: Website | F60: 2026-09-23T16:23:00 | G60: 36315 | H60: false | I60: false | J60: false | K60: false | L60: 32424.11 | M60: 2026-09-06T04:40:00 | N60: 39151 | O60: Cancelled | P60: Pending | Q60: 4 | R60: MICHELIN 215/55/R17 PRIMACY 5 94V
A61: 2026-09-25 02:00:22 | B61: BRIDGESTONE | C61: CHAT | D61: website | E61: Website | F61: 2026-09-09T10:09:00 | G61: 5580 | H61: false | I61: true | J61: true | K61: true | L61: 4982.14 | M61: 2026-09-06T11:28:00 | N61: 39152 | O61: Fulfilled | P61: Fully Paid | Q61: 1 | R61: BRIDGESTONE 195/50/R16 TURANZA ER33 84V
A62: 2026-09-25 02:00:22 | B62: BLACK ARROW | D62: website | E62: Website | F62: 2026-09-07T13:11:00 | G62: 10282 | H62: false | I62: false | J62: false | K62: true | L62: 9180.36 | M62: 2026-09-06T12:56:00 | N62: 39154 | O62: New | P62: Unpaid | Q62: 4 | R62: BLACK ARROW 205/55/R16 DART P15 91V
A63: 2026-09-25 02:00:22 | B63: CST | C63: Website | D63: website | E63: Website | F63: 2026-09-11T18:53:00 | G63: 5059.9 | H63: false | I63: true | J63: true | K63: true | L63: 4517.77 | M63: 2026-09-06T16:11:00 | N63: 39158 | O63: Fulfilled | P63: Fully Paid | Q63: 2 | R63: CST 155/80/R13 MARQUIS MR61 79T
A64: 2026-09-25 02:00:22 | B64: BFGOODRICH | C64: Website | D64: website | E64: Website | F64: 2026-09-23T16:23:00 | G64: 13863.6 | H64: false | I64: false | J64: false | K64: false | L64: 12378.21 | M64: 2026-09-06T17:15:00 | N64: 39160 | O64: Cancelled | P64: Pending | Q64: 4 | R64: BFGOODRICH 185/55/R16 ADVANTAGE TOURING 87H
A65: 2026-09-25 02:00:22 | B65: FRONWAY | D65: website | E65: Website | F65: 2026-09-10T15:25:00 | G65: 10317.8 | H65: false | I65: true | J65: true | K65: true | L65: 9212.32 | M65: 2026-09-06T19:05:00 | N65: 39161 | O65: Fulfilled | P65: Fully Paid | Q65: 4 | R65: FRONWAY 195/50/R15 ECOGREEN ONE 82V
A66: 2026-09-25 02:00:22 | B66: HANKOOK | D66: website | E66: Website | F66: 2026-09-07T13:17:00 | G66: 51292 | H66: false | I66: false | J66: false | K66: true | L66: 45796.43 | M66: 2026-09-06T21:36:00 | N66: 39164 | O66: New | P66: Unpaid | Q66: 5 | R66: HANKOOK 265/50/R20 DYNAPRO AT2 XTREME RF12 111T
A67: 2026-09-25 02:00:22 | B67: HANKOOK | D67: website | E67: Website | F67: 2026-09-10T15:23:00 | G67: 51292 | H67: false | I67: true | J67: true | K67: true | L67: 45796.43 | M67: 2026-09-06T21:43:00 | N67: 39166 | O67: Fulfilled | P67: Fully Paid | Q67: 5 | R67: HANKOOK 265/50/R20 DYNAPRO AT2 XTREME RF12 111T
A68: 2026-09-25 02:00:22 | B68: ARIVO | D68: website | E68: Website | F68: 2026-09-10T15:22:00 | G68: 9105 | H68: false | I68: true | J68: true | K68: true | L68: 8129.46 | M68: 2026-09-06T22:03:00 | N68: 39169 | O68: Fulfilled | P68: Fully Paid | Q68: 2 | R68: ARIVO 215/70/R16C TRANSITO ARZ 6-X
A69: 2026-09-25 02:00:22 | B69: MICHELIN | C69: Website | D69: website | E69: Website | F69: 2026-09-10T14:38:00 | G69: 36715 | H69: false | I69: false | J69: false | K69: false | L69: 32781.25 | M69: 2026-09-06T22:44:00 | N69: 39171 | O69: Cancelled | P69: Pending | Q69: 4 | R69: MICHELIN 215/55/R17 PRIMACY 5 94V
A70: 2026-09-25 02:00:22 | B70: WESTLAKE | D70: website | E70: Website | F70: 2026-09-10T15:33:00 | G70: 9167.2 | H70: false | I70: true | J70: true | K70: true | L70: 8185 | M70: 2026-09-06T23:44:00 | N70: 39172 | O70: Fulfilled | P70: Fully Paid | Q70: 4 | R70: WESTLAKE 165/70/R14 RP36
A71: 2026-09-25 02:00:22 | B71: BFGOODRICH | C71: CHAT | D71: fb | E71: Fb | F71: 2026-09-22T09:56:00 | G71: 22287 | H71: false | I71: true | J71: true | K71: true | L71: 19899.11 | M71: 2026-09-07T09:35:00 | N71: 39179 | O71: Fulfilled | P71: Fully Paid | Q71: 4 | R71: BFGOODRICH 225/45/R17 ADVANTAGE TOURING 94V
A72: 2026-09-25 02:00:22 | B72: MICHELIN | D72: website | E72: Website | F72: 2026-09-07T13:11:00 | G72: 40095 | H72: false | I72: false | J72: false | K72: true | L72: 35799.11 | M72: 2026-09-07T10:56:00 | N72: 39186 | O72: New | P72: Unpaid | Q72: 4 | R72: MICHELIN 225/55/R18 PRIMACY 5 102V
A73: 2026-09-25 02:00:22 | B73: BRIDGESTONE | C73: Website | D73: website | E73: Website | F73: 2026-09-18T09:52:00 | G73: 10750 | H73: false | I73: true | J73: true | K73: true | L73: 9598.21 | M73: 2026-09-07T11:12:00 | N73: 39189 | O73: Fulfilled | P73: Fully Paid | Q73: 1 | R73: BRIDGESTONE 265/65/R17 DUELER H/T 684 (RBT) 112S
A74: 2026-09-25 02:00:22 | B74: ARIVO | C74: Website | D74: website | E74: Website | F74: 2026-09-22T09:40:00 | G74: 10256.6 | H74: false | I74: true | J74: true | K74: true | L74: 9157.68 | M74: 2026-09-07T11:25:00 | N74: 39193 | O74: Fulfilled | P74: Fully Paid | Q74: 4 | R74: ARIVO 175/70/R14 PREMIO COMFORT 6 84T
A75: 2026-09-25 02:00:22 | B75: ARIVO | C75: CHAT | D75: fb | E75: Fb | F75: 2026-09-23T10:58:00 | G75: 16369.2 | H75: false | I75: true | J75: true | K75: true | L75: 14615.36 | M75: 2026-09-07T11:55:00 | N75: 39200 | O75: Fulfilled | P75: Fully Paid | Q75: 4 | R75: ARIVO 215/65/R16 PREMIO COMFORT 6 98H
A76: 2026-09-25 02:00:22 | B76: WESTLAKE | D76: website | E76: Website | F76: 2026-09-14T15:22:00 | G76: 5701.4 | H76: false | I76: true | J76: true | K76: true | L76: 5090.54 | M76: 2026-09-07T12:45:00 | N76: 39201 | O76: Fulfilled | P76: Fully Paid | Q76: 2 | R76: WESTLAKE 185/65/R15 RP36
A77: 2026-09-25 02:00:22 | B77: MICHELIN | C77: CHAT | D77: website | E77: Website | F77: 2026-09-22T11:36:00 | G77: 21870 | H77: false | I77: true | J77: true | K77: true | L77: 19526.79 | M77: 2026-09-07T13:07:00 | N77: 39202 | O77: Fulfilled | P77: Fully Paid | Q77: 4 | R77: MICHELIN 185/60/R15 ENERGY XM2+ 88H
A78: 2026-09-25 02:00:22 | B78: BFGOODRICH | C78: CALL | D78: website | E78: Website | F78: 2026-09-23T10:14:00 | G78: 76746.4 | H78: false | I78: true | J78: true | K78: true | L78: 68523.57 | M78: 2026-09-07T13:57:00 | N78: 39203 | O78: Fulfilled | P78: Fully Paid | Q78: 4 | R78: BFGOODRICH 265/60/R18 ALL-TERRAIN T/A KO3 114/110S
A79: 2026-09-25 02:00:22 | B79: BFGOODRICH | C79: CHAT | D79: website | E79: Website | F79: 2026-09-14T08:32:00 | G79: 24400 | H79: false | I79: true | J79: true | K79: true | L79: 21785.71 | M79: 2026-09-07T14:06:00 | N79: 39204 | O79: Fulfilled | P79: Fully Paid | Q79: 4 | R79: BFGOODRICH 225/55/R18 ADVANTAGE TOURING 98H
A80: 2026-09-25 02:00:22 | B80: BFGOODRICH | C80: Website | D80: website | E80: Website | F80: 2026-09-22T11:25:00 | G80: 20517 | H80: false | I80: true | J80: true | K80: true | L80: 18318.75 | M80: 2026-09-07T17:03:00 | N80: 39212 | O80: Fulfilled | P80: Fully Paid | Q80: 4 | R80: BFGOODRICH 215/55/R16 ADVANTAGE TOURING 97V
A81: 2026-09-25 02:00:22 | B81: DURATURN | C81: Website | D81: website | E81: Website | F81: 2026-09-14T15:26:00 | G81: 2710 | H81: false | I81: true | J81: true | K81: true | L81: 2419.64 | M81: 2026-09-07T17:12:00 | N81: 39213 | O81: Fulfilled | P81: Fully Paid | Q81: 1 | R81: DURATURN 195/60/R15 MOZZO ECO D3 88V
A82: 2026-09-25 02:00:22 | B82: MICHELIN | D82: website | E82: Website | F82: 2026-09-23T16:23:00 | G82: 26650 | H82: false | I82: false | J82: false | K82: false | L82: 23794.64 | M82: 2026-09-07T20:01:00 | N82: 39217 | O82: Cancelled | P82: Pending | Q82: 2 | R82: MICHELIN 225/50/R18 PRIMACY 5 99W
A83: 2026-09-25 02:00:22 | B83: MICHELIN | D83: website | E83: Website | F83: 2026-09-23T16:23:00 | G83: 24230 | H83: false | I83: false | J83: false | K83: false | L83: 21633.93 | M83: 2026-09-07T20:44:00 | N83: 39219 | O83: Cancelled | P83: Pending | Q83: 4 | R83: MICHELIN 205/60/R15 ENERGY XM2+ 91V
A84: 2026-09-25 02:00:22 | B84: ARIVO | C84: Website | D84: website | E84: Website | F84: 2026-09-23T16:23:00 | G84: 6830 | H84: false | I84: false | J84: false | K84: false | L84: 6098.21 | M84: 2026-09-07T21:38:00 | N84: 39220 | O84: Cancelled | P84: Pending | Q84: 2 | R84: ARIVO 205/50/R16 PREMIO SPORT 6 91W
A85: 2026-09-25 02:00:22 | B85: MICHELIN | C85: Website | D85: website | E85: Website | F85: 2026-09-23T16:22:00 | G85: 68475 | H85: false | I85: false | J85: false | K85: false | L85: 61138.39 | M85: 2026-09-08T00:37:00 | N85: 39226 | O85: Cancelled | P85: Pending | Q85: 4 | R85: MICHELIN 255/55/R20 PRIMACY 5 110V
A86: 2026-09-25 02:00:22 | B86: MICHELIN | C86: CHAT | D86: fb | E86: Fb | F86: 2026-09-22T11:29:00 | G86: 36915 | H86: false | I86: true | J86: true | K86: true | L86: 32959.82 | M86: 2026-09-08T10:57:00 | N86: 39230 | O86: Fulfilled | P86: Fully Paid | Q86: 4 | R86: MICHELIN 215/55/R17 PRIMACY 5 94V
A87: 2026-09-25 02:00:22 | B87: YOKOHAMA | D87: website | E87: Website | F87: 2026-09-12T10:48:00 | G87: 38352.2 | H87: false | I87: true | J87: true | K87: true | L87: 34243.04 | M87: 2026-09-08T11:38:00 | N87: 39233 | O87: Fulfilled | P87: Fully Paid | Q87: 4 | R87: YOKOHAMA 255/70/R16 GEOLANDAR H/T4 G062 115T
A88: 2026-09-25 02:00:22 | B88: HANKOOK | D88: website | E88: Website | F88: 2026-09-08T13:55:00 | G88: 13502.4 | H88: false | I88: false | J88: false | K88: true | L88: 12055.71 | M88: 2026-09-08T13:55:00 | N88: 39242 | O88: New | P88: Unpaid | Q88: 4 | R88: HANKOOK 185/65/R15 KINERGY ECO2 88T
A89: 2026-09-25 02:00:22 | B89: BRIDGESTONE | D89: website | E89: Website | F89: 2026-09-11T18:55:00 | G89: 12141.8 | H89: false | I89: true | J89: true | K89: true | L89: 10840.89 | M89: 2026-09-08T15:42:00 | N89: 39246 | O89: Fulfilled | P89: Fully Paid | Q89: 2 | R89: BRIDGESTONE 195/60/R16 ECOPIA EP150 89H
A90: 2026-09-25 02:00:22 | B90: VREDESTEIN | C90: CALL | D90: website | E90: Website | F90: 2026-09-16T15:07:00 | G90: 22280 | H90: false | I90: true | J90: true | K90: true | L90: 19892.86 | M90: 2026-09-08T16:20:00 | N90: 39248 | O90: Fulfilled | P90: Partial Payment | Q90: 4 | R90: VREDESTEIN 215/75/R15 PINZA AT
A91: 2026-09-25 02:00:22 | B91: BFGOODRICH | C91: Website | D91: website | E91: Website | F91: 2026-09-12T11:20:00 | G91: 32828.4 | H91: false | I91: true | J91: true | K91: true | L91: 29311.07 | M91: 2026-09-08T17:30:00 | N91: 39254 | O91: Fulfilled | P91: Fully Paid | Q91: 4 | R91: BFGOODRICH 265/65/R17 ADVANTAGE TOURING 112H
A92: 2026-09-25 02:00:22 | B92: BFGOODRICH | D92: website | E92: Website | F92: 2026-09-24T11:18:00 | G92: 24400 | H92: false | I92: true | J92: true | K92: true | L92: 21785.71 | M92: 2026-09-08T17:32:00 | N92: 39256 | O92: Fulfilled | P92: Fully Paid | Q92: 4 | R92: BFGOODRICH 225/55/R18 ADVANTAGE TOURING 98H
A93: 2026-09-25 02:00:22 | B93: WESTLAKE | C93: Website | D93: website | E93: Website | F93: 2026-09-23T16:22:00 | G93: 13295.7 | H93: false | I93: false | J93: false | K93: false | L93: 11871.16 | M93: 2026-09-08T18:23:00 | N93: 39257 | O93: Cancelled | P93: Pending | Q93: 2 | R93: WESTLAKE 265/50/R20 SA37
A94: 2026-09-25 02:00:22 | B94: VREDESTEIN | C94: Website | D94: website | E94: Website | F94: 2026-09-09T13:06:00 | G94: 27870 | H94: false | I94: false | J94: false | K94: true | L94: 24883.93 | M94: 2026-09-08T22:28:00 | N94: 39260 | O94: New | P94: Unpaid | Q94: 4 | R94: VREDESTEIN 235/55/R17 ULTRAC VORTI I
A95: 2026-09-25 02:00:22 | B95: BFGOODRICH | D95: website | E95: Website | F95: 2026-09-09T13:04:00 | G95: 15283.6 | H95: false | I95: false | J95: false | K95: true | L95: 13646.07 | M95: 2026-09-09T08:39:00 | N95: 39263 | O95: New | P95: Unpaid | Q95: 4 | R95: BFGOODRICH 185/60/R15 ADVANTAGE TOURING 84H
A96: 2026-09-25 02:00:22 | B96: BFGOODRICH | D96: website | E96: Website | F96: 2026-09-09T13:04:00 | G96: 15283.6 | H96: false | I96: false | J96: false | K96: true | L96: 13646.07 | M96: 2026-09-09T08:42:00 | N96: 39264 | O96: New | P96: Unpaid | Q96: 4 | R96: BFGOODRICH 185/60/R15 ADVANTAGE TOURING 84H
A97: 2026-09-25 02:00:22 | B97: BLACK ARROW | C97: Website | D97: website | E97: Website | F97: 2026-09-11T11:20:00 | G97: 8904.6 | H97: false | I97: false | J97: false | K97: true | L97: 7950.54 | M97: 2026-09-09T09:36:00 | N97: 39265 | O97: New | P97: Unpaid | Q97: 4 | R97: BLACK ARROW 185/65/R15 SUPER DART P16 88H
A98: 2026-09-25 02:00:22 | B98: WESTLAKE | D98: website | E98: Website | F98: 2026-09-23T16:22:00 | G98: 22156.2 | H98: false | I98: false | J98: false | K98: false | L98: 19782.32 | M98: 2026-09-09T15:11:00 | N98: 39278 | O98: Cancelled | P98: Pending | Q98: 4 | R98: WESTLAKE 235/55/R18 SU318
A99: 2026-09-25 02:00:22 | B99: WESTLAKE | D99: website | E99: Website | F99: 2026-09-12T13:12:00 | G99: 5382.6 | H99: false | I99: false | J99: false | K99: false | L99: 4805.89 | M99: 2026-09-09T15:15:00 | N99: 39280 | O99: Cancelled | P99: Pending | Q99: 2 | R99: WESTLAKE 185/60/R15 RP36
A100: 2026-09-25 02:00:22 | B100: MICHELIN | C100: Website | D100: website | E100: Website | F100: 2026-09-14T15:04:00 | G100: 22390 | H100: false | I100: true | J100: true | K100: true | L100: 19991.07 | M100: 2026-09-09T15:27:00 | N100: 39282 | O100: Fulfilled | P100: Fully Paid | Q100: 2 | R100: MICHELIN 225/50/R18 PRIMACY 5 ENERGY 99W
...

Sheet Exceptions
A1: Channel | B1: Session campaign | C1: Order ID | D1: Order date | E1: Week | F1: Scope | G1: Customer type | H1: Customer source | I1: Order status | J1: Payment status | K1: Net sales | L1: Fulfilled net revenue | M1: Gross order value | N1: Fulfilled flag | O1: Cancelled flag | P1: Open net value | Q1: Cancelled net value | R1: Return refund net value | S1: Purchase events | T1: Quantity | U1: Brand | V1: SKU | W1: Page path + query string | X1: Source file | Y1: Source CSV row | Z1: Backend loaded at | AA1: Backend updated at | AB1: Test order
A2: Google Ads | B2: Michelin - PMax PH | C2: 38959 | D2: 46265.788 | E2: Outside / unknown | F2: Outside period | G2: Website | H2: Website | I2: Fulfilled | J2: Fully Paid | K2: 27053.57 | L2: 27053.57 | M2: 30300 | N2: 1 | O2: 0 | P2: 0 | Q2: 0 | R2: 0 | S2: 2 | T2: 4 | U2: MICHELIN | V2: MICHELIN 195/60/R16 PRIMACY 5 93V | W2: /complete-order?requestid=Mzg5NTk= | X2: revenue_match/google_cpc.csv | Y2: 36 | Z2: 2026-09-25 02:00:22 | AA2: 2026-09-22T16:14:00 | AB2: false
A3: Direct & Organic | B3: (direct) | C3: 39900 | E3: Outside / unknown | F3: Unmatched | G3: Unknown | H3: Unknown | I3: Unknown | J3: Unknown | N3: 0 | O3: 0 | S3: 2 | W3: /complete-order?requestid=Mzk5MDA= | X3: direct_and_organic_revenue/direct_and_organic.csv | Y3: 64 | AB3: Unknown
A4: Direct & Organic | B4: (direct) | C4: 39109 | E4: Outside / unknown | F4: Unmatched | G4: Unknown | H4: Unknown | I4: Unknown | J4: Unknown | N4: 0 | O4: 0 | S4: 2 | W4: /complete-order?requestid=MzkxMDk= | X4: direct_and_organic_revenue/direct_and_organic.csv | Y4: 75 | AB4: Unknown
A5: Direct & Organic | B5: (direct) | C5: 38805 | D5: 46260.621 | E5: Outside / unknown | F5: Outside period | G5: Fb | H5: CALL | I5: Fulfilled | J5: Fully Paid | K5: 54174.11 | L5: 54174.11 | M5: 60675 | N5: 1 | O5: 0 | P5: 0 | Q5: 0 | R5: 0 | S5: 2 | T5: 4 | U5: MICHELIN | V5: MICHELIN 225/45/ZR19 PILOT SPORT 5 96Y XL TL | W5: /complete-order?requestid=Mzg4MDU= | X5: direct_and_organic_revenue/direct_and_organic.csv | Y5: 87 | Z5: 2026-09-25 02:00:22 | AA5: 2026-09-18T09:53:00 | AB5: false
A6: Direct & Organic | B6: (direct) | C6: 39052 | E6: Outside / unknown | F6: Unmatched | G6: Unknown | H6: Unknown | I6: Unknown | J6: Unknown | N6: 0 | O6: 0 | S6: 1 | W6: /complete-order?requestid=MzkwNTI= | X6: direct_and_organic_revenue/direct_and_organic.csv | Y6: 144 | AB6: Unknown

Sheet Channel Summary
A1: Channel Summary
A3: September 1–24 only. Order values are counted once; status reflects the backend snapshot.
A6: Channel | B6: Orders | C6: Net sales | D6: Fulfilled orders | E6: Fulfilled net revenue | F6: Fulfillment rate | G6: Cancelled orders | H6: Cancelled net value | I6: Open net value | J6: Return refund net value | K6: Net value per order | L6: Fulfilled value share
A7: Google Ads | B7: =COUNTIFS('Source Data'!$F$2:$F$268,"Included",'Source Data'!$A$2:$A$268,"Google Ads") -> 67 | C7: =SUMIFS('Source Data'!$K$2:$K$268,'Source Data'!$F$2:$F$268,"Included",'Source Data'!$A$2:$A$268,"Google Ads") -> 1473109.5 | D7: =SUMIFS('Source Data'!$N$2:$N$268,'Source Data'!$F$2:$F$268,"Included",'Source Data'!$A$2:$A$268,"Google Ads") -> 26 | E7: =SUMIFS('Source Data'!$L$2:$L$268,'Source Data'!$F$2:$F$268,"Included",'Source Data'!$A$2:$A$268,"Google Ads") -> 510707.5 | F7: =IFERROR(D7/B7,0) -> 0.3880597 | G7: =SUMIFS('Source Data'!$O$2:$O$268,'Source Data'!$F$2:$F$268,"Included",'Source Data'!$A$2:$A$268,"Google Ads") -> 18 | H7: =SUMIFS('Source Data'!$Q$2:$Q$268,'Source Data'!$F$2:$F$268,"Included",'Source Data'!$A$2:$A$268,"Google Ads") -> 328191.94 | I7: =SUMIFS('Source Data'!$P$2:$P$268,'Source Data'!$F$2:$F$268,"Included",'Source Data'!$A$2:$A$268,"Google Ads") -> 623269.5 | J7: =SUMIFS('Source Data'!$R$2:$R$268,'Source Data'!$F$2:$F$268,"Included",'Source Data'!$A$2:$A$268,"Google Ads") -> 10940.54 | K7: =IFERROR(C7/B7,0) -> 21986.709 | L7: =IFERROR(E7/C7,0) -> 0.34668672
A8: Direct & Organic | B8: =COUNTIFS('Source Data'!$F$2:$F$268,"Included",'Source Data'!$A$2:$A$268,"Direct & Organic") -> 167 | C8: =SUMIFS('Source Data'!$K$2:$K$268,'Source Data'!$F$2:$F$268,"Included",'Source Data'!$A$2:$A$268,"Direct & Organic") -> 2862122.7 | D8: =SUMIFS('Source Data'!$N$2:$N$268,'Source Data'!$F$2:$F$268,"Included",'Source Data'!$A$2:$A$268,"Direct & Organic") -> 75 | E8: =SUMIFS('Source Data'!$L$2:$L$268,'Source Data'!$F$2:$F$268,"Included",'Source Data'!$A$2:$A$268,"Direct & Organic") -> 1307528.9 | F8: =IFERROR(D8/B8,0) -> 0.4491018 | G8: =SUMIFS('Source Data'!$O$2:$O$268,'Source Data'!$F$2:$F$268,"Included",'Source Data'!$A$2:$A$268,"Direct & Organic") -> 50 | H8: =SUMIFS('Source Data'!$Q$2:$Q$268,'Source Data'!$F$2:$F$268,"Included",'Source Data'!$A$2:$A$268,"Direct & Organic") -> 833341.14 | I8: =SUMIFS('Source Data'!$P$2:$P$268,'Source Data'!$F$2:$F$268,"Included",'Source Data'!$A$2:$A$268,"Direct & Organic") -> 660976.6 | J8: =SUMIFS('Source Data'!$R$2:$R$268,'Source Data'!$F$2:$F$268,"Included",'Source Data'!$A$2:$A$268,"Direct & Organic") -> 60276.07 | K8: =IFERROR(C8/B8,0) -> 17138.459 | L8: =IFERROR(E8/C8,0) -> 0.45683886
A9: Referral | B9: =COUNTIFS('Source Data'!$F$2:$F$268,"Included",'Source Data'!$A$2:$A$268,"Referral") -> 28 | C9: =SUMIFS('Source Data'!$K$2:$K$268,'Source Data'!$F$2:$F$268,"Included",'Source Data'!$A$2:$A$268,"Referral") -> 464584.11 | D9: =SUMIFS('Source Data'!$N$2:$N$268,'Source Data'!$F$2:$F$268,"Included",'Source Data'!$A$2:$A$268,"Referral") -> 10 | E9: =SUMIFS('Source Data'!$L$2:$L$268,'Source Data'!$F$2:$F$268,"Included",'Source Data'!$A$2:$A$268,"Referral") -> 273228.94 | F9: =IFERROR(D9/B9,0) -> 0.35714286 | G9: =SUMIFS('Source Data'!$O$2:$O$268,'Source Data'!$F$2:$F$268,"Included",'Source Data'!$A$2:$A$268,"Referral") -> 11 | H9: =SUMIFS('Source Data'!$Q$2:$Q$268,'Source Data'!$F$2:$F$268,"Included",'Source Data'!$A$2:$A$268,"Referral") -> 132243.91 | I9: =SUMIFS('Source Data'!$P$2:$P$268,'Source Data'!$F$2:$F$268,"Included",'Source Data'!$A$2:$A$268,"Referral") -> 48170.72 | J9: =SUMIFS('Source Data'!$R$2:$R$268,'Source Data'!$F$2:$F$268,"Included",'Source Data'!$A$2:$A$268,"Referral") -> 10940.54 | K9: =IFERROR(C9/B9,0) -> 16592.29 | L9: =IFERROR(E9/C9,0) -> 0.58811512

Sheet Weekly Summary
A1: Weekly Summary
A3: September 1–24 only. Order values are counted once; status reflects the backend snapshot.
A6: Week | B6: Channel | C6: Orders | D6: Net sales | E6: Fulfilled orders | F6: Fulfilled net revenue | G6: Fulfillment rate | H6: Cancelled orders | I6: Cancelled net value | J6: Open net value | K6: Return refund net value | L6: Net value per order | M6: Fulfilled value share
A7: Week 1 | B7: Google Ads | C7: =COUNTIFS('Source Data'!$F$2:$F$268,"Included",'Source Data'!$E$2:$E$268,"Week 1",'Source Data'!$A$2:$A$268,"Google Ads") -> 24 | D7: =SUMIFS('Source Data'!$K$2:$K$268,'Source Data'!$F$2:$F$268,"Included",'Source Data'!$E$2:$E$268,"Week 1",'Source Data'!$A$2:$A$268,"Google Ads") -> 522608.31 | E7: =SUMIFS('Source Data'!$N$2:$N$268,'Source Data'!$F$2:$F$268,"Included",'Source Data'!$E$2:$E$268,"Week 1",'Source Data'!$A$2:$A$268,"Google Ads") -> 15 | F7: =SUMIFS('Source Data'!$L$2:$L$268,'Source Data'!$F$2:$F$268,"Included",'Source Data'!$E$2:$E$268,"Week 1",'Source Data'!$A$2:$A$268,"Google Ads") -> 324575.99 | G7: =IFERROR(E7/C7,0) -> 0.625 | H7: =SUMIFS('Source Data'!$O$2:$O$268,'Source Data'!$F$2:$F$268,"Included",'Source Data'!$E$2:$E$268,"Week 1",'Source Data'!$A$2:$A$268,"Google Ads") -> 6 | I7: =SUMIFS('Source Data'!$Q$2:$Q$268,'Source Data'!$F$2:$F$268,"Included",'Source Data'!$E$2:$E$268,"Week 1",'Source Data'!$A$2:$A$268,"Google Ads") -> 112916.25 | J7: =SUMIFS('Source Data'!$P$2:$P$268,'Source Data'!$F$2:$F$268,"Included",'Source Data'!$E$2:$E$268,"Week 1",'Source Data'!$A$2:$A$268,"Google Ads") -> 85116.07 | K7: =SUMIFS('Source Data'!$R$2:$R$268,'Source Data'!$F$2:$F$268,"Included",'Source Data'!$E$2:$E$268,"Week 1",'Source Data'!$A$2:$A$268,"Google Ads") -> 0 | L7: =IFERROR(D7/C7,0) -> 21775.346 | M7: =IFERROR(F7/D7,0) -> 0.62106932
A8: Week 1 | B8: Direct & Organic | C8: =COUNTIFS('Source Data'!$F$2:$F$268,"Included",'Source Data'!$E$2:$E$268,"Week 1",'Source Data'!$A$2:$A$268,"Direct & Organic") -> 52 | D8: =SUMIFS('Source Data'!$K$2:$K$268,'Source Data'!$F$2:$F$268,"Included",'Source Data'!$E$2:$E$268,"Week 1",'Source Data'!$A$2:$A$268,"Direct & Organic") -> 793046.8 | E8: =SUMIFS('Source Data'!$N$2:$N$268,'Source Data'!$F$2:$F$268,"Included",'Source Data'!$E$2:$E$268,"Week 1",'Source Data'!$A$2:$A$268,"Direct & Organic") -> 27 | F8: =SUMIFS('Source Data'!$L$2:$L$268,'Source Data'!$F$2:$F$268,"Included",'Source Data'!$E$2:$E$268,"Week 1",'Source Data'!$A$2:$A$268,"Direct & Organic") -> 403835.56 | G8: =IFERROR(E8/C8,0) -> 0.51923077 | H8: =SUMIFS('Source Data'!$O$2:$O$268,'Source Data'!$F$2:$F$268,"Included",'Source Data'!$E$2:$E$268,"Week 1",'Source Data'!$A$2:$A$268,"Direct & Organic") -> 21 | I8: =SUMIFS('Source Data'!$Q$2:$Q$268,'Source Data'!$F$2:$F$268,"Included",'Source Data'!$E$2:$E$268,"Week 1",'Source Data'!$A$2:$A$268,"Direct & Organic") -> 288772.84 | J8: =SUMIFS('Source Data'!$P$2:$P$268,'Source Data'!$F$2:$F$268,"Included",'Source Data'!$E$2:$E$268,"Week 1",'Source Data'!$A$2:$A$268,"Direct & Organic") -> 100438.4 | K8: =SUMIFS('Source Data'!$R$2:$R$268,'Source Data'!$F$2:$F$268,"Included",'Source Data'!$E$2:$E$268,"Week 1",'Source Data'!$A$2:$A$268,"Direct & Organic") -> 0 | L8: =IFERROR(D8/C8,0) -> 15250.9 | M8: =IFERROR(F8/D8,0) -> 0.50922034
A9: Week 1 | B9: Referral | C9: =COUNTIFS('Source Data'!$F$2:$F$268,"Included",'Source Data'!$E$2:$E$268,"Week 1",'Source Data'!$A$2:$A$268,"Referral") -> 5 | D9: =SUMIFS('Source Data'!$K$2:$K$268,'Source Data'!$F$2:$F$268,"Included",'Source Data'!$E$2:$E$268,"Week 1",'Source Data'!$A$2:$A$268,"Referral") -> 90845.09 | E9: =SUMIFS('Source Data'!$N$2:$N$268,'Source Data'!$F$2:$F$268,"Included",'Source Data'!$E$2:$E$268,"Week 1",'Source Data'!$A$2:$A$268,"Referral") -> 2 | F9: =SUMIFS('Source Data'!$L$2:$L$268,'Source Data'!$F$2:$F$268,"Included",'Source Data'!$E$2:$E$268,"Week 1",'Source Data'!$A$2:$A$268,"Referral") -> 76986.61 | G9: =IFERROR(E9/C9,0) -> 0.4 | H9: =SUMIFS('Source Data'!$O$2:$O$268,'Source Data'!$F$2:$F$268,"Included",'Source Data'!$E$2:$E$268,"Week 1",'Source Data'!$A$2:$A$268,"Referral") -> 2 | I9: =SUMIFS('Source Data'!$Q$2:$Q$268,'Source Data'!$F$2:$F$268,"Included",'Source Data'!$E$2:$E$268,"Week 1",'Source Data'!$A$2:$A$268,"Referral") -> 7907.59 | J9: =SUMIFS('Source Data'!$P$2:$P$268,'Source Data'!$F$2:$F$268,"Included",'Source Data'!$E$2:$E$268,"Week 1",'Source Data'!$A$2:$A$268,"Referral") -> 5950.89 | K9: =SUMIFS('Source Data'!$R$2:$R$268,'Source Data'!$F$2:$F$268,"Included",'Source Data'!$E$2:$E$268,"Week 1",'Source Data'!$A$2:$A$268,"Referral") -> 0 | L9: =IFERROR(D9/C9,0) -> 18169.018 | M9: =IFERROR(F9/D9,0) -> 0.84744932
A10: Week 2 | B10: Google Ads | C10: =COUNTIFS('Source Data'!$F$2:$F$268,"Included",'Source Data'!$E$2:$E$268,"Week 2",'Source Data'!$A$2:$A$268,"Google Ads") -> 12 | D10: =SUMIFS('Source Data'!$K$2:$K$268,'Source Data'!$F$2:$F$268,"Included",'Source Data'!$E$2:$E$268,"Week 2",'Source Data'!$A$2:$A$268,"Google Ads") -> 232561.16 | E10: =SUMIFS('Source Data'!$N$2:$N$268,'Source Data'!$F$2:$F$268,"Included",'Source Data'!$E$2:$E$268,"Week 2",'Source Data'!$A$2:$A$268,"Google Ads") -> 4 | F10: =SUMIFS('Source Data'!$L$2:$L$268,'Source Data'!$F$2:$F$268,"Included",'Source Data'!$E$2:$E$268,"Week 2",'Source Data'!$A$2:$A$268,"Google Ads") -> 85278.66 | G10: =IFERROR(E10/C10,0) -> 0.33333333 | H10: =SUMIFS('Source Data'!$O$2:$O$268,'Source Data'!$F$2:$F$268,"Included",'Source Data'!$E$2:$E$268,"Week 2",'Source Data'!$A$2:$A$268,"Google Ads") -> 4 | I10: =SUMIFS('Source Data'!$Q$2:$Q$268,'Source Data'!$F$2:$F$268,"Included",'Source Data'!$E$2:$E$268,"Week 2",'Source Data'!$A$2:$A$268,"Google Ads") -> 81415.88 | J10: =SUMIFS('Source Data'!$P$2:$P$268,'Source Data'!$F$2:$F$268,"Included",'Source Data'!$E$2:$E$268,"Week 2",'Source Data'!$A$2:$A$268,"Google Ads") -> 65866.62 | K10: =SUMIFS('Source Data'!$R$2:$R$268,'Source Data'!$F$2:$F$268,"Included",'Source Data'!$E$2:$E$268,"Week 2",'Source Data'!$A$2:$A$268,"Google Ads") -> 0 | L10: =IFERROR(D10/C10,0) -> 19380.097 | M10: =IFERROR(F10/D10,0) -> 0.36669348
A11: Week 2 | B11: Direct & Organic | C11: =COUNTIFS('Source Data'!$F$2:$F$268,"Included",'Source Data'!$E$2:$E$268,"Week 2",'Source Data'!$A$2:$A$268,"Direct & Organic") -> 58 | D11: =SUMIFS('Source Data'!$K$2:$K$268,'Source Data'!$F$2:$F$268,"Included",'Source Data'!$E$2:$E$268,"Week 2",'Source Data'!$A$2:$A$268,"Direct & Organic") -> 1071885 | E11: =SUMIFS('Source Data'!$N$2:$N$268,'Source Data'!$F$2:$F$268,"Included",'Source Data'!$E$2:$E$268,"Week 2",'Source Data'!$A$2:$A$268,"Direct & Organic") -> 30 | F11: =SUMIFS('Source Data'!$L$2:$L$268,'Source Data'!$F$2:$F$268,"Included",'Source Data'!$E$2:$E$268,"Week 2",'Source Data'!$A$2:$A$268,"Direct & Organic") -> 601332.86 | G11: =IFERROR(E11/C11,0) -> 0.51724138 | H11: =SUMIFS('Source Data'!$O$2:$O$268,'Source Data'!$F$2:$F$268,"Included",'Source Data'!$E$2:$E$268,"Week 2",'Source Data'!$A$2:$A$268,"Direct & Organic") -> 17 | I11: =SUMIFS('Source Data'!$Q$2:$Q$268,'Source Data'!$F$2:$F$268,"Included",'Source Data'!$E$2:$E$268,"Week 2",'Source Data'!$A$2:$A$268,"Direct & Organic") -> 312359.55 | J11: =SUMIFS('Source Data'!$P$2:$P$268,'Source Data'!$F$2:$F$268,"Included",'Source Data'!$E$2:$E$268,"Week 2",'Source Data'!$A$2:$A$268,"Direct & Organic") -> 126891.49 | K11: =SUMIFS('Source Data'!$R$2:$R$268,'Source Data'!$F$2:$F$268,"Included",'Source Data'!$E$2:$E$268,"Week 2",'Source Data'!$A$2:$A$268,"Direct & Organic") -> 31301.07 | L11: =IFERROR(D11/C11,0) -> 18480.775 | M11: =IFERROR(F11/D11,0) -> 0.56100503
A12: Week 2 | B12: Referral | C12: =COUNTIFS('Source Data'!$F$2:$F$268,"Included",'Source Data'!$E$2:$E$268,"Week 2",'Source Data'!$A$2:$A$268,"Referral") -> 13 | D12: =SUMIFS('Source Data'!$K$2:$K$268,'Source Data'!$F$2:$F$268,"Included",'Source Data'!$E$2:$E$268,"Week 2",'Source Data'!$A$2:$A$268,"Referral") -> 208630.37 | E12: =SUMIFS('Source Data'!$N$2:$N$268,'Source Data'!$F$2:$F$268,"Included",'Source Data'!$E$2:$E$268,"Week 2",'Source Data'!$A$2:$A$268,"Referral") -> 5 | F12: =SUMIFS('Source Data'!$L$2:$L$268,'Source Data'!$F$2:$F$268,"Included",'Source Data'!$E$2:$E$268,"Week 2",'Source Data'!$A$2:$A$268,"Referral") -> 125783.22 | G12: =IFERROR(E12/C12,0) -> 0.38461538 | H12: =SUMIFS('Source Data'!$O$2:$O$268,'Source Data'!$F$2:$F$268,"Included",'Source Data'!$E$2:$E$268,"Week 2",'Source Data'!$A$2:$A$268,"Referral") -> 3 | I12: =SUMIFS('Source Data'!$Q$2:$Q$268,'Source Data'!$F$2:$F$268,"Included",'Source Data'!$E$2:$E$268,"Week 2",'Source Data'!$A$2:$A$268,"Referral") -> 43421.96 | J12: =SUMIFS('Source Data'!$P$2:$P$268,'Source Data'!$F$2:$F$268,"Included",'Source Data'!$E$2:$E$268,"Week 2",'Source Data'!$A$2:$A$268,"Referral") -> 28484.65 | K12: =SUMIFS('Source Data'!$R$2:$R$268,'Source Data'!$F$2:$F$268,"Included",'Source Data'!$E$2:$E$268,"Week 2",'Source Data'!$A$2:$A$268,"Referral") -> 10940.54 | L12: =IFERROR(D12/C12,0) -> 16048.49 | M12: =IFERROR(F12/D12,0) -> 0.60289986
A13: Week 3 | B13: Google Ads | C13: =COUNTIFS('Source Data'!$F$2:$F$268,"Included",'Source Data'!$E$2:$E$268,"Week 3",'Source Data'!$A$2:$A$268,"Google Ads") -> 22 | D13: =SUMIFS('Source Data'!$K$2:$K$268,'Source Data'!$F$2:$F$268,"Included",'Source Data'!$E$2:$E$268,"Week 3",'Source Data'!$A$2:$A$268,"Google Ads") -> 552631.53 | E13: =SUMIFS('Source Data'!$N$2:$N$268,'Source Data'!$F$2:$F$268,"Included",'Source Data'!$E$2:$E$268,"Week 3",'Source Data'!$A$2:$A$268,"Google Ads") -> 7 | F13: =SUMIFS('Source Data'!$L$2:$L$268,'Source Data'!$F$2:$F$268,"Included",'Source Data'!$E$2:$E$268,"Week 3",'Source Data'!$A$2:$A$268,"Google Ads") -> 100852.85 | G13: =IFERROR(E13/C13,0) -> 0.31818182 | H13: =SUMIFS('Source Data'!$O$2:$O$268,'Source Data'!$F$2:$F$268,"Included",'Source Data'!$E$2:$E$268,"Week 3",'Source Data'!$A$2:$A$268,"Google Ads") -> 5 | I13: =SUMIFS('Source Data'!$Q$2:$Q$268,'Source Data'!$F$2:$F$268,"Included",'Source Data'!$E$2:$E$268,"Week 3",'Source Data'!$A$2:$A$268,"Google Ads") -> 70828.57 | J13: =SUMIFS('Source Data'!$P$2:$P$268,'Source Data'!$F$2:$F$268,"Included",'Source Data'!$E$2:$E$268,"Week 3",'Source Data'!$A$2:$A$268,"Google Ads") -> 370009.57 | K13: =SUMIFS('Source Data'!$R$2:$R$268,'Source Data'!$F$2:$F$268,"Included",'Source Data'!$E$2:$E$268,"Week 3",'Source Data'!$A$2:$A$268,"Google Ads") -> 10940.54 | L13: =IFERROR(D13/C13,0) -> 25119.615 | M13: =IFERROR(F13/D13,0) -> 0.18249565
A14: Week 3 | B14: Direct & Organic | C14: =COUNTIFS('Source Data'!$F$2:$F$268,"Included",'Source Data'!$E$2:$E$268,"Week 3",'Source Data'!$A$2:$A$268,"Direct & Organic") -> 41 | D14: =SUMIFS('Source Data'!$K$2:$K$268,'Source Data'!$F$2:$F$268,"Included",'Source Data'!$E$2:$E$268,"Week 3",'Source Data'!$A$2:$A$268,"Direct & Organic") -> 684801.78 | E14: =SUMIFS('Source Data'!$N$2:$N$268,'Source Data'!$F$2:$F$268,"Included",'Source Data'!$E$2:$E$268,"Week 3",'Source Data'!$A$2:$A$268,"Direct & Organic") -> 18 | F14: =SUMIFS('Source Data'!$L$2:$L$268,'Source Data'!$F$2:$F$268,"Included",'Source Data'!$E$2:$E$268,"Week 3",'Source Data'!$A$2:$A$268,"Direct & Organic") -> 302360.43 | G14: =IFERROR(E14/C14,0) -> 0.43902439 | H14: =SUMIFS('Source Data'!$O$2:$O$268,'Source Data'!$F$2:$F$268,"Included",'Source Data'!$E$2:$E$268,"Week 3",'Source Data'!$A$2:$A$268,"Direct & Organic") -> 11 | I14: =SUMIFS('Source Data'!$Q$2:$Q$268,'Source Data'!$F$2:$F$268,"Included",'Source Data'!$E$2:$E$268,"Week 3",'Source Data'!$A$2:$A$268,"Direct & Organic") -> 224396.61 | J14: =SUMIFS('Source Data'!$P$2:$P$268,'Source Data'!$F$2:$F$268,"Included",'Source Data'!$E$2:$E$268,"Week 3",'Source Data'!$A$2:$A$268,"Direct & Organic") -> 129069.74 | K14: =SUMIFS('Source Data'!$R$2:$R$268,'Source Data'!$F$2:$F$268,"Included",'Source Data'!$E$2:$E$268,"Week 3",'Source Data'!$A$2:$A$268,"Direct & Organic") -> 28975 | L14: =IFERROR(D14/C14,0) -> 16702.482 | M14: =IFERROR(F14/D14,0) -> 0.44152985
A15: Week 3 | B15: Referral | C15: =COUNTIFS('Source Data'!$F$2:$F$268,"Included",'Source Data'!$E$2:$E$268,"Week 3",'Source Data'!$A$2:$A$268,"Referral") -> 8 | D15: =SUMIFS('Source Data'!$K$2:$K$268,'Source Data'!$F$2:$F$268,"Included",'Source Data'!$E$2:$E$268,"Week 3",'Source Data'!$A$2:$A$268,"Referral") -> 134840.53 | E15: =SUMIFS('Source Data'!$N$2:$N$268,'Source Data'!$F$2:$F$268,"Included",'Source Data'!$E$2:$E$268,"Week 3",'Source Data'!$A$2:$A$268,"Referral") -> 3 | F15: =SUMIFS('Source Data'!$L$2:$L$268,'Source Data'!$F$2:$F$268,"Included",'Source Data'!$E$2:$E$268,"Week 3",'Source Data'!$A$2:$A$268,"Referral") -> 70459.11 | G15: =IFERROR(E15/C15,0) -> 0.375 | H15: =SUMIFS('Source Data'!$O$2:$O$268,'Source Data'!$F$2:$F$268,"Included",'Source Data'!$E$2:$E$268,"Week 3",'Source Data'!$A$2:$A$268,"Referral") -> 4 | I15: =SUMIFS('Source Data'!$Q$2:$Q$268,'Source Data'!$F$2:$F$268,"Included",'Source Data'!$E$2:$E$268,"Week 3",'Source Data'!$A$2:$A$268,"Referral") -> 50646.24 | J15: =SUMIFS('Source Data'!$P$2:$P$268,'Source Data'!$F$2:$F$268,"Included",'Source Data'!$E$2:$E$268,"Week 3",'Source Data'!$A$2:$A$268,"Referral") -> 13735.18 | K15: =SUMIFS('Source Data'!$R$2:$R$268,'Source Data'!$F$2:$F$268,"Included",'Source Data'!$E$2:$E$268,"Week 3",'Source Data'!$A$2:$A$268,"Referral") -> 0 | L15: =IFERROR(D15/C15,0) -> 16855.066 | M15: =IFERROR(F15/D15,0) -> 0.52253658
A16: Week 4 | B16: Google Ads | C16: =COUNTIFS('Source Data'!$F$2:$F$268,"Included",'Source Data'!$E$2:$E$268,"Week 4",'Source Data'!$A$2:$A$268,"Google Ads") -> 9 | D16: =SUMIFS('Source Data'!$K$2:$K$268,'Source Data'!$F$2:$F$268,"Included",'Source Data'!$E$2:$E$268,"Week 4",'Source Data'!$A$2:$A$268,"Google Ads") -> 165308.48 | E16: =SUMIFS('Source Data'!$N$2:$N$268,'Source Data'!$F$2:$F$268,"Included",'Source Data'!$E$2:$E$268,"Week 4",'Source Data'!$A$2:$A$268,"Google Ads") -> 0 | F16: =SUMIFS('Source Data'!$L$2:$L$268,'Source Data'!$F$2:$F$268,"Included",'Source Data'!$E$2:$E$268,"Week 4",'Source Data'!$A$2:$A$268,"Google Ads") -> 0 | G16: =IFERROR(E16/C16,0) -> 0 | H16: =SUMIFS('Source Data'!$O$2:$O$268,'Source Data'!$F$2:$F$268,"Included",'Source Data'!$E$2:$E$268,"Week 4",'Source Data'!$A$2:$A$268,"Google Ads") -> 3 | I16: =SUMIFS('Source Data'!$Q$2:$Q$268,'Source Data'!$F$2:$F$268,"Included",'Source Data'!$E$2:$E$268,"Week 4",'Source Data'!$A$2:$A$268,"Google Ads") -> 63031.24 | J16: =SUMIFS('Source Data'!$P$2:$P$268,'Source Data'!$F$2:$F$268,"Included",'Source Data'!$E$2:$E$268,"Week 4",'Source Data'!$A$2:$A$268,"Google Ads") -> 102277.24 | K16: =SUMIFS('Source Data'!$R$2:$R$268,'Source Data'!$F$2:$F$268,"Included",'Source Data'!$E$2:$E$268,"Week 4",'Source Data'!$A$2:$A$268,"Google Ads") -> 0 | L16: =IFERROR(D16/C16,0) -> 18367.609 | M16: =IFERROR(F16/D16,0) -> 0
A17: Week 4 | B17: Direct & Organic | C17: =COUNTIFS('Source Data'!$F$2:$F$268,"Included",'Source Data'!$E$2:$E$268,"Week 4",'Source Data'!$A$2:$A$268,"Direct & Organic") -> 16 | D17: =SUMIFS('Source Data'!$K$2:$K$268,'Source Data'!$F$2:$F$268,"Included",'Source Data'!$E$2:$E$268,"Week 4",'Source Data'!$A$2:$A$268,"Direct & Organic") -> 312389.11 | E17: =SUMIFS('Source Data'!$N$2:$N$268,'Source Data'!$F$2:$F$268,"Included",'Source Data'!$E$2:$E$268,"Week 4",'Source Data'!$A$2:$A$268,"Direct & Organic") -> 0 | F17: =SUMIFS('Source Data'!$L$2:$L$268,'Source Data'!$F$2:$F$268,"Included",'Source Data'!$E$2:$E$268,"Week 4",'Source Data'!$A$2:$A$268,"Direct & Organic") -> 0 | G17: =IFERROR(E17/C17,0) -> 0 | H17: =SUMIFS('Source Data'!$O$2:$O$268,'Source Data'!$F$2:$F$268,"Included",'Source Data'!$E$2:$E$268,"Week 4",'Source Data'!$A$2:$A$268,"Direct & Organic") -> 1 | I17: =SUMIFS('Source Data'!$Q$2:$Q$268,'Source Data'!$F$2:$F$268,"Included",'Source Data'!$E$2:$E$268,"Week 4",'Source Data'!$A$2:$A$268,"Direct & Organic") -> 7812.14 | J17: =SUMIFS('Source Data'!$P$2:$P$268,'Source Data'!$F$2:$F$268,"Included",'Source Data'!$E$2:$E$268,"Week 4",'Source Data'!$A$2:$A$268,"Direct & Organic") -> 304576.97 | K17: =SUMIFS('Source Data'!$R$2:$R$268,'Source Data'!$F$2:$F$268,"Included",'Source Data'!$E$2:$E$268,"Week 4",'Source Data'!$A$2:$A$268,"Direct & Organic") -> 0 | L17: =IFERROR(D17/C17,0) -> 19524.319 | M17: =IFERROR(F17/D17,0) -> 0
A18: Week 4 | B18: Referral | C18: =COUNTIFS('Source Data'!$F$2:$F$268,"Included",'Source Data'!$E$2:$E$268,"Week 4",'Source Data'!$A$2:$A$268,"Referral") -> 2 | D18: =SUMIFS('Source Data'!$K$2:$K$268,'Source Data'!$F$2:$F$268,"Included",'Source Data'!$E$2:$E$268,"Week 4",'Source Data'!$A$2:$A$268,"Referral") -> 30268.12 | E18: =SUMIFS('Source Data'!$N$2:$N$268,'Source Data'!$F$2:$F$268,"Included",'Source Data'!$E$2:$E$268,"Week 4",'Source Data'!$A$2:$A$268,"Referral") -> 0 | F18: =SUMIFS('Source Data'!$L$2:$L$268,'Source Data'!$F$2:$F$268,"Included",'Source Data'!$E$2:$E$268,"Week 4",'Source Data'!$A$2:$A$268,"Referral") -> 0 | G18: =IFERROR(E18/C18,0) -> 0 | H18: =SUMIFS('Source Data'!$O$2:$O$268,'Source Data'!$F$2:$F$268,"Included",'Source Data'!$E$2:$E$268,"Week 4",'Source Data'!$A$2:$A$268,"Referral") -> 2 | I18: =SUMIFS('Source Data'!$Q$2:$Q$268,'Source Data'!$F$2:$F$268,"Included",'Source Data'!$E$2:$E$268,"Week 4",'Source Data'!$A$2:$A$268,"Referral") -> 30268.12 | J18: =SUMIFS('Source Data'!$P$2:$P$268,'Source Data'!$F$2:$F$268,"Included",'Source Data'!$E$2:$E$268,"Week 4",'Source Data'!$A$2:$A$268,"Referral") -> 0 | K18: =SUMIFS('Source Data'!$R$2:$R$268,'Source Data'!$F$2:$F$268,"Included",'Source Data'!$E$2:$E$268,"Week 4",'Source Data'!$A$2:$A$268,"Referral") -> 0 | L18: =IFERROR(D18/C18,0) -> 15134.06 | M18: =IFERROR(F18/D18,0) -> 0

Sheet Customer Type
A1: Customer Type
A3: September 1–24 only. Order values are counted once; status reflects the backend snapshot.
A6: Customer type | B6: Orders | C6: Net sales | D6: Fulfilled orders | E6: Fulfilled net revenue | F6: Fulfillment rate | G6: Cancelled orders | H6: Cancelled net value | I6: Open net value | J6: Return refund net value | K6: Net value per order | L6: Fulfilled value share
A7: Chatbot | B7: =COUNTIFS('Source Data'!$F$2:$F$268,"Included",'Source Data'!$G$2:$G$268,"Chatbot") -> 1 | C7: =SUMIFS('Source Data'!$K$2:$K$268,'Source Data'!$F$2:$F$268,"Included",'Source Data'!$G$2:$G$268,"Chatbot") -> 71428.57 | D7: =SUMIFS('Source Data'!$N$2:$N$268,'Source Data'!$F$2:$F$268,"Included",'Source Data'!$G$2:$G$268,"Chatbot") -> 0 | E7: =SUMIFS('Source Data'!$L$2:$L$268,'Source Data'!$F$2:$F$268,"Included",'Source Data'!$G$2:$G$268,"Chatbot") -> 0 | F7: =IFERROR(D7/B7,0) -> 0 | G7: =SUMIFS('Source Data'!$O$2:$O$268,'Source Data'!$F$2:$F$268,"Included",'Source Data'!$G$2:$G$268,"Chatbot") -> 0 | H7: =SUMIFS('Source Data'!$Q$2:$Q$268,'Source Data'!$F$2:$F$268,"Included",'Source Data'!$G$2:$G$268,"Chatbot") -> 0 | I7: =SUMIFS('Source Data'!$P$2:$P$268,'Source Data'!$F$2:$F$268,"Included",'Source Data'!$G$2:$G$268,"Chatbot") -> 71428.57 | J7: =SUMIFS('Source Data'!$R$2:$R$268,'Source Data'!$F$2:$F$268,"Included",'Source Data'!$G$2:$G$268,"Chatbot") -> 0 | K7: =IFERROR(C7/B7,0) -> 71428.57 | L7: =IFERROR(E7/C7,0) -> 0
A8: Fb | B8: =COUNTIFS('Source Data'!$F$2:$F$268,"Included",'Source Data'!$G$2:$G$268,"Fb") -> 9 | C8: =SUMIFS('Source Data'!$K$2:$K$268,'Source Data'!$F$2:$F$268,"Included",'Source Data'!$G$2:$G$268,"Fb") -> 144461.16 | D8: =SUMIFS('Source Data'!$N$2:$N$268,'Source Data'!$F$2:$F$268,"Included",'Source Data'!$G$2:$G$268,"Fb") -> 8 | E8: =SUMIFS('Source Data'!$L$2:$L$268,'Source Data'!$F$2:$F$268,"Included",'Source Data'!$G$2:$G$268,"Fb") -> 128788.48 | F8: =IFERROR(D8/B8,0) -> 0.88888889 | G8: =SUMIFS('Source Data'!$O$2:$O$268,'Source Data'!$F$2:$F$268,"Included",'Source Data'!$G$2:$G$268,"Fb") -> 0 | H8: =SUMIFS('Source Data'!$Q$2:$Q$268,'Source Data'!$F$2:$F$268,"Included",'Source Data'!$G$2:$G$268,"Fb") -> 0 | I8: =SUMIFS('Source Data'!$P$2:$P$268,'Source Data'!$F$2:$F$268,"Included",'Source Data'!$G$2:$G$268,"Fb") -> 15672.68 | J8: =SUMIFS('Source Data'!$R$2:$R$268,'Source Data'!$F$2:$F$268,"Included",'Source Data'!$G$2:$G$268,"Fb") -> 0 | K8: =IFERROR(C8/B8,0) -> 16051.24 | L8: =IFERROR(E8/C8,0) -> 0.89150939
A9: Website | B9: =COUNTIFS('Source Data'!$F$2:$F$268,"Included",'Source Data'!$G$2:$G$268,"Website") -> 252 | C9: =SUMIFS('Source Data'!$K$2:$K$268,'Source Data'!$F$2:$F$268,"Included",'Source Data'!$G$2:$G$268,"Website") -> 4583926.5 | D9: =SUMIFS('Source Data'!$N$2:$N$268,'Source Data'!$F$2:$F$268,"Included",'Source Data'!$G$2:$G$268,"Website") -> 103 | E9: =SUMIFS('Source Data'!$L$2:$L$268,'Source Data'!$F$2:$F$268,"Included",'Source Data'!$G$2:$G$268,"Website") -> 1962676.8 | F9: =IFERROR(D9/B9,0) -> 0.40873016 | G9: =SUMIFS('Source Data'!$O$2:$O$268,'Source Data'!$F$2:$F$268,"Included",'Source Data'!$G$2:$G$268,"Website") -> 79 | H9: =SUMIFS('Source Data'!$Q$2:$Q$268,'Source Data'!$F$2:$F$268,"Included",'Source Data'!$G$2:$G$268,"Website") -> 1293777 | I9: =SUMIFS('Source Data'!$P$2:$P$268,'Source Data'!$F$2:$F$268,"Included",'Source Data'!$G$2:$G$268,"Website") -> 1245315.6 | J9: =SUMIFS('Source Data'!$R$2:$R$268,'Source Data'!$F$2:$F$268,"Included",'Source Data'!$G$2:$G$268,"Website") -> 82157.15 | K9: =IFERROR(C9/B9,0) -> 18190.185 | L9: =IFERROR(E9/C9,0) -> 0.42816498

Sheet Channel Customer Type
A1: Channel Customer Type
A3: September 1–24 only. Order values are counted once; status reflects the backend snapshot.
A6: Channel | B6: Customer type | C6: Orders | D6: Net sales | E6: Fulfilled orders | F6: Fulfilled net revenue | G6: Fulfillment rate | H6: Cancelled orders | I6: Cancelled net value | J6: Open net value | K6: Return refund net value | L6: Net value per order | M6: Fulfilled value share
A7: Google Ads | B7: Chatbot | C7: =COUNTIFS('Source Data'!$F$2:$F$268,"Included",'Source Data'!$A$2:$A$268,"Google Ads",'Source Data'!$G$2:$G$268,"Chatbot") -> 0 | D7: =SUMIFS('Source Data'!$K$2:$K$268,'Source Data'!$F$2:$F$268,"Included",'Source Data'!$A$2:$A$268,"Google Ads",'Source Data'!$G$2:$G$268,"Chatbot") -> 0 | E7: =SUMIFS('Source Data'!$N$2:$N$268,'Source Data'!$F$2:$F$268,"Included",'Source Data'!$A$2:$A$268,"Google Ads",'Source Data'!$G$2:$G$268,"Chatbot") -> 0 | F7: =SUMIFS('Source Data'!$L$2:$L$268,'Source Data'!$F$2:$F$268,"Included",'Source Data'!$A$2:$A$268,"Google Ads",'Source Data'!$G$2:$G$268,"Chatbot") -> 0 | G7: =IFERROR(E7/C7,0) -> 0 | H7: =SUMIFS('Source Data'!$O$2:$O$268,'Source Data'!$F$2:$F$268,"Included",'Source Data'!$A$2:$A$268,"Google Ads",'Source Data'!$G$2:$G$268,"Chatbot") -> 0 | I7: =SUMIFS('Source Data'!$Q$2:$Q$268,'Source Data'!$F$2:$F$268,"Included",'Source Data'!$A$2:$A$268,"Google Ads",'Source Data'!$G$2:$G$268,"Chatbot") -> 0 | J7: =SUMIFS('Source Data'!$P$2:$P$268,'Source Data'!$F$2:$F$268,"Included",'Source Data'!$A$2:$A$268,"Google Ads",'Source Data'!$G$2:$G$268,"Chatbot") -> 0 | K7: =SUMIFS('Source Data'!$R$2:$R$268,'Source Data'!$F$2:$F$268,"Included",'Source Data'!$A$2:$A$268,"Google Ads",'Source Data'!$G$2:$G$268,"Chatbot") -> 0 | L7: =IFERROR(D7/C7,0) -> 0 | M7: =IFERROR(F7/D7,0) -> 0
A8: Google Ads | B8: Fb | C8: =COUNTIFS('Source Data'!$F$2:$F$268,"Included",'Source Data'!$A$2:$A$268,"Google Ads",'Source Data'!$G$2:$G$268,"Fb") -> 0 | D8: =SUMIFS('Source Data'!$K$2:$K$268,'Source Data'!$F$2:$F$268,"Included",'Source Data'!$A$2:$A$268,"Google Ads",'Source Data'!$G$2:$G$268,"Fb") -> 0 | E8: =SUMIFS('Source Data'!$N$2:$N$268,'Source Data'!$F$2:$F$268,"Included",'Source Data'!$A$2:$A$268,"Google Ads",'Source Data'!$G$2:$G$268,"Fb") -> 0 | F8: =SUMIFS('Source Data'!$L$2:$L$268,'Source Data'!$F$2:$F$268,"Included",'Source Data'!$A$2:$A$268,"Google Ads",'Source Data'!$G$2:$G$268,"Fb") -> 0 | G8: =IFERROR(E8/C8,0) -> 0 | H8: =SUMIFS('Source Data'!$O$2:$O$268,'Source Data'!$F$2:$F$268,"Included",'Source Data'!$A$2:$A$268,"Google Ads",'Source Data'!$G$2:$G$268,"Fb") -> 0 | I8: =SUMIFS('Source Data'!$Q$2:$Q$268,'Source Data'!$F$2:$F$268,"Included",'Source Data'!$A$2:$A$268,"Google Ads",'Source Data'!$G$2:$G$268,"Fb") -> 0 | J8: =SUMIFS('Source Data'!$P$2:$P$268,'Source Data'!$F$2:$F$268,"Included",'Source Data'!$A$2:$A$268,"Google Ads",'Source Data'!$G$2:$G$268,"Fb") -> 0 | K8: =SUMIFS('Source Data'!$R$2:$R$268,'Source Data'!$F$2:$F$268,"Included",'Source Data'!$A$2:$A$268,"Google Ads",'Source Data'!$G$2:$G$268,"Fb") -> 0 | L8: =IFERROR(D8/C8,0) -> 0 | M8: =IFERROR(F8/D8,0) -> 0
A9: Google Ads | B9: Website | C9: =COUNTIFS('Source Data'!$F$2:$F$268,"Included",'Source Data'!$A$2:$A$268,"Google Ads",'Source Data'!$G$2:$G$268,"Website") -> 67 | D9: =SUMIFS('Source Data'!$K$2:$K$268,'Source Data'!$F$2:$F$268,"Included",'Source Data'!$A$2:$A$268,"Google Ads",'Source Data'!$G$2:$G$268,"Website") -> 1473109.5 | E9: =SUMIFS('Source Data'!$N$2:$N$268,'Source Data'!$F$2:$F$268,"Included",'Source Data'!$A$2:$A$268,"Google Ads",'Source Data'!$G$2:$G$268,"Website") -> 26 | F9: =SUMIFS('Source Data'!$L$2:$L$268,'Source Data'!$F$2:$F$268,"Included",'Source Data'!$A$2:$A$268,"Google Ads",'Source Data'!$G$2:$G$268,"Website") -> 510707.5 | G9: =IFERROR(E9/C9,0) -> 0.3880597 | H9: =SUMIFS('Source Data'!$O$2:$O$268,'Source Data'!$F$2:$F$268,"Included",'Source Data'!$A$2:$A$268,"Google Ads",'Source Data'!$G$2:$G$268,"Website") -> 18 | I9: =SUMIFS('Source Data'!$Q$2:$Q$268,'Source Data'!$F$2:$F$268,"Included",'Source Data'!$A$2:$A$268,"Google Ads",'Source Data'!$G$2:$G$268,"Website") -> 328191.94 | J9: =SUMIFS('Source Data'!$P$2:$P$268,'Source Data'!$F$2:$F$268,"Included",'Source Data'!$A$2:$A$268,"Google Ads",'Source Data'!$G$2:$G$268,"Website") -> 623269.5 | K9: =SUMIFS('Source Data'!$R$2:$R$268,'Source Data'!$F$2:$F$268,"Included",'Source Data'!$A$2:$A$268,"Google Ads",'Source Data'!$G$2:$G$268,"Website") -> 10940.54 | L9: =IFERROR(D9/C9,0) -> 21986.709 | M9: =IFERROR(F9/D9,0) -> 0.34668672
A10: Direct & Organic | B10: Chatbot | C10: =COUNTIFS('Source Data'!$F$2:$F$268,"Included",'Source Data'!$A$2:$A$268,"Direct & Organic",'Source Data'!$G$2:$G$268,"Chatbot") -> 1 | D10: =SUMIFS('Source Data'!$K$2:$K$268,'Source Data'!$F$2:$F$268,"Included",'Source Data'!$A$2:$A$268,"Direct & Organic",'Source Data'!$G$2:$G$268,"Chatbot") -> 71428.57 | E10: =SUMIFS('Source Data'!$N$2:$N$268,'Source Data'!$F$2:$F$268,"Included",'Source Data'!$A$2:$A$268,"Direct & Organic",'Source Data'!$G$2:$G$268,"Chatbot") -> 0 | F10: =SUMIFS('Source Data'!$L$2:$L$268,'Source Data'!$F$2:$F$268,"Included",'Source Data'!$A$2:$A$268,"Direct & Organic",'Source Data'!$G$2:$G$268,"Chatbot") -> 0 | G10: =IFERROR(E10/C10,0) -> 0 | H10: =SUMIFS('Source Data'!$O$2:$O$268,'Source Data'!$F$2:$F$268,"Included",'Source Data'!$A$2:$A$268,"Direct & Organic",'Source Data'!$G$2:$G$268,"Chatbot") -> 0 | I10: =SUMIFS('Source Data'!$Q$2:$Q$268,'Source Data'!$F$2:$F$268,"Included",'Source Data'!$A$2:$A$268,"Direct & Organic",'Source Data'!$G$2:$G$268,"Chatbot") -> 0 | J10: =SUMIFS('Source Data'!$P$2:$P$268,'Source Data'!$F$2:$F$268,"Included",'Source Data'!$A$2:$A$268,"Direct & Organic",'Source Data'!$G$2:$G$268,"Chatbot") -> 71428.57 | K10: =SUMIFS('Source Data'!$R$2:$R$268,'Source Data'!$F$2:$F$268,"Included",'Source Data'!$A$2:$A$268,"Direct & Organic",'Source Data'!$G$2:$G$268,"Chatbot") -> 0 | L10: =IFERROR(D10/C10,0) -> 71428.57 | M10: =IFERROR(F10/D10,0) -> 0
A11: Direct & Organic | B11: Fb | C11: =COUNTIFS('Source Data'!$F$2:$F$268,"Included",'Source Data'!$A$2:$A$268,"Direct & Organic",'Source Data'!$G$2:$G$268,"Fb") -> 9 | D11: =SUMIFS('Source Data'!$K$2:$K$268,'Source Data'!$F$2:$F$268,"Included",'Source Data'!$A$2:$A$268,"Direct & Organic",'Source Data'!$G$2:$G$268,"Fb") -> 144461.16 | E11: =SUMIFS('Source Data'!$N$2:$N$268,'Source Data'!$F$2:$F$268,"Included",'Source Data'!$A$2:$A$268,"Direct & Organic",'Source Data'!$G$2:$G$268,"Fb") -> 8 | F11: =SUMIFS('Source Data'!$L$2:$L$268,'Source Data'!$F$2:$F$268,"Included",'Source Data'!$A$2:$A$268,"Direct & Organic",'Source Data'!$G$2:$G$268,"Fb") -> 128788.48 | G11: =IFERROR(E11/C11,0) -> 0.88888889 | H11: =SUMIFS('Source Data'!$O$2:$O$268,'Source Data'!$F$2:$F$268,"Included",'Source Data'!$A$2:$A$268,"Direct & Organic",'Source Data'!$G$2:$G$268,"Fb") -> 0 | I11: =SUMIFS('Source Data'!$Q$2:$Q$268,'Source Data'!$F$2:$F$268,"Included",'Source Data'!$A$2:$A$268,"Direct & Organic",'Source Data'!$G$2:$G$268,"Fb") -> 0 | J11: =SUMIFS('Source Data'!$P$2:$P$268,'Source Data'!$F$2:$F$268,"Included",'Source Data'!$A$2:$A$268,"Direct & Organic",'Source Data'!$G$2:$G$268,"Fb") -> 15672.68 | K11: =SUMIFS('Source Data'!$R$2:$R$268,'Source Data'!$F$2:$F$268,"Included",'Source Data'!$A$2:$A$268,"Direct & Organic",'Source Data'!$G$2:$G$268,"Fb") -> 0 | L11: =IFERROR(D11/C11,0) -> 16051.24 | M11: =IFERROR(F11/D11,0) -> 0.89150939
A12: Direct & Organic | B12: Website | C12: =COUNTIFS('Source Data'!$F$2:$F$268,"Included",'Source Data'!$A$2:$A$268,"Direct & Organic",'Source Data'!$G$2:$G$268,"Website") -> 157 | D12: =SUMIFS('Source Data'!$K$2:$K$268,'Source Data'!$F$2:$F$268,"Included",'Source Data'!$A$2:$A$268,"Direct & Organic",'Source Data'!$G$2:$G$268,"Website") -> 2646232.9 | E12: =SUMIFS('Source Data'!$N$2:$N$268,'Source Data'!$F$2:$F$268,"Included",'Source Data'!$A$2:$A$268,"Direct & Organic",'Source Data'!$G$2:$G$268,"Website") -> 67 | F12: =SUMIFS('Source Data'!$L$2:$L$268,'Source Data'!$F$2:$F$268,"Included",'Source Data'!$A$2:$A$268,"Direct & Organic",'Source Data'!$G$2:$G$268,"Website") -> 1178740.4 | G12: =IFERROR(E12/C12,0) -> 0.42675159 | H12: =SUMIFS('Source Data'!$O$2:$O$268,'Source Data'!$F$2:$F$268,"Included",'Source Data'!$A$2:$A$268,"Direct & Organic",'Source Data'!$G$2:$G$268,"Website") -> 50 | I12: =SUMIFS('Source Data'!$Q$2:$Q$268,'Source Data'!$F$2:$F$268,"Included",'Source Data'!$A$2:$A$268,"Direct & Organic",'Source Data'!$G$2:$G$268,"Website") -> 833341.14 | J12: =SUMIFS('Source Data'!$P$2:$P$268,'Source Data'!$F$2:$F$268,"Included",'Source Data'!$A$2:$A$268,"Direct & Organic",'Source Data'!$G$2:$G$268,"Website") -> 573875.35 | K12: =SUMIFS('Source Data'!$R$2:$R$268,'Source Data'!$F$2:$F$268,"Included",'Source Data'!$A$2:$A$268,"Direct & Organic",'Source Data'!$G$2:$G$268,"Website") -> 60276.07 | L12: =IFERROR(D12/C12,0) -> 16854.987 | M12: =IFERROR(F12/D12,0) -> 0.4454409
A13: Referral | B13: Chatbot | C13: =COUNTIFS('Source Data'!$F$2:$F$268,"Included",'Source Data'!$A$2:$A$268,"Referral",'Source Data'!$G$2:$G$268,"Chatbot") -> 0 | D13: =SUMIFS('Source Data'!$K$2:$K$268,'Source Data'!$F$2:$F$268,"Included",'Source Data'!$A$2:$A$268,"Referral",'Source Data'!$G$2:$G$268,"Chatbot") -> 0 | E13: =SUMIFS('Source Data'!$N$2:$N$268,'Source Data'!$F$2:$F$268,"Included",'Source Data'!$A$2:$A$268,"Referral",'Source Data'!$G$2:$G$268,"Chatbot") -> 0 | F13: =SUMIFS('Source Data'!$L$2:$L$268,'Source Data'!$F$2:$F$268,"Included",'Source Data'!$A$2:$A$268,"Referral",'Source Data'!$G$2:$G$268,"Chatbot") -> 0 | G13: =IFERROR(E13/C13,0) -> 0 | H13: =SUMIFS('Source Data'!$O$2:$O$268,'Source Data'!$F$2:$F$268,"Included",'Source Data'!$A$2:$A$268,"Referral",'Source Data'!$G$2:$G$268,"Chatbot") -> 0 | I13: =SUMIFS('Source Data'!$Q$2:$Q$268,'Source Data'!$F$2:$F$268,"Included",'Source Data'!$A$2:$A$268,"Referral",'Source Data'!$G$2:$G$268,"Chatbot") -> 0 | J13: =SUMIFS('Source Data'!$P$2:$P$268,'Source Data'!$F$2:$F$268,"Included",'Source Data'!$A$2:$A$268,"Referral",'Source Data'!$G$2:$G$268,"Chatbot") -> 0 | K13: =SUMIFS('Source Data'!$R$2:$R$268,'Source Data'!$F$2:$F$268,"Included",'Source Data'!$A$2:$A$268,"Referral",'Source Data'!$G$2:$G$268,"Chatbot") -> 0 | L13: =IFERROR(D13/C13,0) -> 0 | M13: =IFERROR(F13/D13,0) -> 0
A14: Referral | B14: Fb | C14: =COUNTIFS('Source Data'!$F$2:$F$268,"Included",'Source Data'!$A$2:$A$268,"Referral",'Source Data'!$G$2:$G$268,"Fb") -> 0 | D14: =SUMIFS('Source Data'!$K$2:$K$268,'Source Data'!$F$2:$F$268,"Included",'Source Data'!$A$2:$A$268,"Referral",'Source Data'!$G$2:$G$268,"Fb") -> 0 | E14: =SUMIFS('Source Data'!$N$2:$N$268,'Source Data'!$F$2:$F$268,"Included",'Source Data'!$A$2:$A$268,"Referral",'Source Data'!$G$2:$G$268,"Fb") -> 0 | F14: =SUMIFS('Source Data'!$L$2:$L$268,'Source Data'!$F$2:$F$268,"Included",'Source Data'!$A$2:$A$268,"Referral",'Source Data'!$G$2:$G$268,"Fb") -> 0 | G14: =IFERROR(E14/C14,0) -> 0 | H14: =SUMIFS('Source Data'!$O$2:$O$268,'Source Data'!$F$2:$F$268,"Included",'Source Data'!$A$2:$A$268,"Referral",'Source Data'!$G$2:$G$268,"Fb") -> 0 | I14: =SUMIFS('Source Data'!$Q$2:$Q$268,'Source Data'!$F$2:$F$268,"Included",'Source Data'!$A$2:$A$268,"Referral",'Source Data'!$G$2:$G$268,"Fb") -> 0 | J14: =SUMIFS('Source Data'!$P$2:$P$268,'Source Data'!$F$2:$F$268,"Included",'Source Data'!$A$2:$A$268,"Referral",'Source Data'!$G$2:$G$268,"Fb") -> 0 | K14: =SUMIFS('Source Data'!$R$2:$R$268,'Source Data'!$F$2:$F$268,"Included",'Source Data'!$A$2:$A$268,"Referral",'Source Data'!$G$2:$G$268,"Fb") -> 0 | L14: =IFERROR(D14/C14,0) -> 0 | M14: =IFERROR(F14/D14,0) -> 0
A15: Referral | B15: Website | C15: =COUNTIFS('Source Data'!$F$2:$F$268,"Included",'Source Data'!$A$2:$A$268,"Referral",'Source Data'!$G$2:$G$268,"Website") -> 28 | D15: =SUMIFS('Source Data'!$K$2:$K$268,'Source Data'!$F$2:$F$268,"Included",'Source Data'!$A$2:$A$268,"Referral",'Source Data'!$G$2:$G$268,"Website") -> 464584.11 | E15: =SUMIFS('Source Data'!$N$2:$N$268,'Source Data'!$F$2:$F$268,"Included",'Source Data'!$A$2:$A$268,"Referral",'Source Data'!$G$2:$G$268,"Website") -> 10 | F15: =SUMIFS('Source Data'!$L$2:$L$268,'Source Data'!$F$2:$F$268,"Included",'Source Data'!$A$2:$A$268,"Referral",'Source Data'!$G$2:$G$268,"Website") -> 273228.94 | G15: =IFERROR(E15/C15,0) -> 0.35714286 | H15: =SUMIFS('Source Data'!$O$2:$O$268,'Source Data'!$F$2:$F$268,"Included",'Source Data'!$A$2:$A$268,"Referral",'Source Data'!$G$2:$G$268,"Website") -> 11 | I15: =SUMIFS('Source Data'!$Q$2:$Q$268,'Source Data'!$F$2:$F$268,"Included",'Source Data'!$A$2:$A$268,"Referral",'Source Data'!$G$2:$G$268,"Website") -> 132243.91 | J15: =SUMIFS('Source Data'!$P$2:$P$268,'Source Data'!$F$2:$F$268,"Included",'Source Data'!$A$2:$A$268,"Referral",'Source Data'!$G$2:$G$268,"Website") -> 48170.72 | K15: =SUMIFS('Source Data'!$R$2:$R$268,'Source Data'!$F$2:$F$268,"Included",'Source Data'!$A$2:$A$268,"Referral",'Source Data'!$G$2:$G$268,"Website") -> 10940.54 | L15: =IFERROR(D15/C15,0) -> 16592.29 | M15: =IFERROR(F15/D15,0) -> 0.58811512

Sheet Status Breakdown
A1: Status Breakdown
A3: September 1–24 only. Order values are counted once; status reflects the backend snapshot.
A6: Order status | B6: Channel | C6: Orders | D6: Net sales | E6: Fulfilled orders | F6: Fulfilled net revenue | G6: Fulfillment rate | H6: Cancelled orders | I6: Cancelled net value | J6: Open net value | K6: Return refund net value | L6: Net value per order | M6: Fulfilled value share
A7: Cancelled | B7: Google Ads | C7: =COUNTIFS('Source Data'!$F$2:$F$268,"Included",'Source Data'!$I$2:$I$268,"Cancelled",'Source Data'!$A$2:$A$268,"Google Ads") -> 18 | D7: =SUMIFS('Source Data'!$K$2:$K$268,'Source Data'!$F$2:$F$268,"Included",'Source Data'!$I$2:$I$268,"Cancelled",'Source Data'!$A$2:$A$268,"Google Ads") -> 328191.94 | E7: =SUMIFS('Source Data'!$N$2:$N$268,'Source Data'!$F$2:$F$268,"Included",'Source Data'!$I$2:$I$268,"Cancelled",'Source Data'!$A$2:$A$268,"Google Ads") -> 0 | F7: =SUMIFS('Source Data'!$L$2:$L$268,'Source Data'!$F$2:$F$268,"Included",'Source Data'!$I$2:$I$268,"Cancelled",'Source Data'!$A$2:$A$268,"Google Ads") -> 0 | G7: =IFERROR(E7/C7,0) -> 0 | H7: =SUMIFS('Source Data'!$O$2:$O$268,'Source Data'!$F$2:$F$268,"Included",'Source Data'!$I$2:$I$268,"Cancelled",'Source Data'!$A$2:$A$268,"Google Ads") -> 18 | I7: =SUMIFS('Source Data'!$Q$2:$Q$268,'Source Data'!$F$2:$F$268,"Included",'Source Data'!$I$2:$I$268,"Cancelled",'Source Data'!$A$2:$A$268,"Google Ads") -> 328191.94 | J7: =SUMIFS('Source Data'!$P$2:$P$268,'Source Data'!$F$2:$F$268,"Included",'Source Data'!$I$2:$I$268,"Cancelled",'Source Data'!$A$2:$A$268,"Google Ads") -> 0 | K7: =SUMIFS('Source Data'!$R$2:$R$268,'Source Data'!$F$2:$F$268,"Included",'Source Data'!$I$2:$I$268,"Cancelled",'Source Data'!$A$2:$A$268,"Google Ads") -> 0 | L7: =IFERROR(D7/C7,0) -> 18232.886 | M7: =IFERROR(F7/D7,0) -> 0
A8: Cancelled | B8: Direct & Organic | C8: =COUNTIFS('Source Data'!$F$2:$F$268,"Included",'Source Data'!$I$2:$I$268,"Cancelled",'Source Data'!$A$2:$A$268,"Direct & Organic") -> 50 | D8: =SUMIFS('Source Data'!$K$2:$K$268,'Source Data'!$F$2:$F$268,"Included",'Source Data'!$I$2:$I$268,"Cancelled",'Source Data'!$A$2:$A$268,"Direct & Organic") -> 833341.14 | E8: =SUMIFS('Source Data'!$N$2:$N$268,'Source Data'!$F$2:$F$268,"Included",'Source Data'!$I$2:$I$268,"Cancelled",'Source Data'!$A$2:$A$268,"Direct & Organic") -> 0 | F8: =SUMIFS('Source Data'!$L$2:$L$268,'Source Data'!$F$2:$F$268,"Included",'Source Data'!$I$2:$I$268,"Cancelled",'Source Data'!$A$2:$A$268,"Direct & Organic") -> 0 | G8: =IFERROR(E8/C8,0) -> 0 | H8: =SUMIFS('Source Data'!$O$2:$O$268,'Source Data'!$F$2:$F$268,"Included",'Source Data'!$I$2:$I$268,"Cancelled",'Source Data'!$A$2:$A$268,"Direct & Organic") -> 50 | I8: =SUMIFS('Source Data'!$Q$2:$Q$268,'Source Data'!$F$2:$F$268,"Included",'Source Data'!$I$2:$I$268,"Cancelled",'Source Data'!$A$2:$A$268,"Direct & Organic") -> 833341.14 | J8: =SUMIFS('Source Data'!$P$2:$P$268,'Source Data'!$F$2:$F$268,"Included",'Source Data'!$I$2:$I$268,"Cancelled",'Source Data'!$A$2:$A$268,"Direct & Organic") -> 0 | K8: =SUMIFS('Source Data'!$R$2:$R$268,'Source Data'!$F$2:$F$268,"Included",'Source Data'!$I$2:$I$268,"Cancelled",'Source Data'!$A$2:$A$268,"Direct & Organic") -> 0 | L8: =IFERROR(D8/C8,0) -> 16666.823 | M8: =IFERROR(F8/D8,0) -> 0
A9: Cancelled | B9: Referral | C9: =COUNTIFS('Source Data'!$F$2:$F$268,"Included",'Source Data'!$I$2:$I$268,"Cancelled",'Source Data'!$A$2:$A$268,"Referral") -> 11 | D9: =SUMIFS('Source Data'!$K$2:$K$268,'Source Data'!$F$2:$F$268,"Included",'Source Data'!$I$2:$I$268,"Cancelled",'Source Data'!$A$2:$A$268,"Referral") -> 132243.91 | E9: =SUMIFS('Source Data'!$N$2:$N$268,'Source Data'!$F$2:$F$268,"Included",'Source Data'!$I$2:$I$268,"Cancelled",'Source Data'!$A$2:$A$268,"Referral") -> 0 | F9: =SUMIFS('Source Data'!$L$2:$L$268,'Source Data'!$F$2:$F$268,"Included",'Source Data'!$I$2:$I$268,"Cancelled",'Source Data'!$A$2:$A$268,"Referral") -> 0 | G9: =IFERROR(E9/C9,0) -> 0 | H9: =SUMIFS('Source Data'!$O$2:$O$268,'Source Data'!$F$2:$F$268,"Included",'Source Data'!$I$2:$I$268,"Cancelled",'Source Data'!$A$2:$A$268,"Referral") -> 11 | I9: =SUMIFS('Source Data'!$Q$2:$Q$268,'Source Data'!$F$2:$F$268,"Included",'Source Data'!$I$2:$I$268,"Cancelled",'Source Data'!$A$2:$A$268,"Referral") -> 132243.91 | J9: =SUMIFS('Source Data'!$P$2:$P$268,'Source Data'!$F$2:$F$268,"Included",'Source Data'!$I$2:$I$268,"Cancelled",'Source Data'!$A$2:$A$268,"Referral") -> 0 | K9: =SUMIFS('Source Data'!$R$2:$R$268,'Source Data'!$F$2:$F$268,"Included",'Source Data'!$I$2:$I$268,"Cancelled",'Source Data'!$A$2:$A$268,"Referral") -> 0 | L9: =IFERROR(D9/C9,0) -> 12022.174 | M9: =IFERROR(F9/D9,0) -> 0
A10: For Refund | B10: Google Ads | C10: =COUNTIFS('Source Data'!$F$2:$F$268,"Included",'Source Data'!$I$2:$I$268,"For Refund",'Source Data'!$A$2:$A$268,"Google Ads") -> 0 | D10: =SUMIFS('Source Data'!$K$2:$K$268,'Source Data'!$F$2:$F$268,"Included",'Source Data'!$I$2:$I$268,"For Refund",'Source Data'!$A$2:$A$268,"Google Ads") -> 0 | E10: =SUMIFS('Source Data'!$N$2:$N$268,'Source Data'!$F$2:$F$268,"Included",'Source Data'!$I$2:$I$268,"For Refund",'Source Data'!$A$2:$A$268,"Google Ads") -> 0 | F10: =SUMIFS('Source Data'!$L$2:$L$268,'Source Data'!$F$2:$F$268,"Included",'Source Data'!$I$2:$I$268,"For Refund",'Source Data'!$A$2:$A$268,"Google Ads") -> 0 | G10: =IFERROR(E10/C10,0) -> 0 | H10: =SUMIFS('Source Data'!$O$2:$O$268,'Source Data'!$F$2:$F$268,"Included",'Source Data'!$I$2:$I$268,"For Refund",'Source Data'!$A$2:$A$268,"Google Ads") -> 0 | I10: =SUMIFS('Source Data'!$Q$2:$Q$268,'Source Data'!$F$2:$F$268,"Included",'Source Data'!$I$2:$I$268,"For Refund",'Source Data'!$A$2:$A$268,"Google Ads") -> 0 | J10: =SUMIFS('Source Data'!$P$2:$P$268,'Source Data'!$F$2:$F$268,"Included",'Source Data'!$I$2:$I$268,"For Refund",'Source Data'!$A$2:$A$268,"Google Ads") -> 0 | K10: =SUMIFS('Source Data'!$R$2:$R$268,'Source Data'!$F$2:$F$268,"Included",'Source Data'!$I$2:$I$268,"For Refund",'Source Data'!$A$2:$A$268,"Google Ads") -> 0 | L10: =IFERROR(D10/C10,0) -> 0 | M10: =IFERROR(F10/D10,0) -> 0
A11: For Refund | B11: Direct & Organic | C11: =COUNTIFS('Source Data'!$F$2:$F$268,"Included",'Source Data'!$I$2:$I$268,"For Refund",'Source Data'!$A$2:$A$268,"Direct & Organic") -> 2 | D11: =SUMIFS('Source Data'!$K$2:$K$268,'Source Data'!$F$2:$F$268,"Included",'Source Data'!$I$2:$I$268,"For Refund",'Source Data'!$A$2:$A$268,"Direct & Organic") -> 28975 | E11: =SUMIFS('Source Data'!$N$2:$N$268,'Source Data'!$F$2:$F$268,"Included",'Source Data'!$I$2:$I$268,"For Refund",'Source Data'!$A$2:$A$268,"Direct & Organic") -> 0 | F11: =SUMIFS('Source Data'!$L$2:$L$268,'Source Data'!$F$2:$F$268,"Included",'Source Data'!$I$2:$I$268,"For Refund",'Source Data'!$A$2:$A$268,"Direct & Organic") -> 0 | G11: =IFERROR(E11/C11,0) -> 0 | H11: =SUMIFS('Source Data'!$O$2:$O$268,'Source Data'!$F$2:$F$268,"Included",'Source Data'!$I$2:$I$268,"For Refund",'Source Data'!$A$2:$A$268,"Direct & Organic") -> 0 | I11: =SUMIFS('Source Data'!$Q$2:$Q$268,'Source Data'!$F$2:$F$268,"Included",'Source Data'!$I$2:$I$268,"For Refund",'Source Data'!$A$2:$A$268,"Direct & Organic") -> 0 | J11: =SUMIFS('Source Data'!$P$2:$P$268,'Source Data'!$F$2:$F$268,"Included",'Source Data'!$I$2:$I$268,"For Refund",'Source Data'!$A$2:$A$268,"Direct & Organic") -> 0 | K11: =SUMIFS('Source Data'!$R$2:$R$268,'Source Data'!$F$2:$F$268,"Included",'Source Data'!$I$2:$I$268,"For Refund",'Source Data'!$A$2:$A$268,"Direct & Organic") -> 28975 | L11: =IFERROR(D11/C11,0) -> 14487.5 | M11: =IFERROR(F11/D11,0) -> 0
A12: For Refund | B12: Referral | C12: =COUNTIFS('Source Data'!$F$2:$F$268,"Included",'Source Data'!$I$2:$I$268,"For Refund",'Source Data'!$A$2:$A$268,"Referral") -> 0 | D12: =SUMIFS('Source Data'!$K$2:$K$268,'Source Data'!$F$2:$F$268,"Included",'Source Data'!$I$2:$I$268,"For Refund",'Source Data'!$A$2:$A$268,"Referral") -> 0 | E12: =SUMIFS('Source Data'!$N$2:$N$268,'Source Data'!$F$2:$F$268,"Included",'Source Data'!$I$2:$I$268,"For Refund",'Source Data'!$A$2:$A$268,"Referral") -> 0 | F12: =SUMIFS('Source Data'!$L$2:$L$268,'Source Data'!$F$2:$F$268,"Included",'Source Data'!$I$2:$I$268,"For Refund",'Source Data'!$A$2:$A$268,"Referral") -> 0 | G12: =IFERROR(E12/C12,0) -> 0 | H12: =SUMIFS('Source Data'!$O$2:$O$268,'Source Data'!$F$2:$F$268,"Included",'Source Data'!$I$2:$I$268,"For Refund",'Source Data'!$A$2:$A$268,"Referral") -> 0 | I12: =SUMIFS('Source Data'!$Q$2:$Q$268,'Source Data'!$F$2:$F$268,"Included",'Source Data'!$I$2:$I$268,"For Refund",'Source Data'!$A$2:$A$268,"Referral") -> 0 | J12: =SUMIFS('Source Data'!$P$2:$P$268,'Source Data'!$F$2:$F$268,"Included",'Source Data'!$I$2:$I$268,"For Refund",'Source Data'!$A$2:$A$268,"Referral") -> 0 | K12: =SUMIFS('Source Data'!$R$2:$R$268,'Source Data'!$F$2:$F$268,"Included",'Source Data'!$I$2:$I$268,"For Refund",'Source Data'!$A$2:$A$268,"Referral") -> 0 | L12: =IFERROR(D12/C12,0) -> 0 | M12: =IFERROR(F12/D12,0) -> 0
A13: For Return | B13: Google Ads | C13: =COUNTIFS('Source Data'!$F$2:$F$268,"Included",'Source Data'!$I$2:$I$268,"For Return",'Source Data'!$A$2:$A$268,"Google Ads") -> 1 | D13: =SUMIFS('Source Data'!$K$2:$K$268,'Source Data'!$F$2:$F$268,"Included",'Source Data'!$I$2:$I$268,"For Return",'Source Data'!$A$2:$A$268,"Google Ads") -> 10940.54 | E13: =SUMIFS('Source Data'!$N$2:$N$268,'Source Data'!$F$2:$F$268,"Included",'Source Data'!$I$2:$I$268,"For Return",'Source Data'!$A$2:$A$268,"Google Ads") -> 0 | F13: =SUMIFS('Source Data'!$L$2:$L$268,'Source Data'!$F$2:$F$268,"Included",'Source Data'!$I$2:$I$268,"For Return",'Source Data'!$A$2:$A$268,"Google Ads") -> 0 | G13: =IFERROR(E13/C13,0) -> 0 | H13: =SUMIFS('Source Data'!$O$2:$O$268,'Source Data'!$F$2:$F$268,"Included",'Source Data'!$I$2:$I$268,"For Return",'Source Data'!$A$2:$A$268,"Google Ads") -> 0 | I13: =SUMIFS('Source Data'!$Q$2:$Q$268,'Source Data'!$F$2:$F$268,"Included",'Source Data'!$I$2:$I$268,"For Return",'Source Data'!$A$2:$A$268,"Google Ads") -> 0 | J13: =SUMIFS('Source Data'!$P$2:$P$268,'Source Data'!$F$2:$F$268,"Included",'Source Data'!$I$2:$I$268,"For Return",'Source Data'!$A$2:$A$268,"Google Ads") -> 0 | K13: =SUMIFS('Source Data'!$R$2:$R$268,'Source Data'!$F$2:$F$268,"Included",'Source Data'!$I$2:$I$268,"For Return",'Source Data'!$A$2:$A$268,"Google Ads") -> 10940.54 | L13: =IFERROR(D13/C13,0) -> 10940.54 | M13: =IFERROR(F13/D13,0) -> 0
A14: For Return | B14: Direct & Organic | C14: =COUNTIFS('Source Data'!$F$2:$F$268,"Included",'Source Data'!$I$2:$I$268,"For Return",'Source Data'!$A$2:$A$268,"Direct & Organic") -> 1 | D14: =SUMIFS('Source Data'!$K$2:$K$268,'Source Data'!$F$2:$F$268,"Included",'Source Data'!$I$2:$I$268,"For Return",'Source Data'!$A$2:$A$268,"Direct & Organic") -> 31301.07 | E14: =SUMIFS('Source Data'!$N$2:$N$268,'Source Data'!$F$2:$F$268,"Included",'Source Data'!$I$2:$I$268,"For Return",'Source Data'!$A$2:$A$268,"Direct & Organic") -> 0 | F14: =SUMIFS('Source Data'!$L$2:$L$268,'Source Data'!$F$2:$F$268,"Included",'Source Data'!$I$2:$I$268,"For Return",'Source Data'!$A$2:$A$268,"Direct & Organic") -> 0 | G14: =IFERROR(E14/C14,0) -> 0 | H14: =SUMIFS('Source Data'!$O$2:$O$268,'Source Data'!$F$2:$F$268,"Included",'Source Data'!$I$2:$I$268,"For Return",'Source Data'!$A$2:$A$268,"Direct & Organic") -> 0 | I14: =SUMIFS('Source Data'!$Q$2:$Q$268,'Source Data'!$F$2:$F$268,"Included",'Source Data'!$I$2:$I$268,"For Return",'Source Data'!$A$2:$A$268,"Direct & Organic") -> 0 | J14: =SUMIFS('Source Data'!$P$2:$P$268,'Source Data'!$F$2:$F$268,"Included",'Source Data'!$I$2:$I$268,"For Return",'Source Data'!$A$2:$A$268,"Direct & Organic") -> 0 | K14: =SUMIFS('Source Data'!$R$2:$R$268,'Source Data'!$F$2:$F$268,"Included",'Source Data'!$I$2:$I$268,"For Return",'Source Data'!$A$2:$A$268,"Direct & Organic") -> 31301.07 | L14: =IFERROR(D14/C14,0) -> 31301.07 | M14: =IFERROR(F14/D14,0) -> 0
A15: For Return | B15: Referral | C15: =COUNTIFS('Source Data'!$F$2:$F$268,"Included",'Source Data'!$I$2:$I$268,"For Return",'Source Data'!$A$2:$A$268,"Referral") -> 1 | D15: =SUMIFS('Source Data'!$K$2:$K$268,'Source Data'!$F$2:$F$268,"Included",'Source Data'!$I$2:$I$268,"For Return",'Source Data'!$A$2:$A$268,"Referral") -> 10940.54 | E15: =SUMIFS('Source Data'!$N$2:$N$268,'Source Data'!$F$2:$F$268,"Included",'Source Data'!$I$2:$I$268,"For Return",'Source Data'!$A$2:$A$268,"Referral") -> 0 | F15: =SUMIFS('Source Data'!$L$2:$L$268,'Source Data'!$F$2:$F$268,"Included",'Source Data'!$I$2:$I$268,"For Return",'Source Data'!$A$2:$A$268,"Referral") -> 0 | G15: =IFERROR(E15/C15,0) -> 0 | H15: =SUMIFS('Source Data'!$O$2:$O$268,'Source Data'!$F$2:$F$268,"Included",'Source Data'!$I$2:$I$268,"For Return",'Source Data'!$A$2:$A$268,"Referral") -> 0 | I15: =SUMIFS('Source Data'!$Q$2:$Q$268,'Source Data'!$F$2:$F$268,"Included",'Source Data'!$I$2:$I$268,"For Return",'Source Data'!$A$2:$A$268,"Referral") -> 0 | J15: =SUMIFS('Source Data'!$P$2:$P$268,'Source Data'!$F$2:$F$268,"Included",'Source Data'!$I$2:$I$268,"For Return",'Source Data'!$A$2:$A$268,"Referral") -> 0 | K15: =SUMIFS('Source Data'!$R$2:$R$268,'Source Data'!$F$2:$F$268,"Included",'Source Data'!$I$2:$I$268,"For Return",'Source Data'!$A$2:$A$268,"Referral") -> 10940.54 | L15: =IFERROR(D15/C15,0) -> 10940.54 | M15: =IFERROR(F15/D15,0) -> 0
A16: Fulfilled | B16: Google Ads | C16: =COUNTIFS('Source Data'!$F$2:$F$268,"Included",'Source Data'!$I$2:$I$268,"Fulfilled",'Source Data'!$A$2:$A$268,"Google Ads") -> 26 | D16: =SUMIFS('Source Data'!$K$2:$K$268,'Source Data'!$F$2:$F$268,"Included",'Source Data'!$I$2:$I$268,"Fulfilled",'Source Data'!$A$2:$A$268,"Google Ads") -> 510707.5 | E16: =SUMIFS('Source Data'!$N$2:$N$268,'Source Data'!$F$2:$F$268,"Included",'Source Data'!$I$2:$I$268,"Fulfilled",'Source Data'!$A$2:$A$268,"Google Ads") -> 26 | F16: =SUMIFS('Source Data'!$L$2:$L$268,'Source Data'!$F$2:$F$268,"Included",'Source Data'!$I$2:$I$268,"Fulfilled",'Source Data'!$A$2:$A$268,"Google Ads") -> 510707.5 | G16: =IFERROR(E16/C16,0) -> 1 | H16: =SUMIFS('Source Data'!$O$2:$O$268,'Source Data'!$F$2:$F$268,"Included",'Source Data'!$I$2:$I$268,"Fulfilled",'Source Data'!$A$2:$A$268,"Google Ads") -> 0 | I16: =SUMIFS('Source Data'!$Q$2:$Q$268,'Source Data'!$F$2:$F$268,"Included",'Source Data'!$I$2:$I$268,"Fulfilled",'Source Data'!$A$2:$A$268,"Google Ads") -> 0 | J16: =SUMIFS('Source Data'!$P$2:$P$268,'Source Data'!$F$2:$F$268,"Included",'Source Data'!$I$2:$I$268,"Fulfilled",'Source Data'!$A$2:$A$268,"Google Ads") -> 0 | K16: =SUMIFS('Source Data'!$R$2:$R$268,'Source Data'!$F$2:$F$268,"Included",'Source Data'!$I$2:$I$268,"Fulfilled",'Source Data'!$A$2:$A$268,"Google Ads") -> 0 | L16: =IFERROR(D16/C16,0) -> 19642.596 | M16: =IFERROR(F16/D16,0) -> 1
A17: Fulfilled | B17: Direct & Organic | C17: =COUNTIFS('Source Data'!$F$2:$F$268,"Included",'Source Data'!$I$2:$I$268,"Fulfilled",'Source Data'!$A$2:$A$268,"Direct & Organic") -> 75 | D17: =SUMIFS('Source Data'!$K$2:$K$268,'Source Data'!$F$2:$F$268,"Included",'Source Data'!$I$2:$I$268,"Fulfilled",'Source Data'!$A$2:$A$268,"Direct & Organic") -> 1307528.9 | E17: =SUMIFS('Source Data'!$N$2:$N$268,'Source Data'!$F$2:$F$268,"Included",'Source Data'!$I$2:$I$268,"Fulfilled",'Source Data'!$A$2:$A$268,"Direct & Organic") -> 75 | F17: =SUMIFS('Source Data'!$L$2:$L$268,'Source Data'!$F$2:$F$268,"Included",'Source Data'!$I$2:$I$268,"Fulfilled",'Source Data'!$A$2:$A$268,"Direct & Organic") -> 1307528.9 | G17: =IFERROR(E17/C17,0) -> 1 | H17: =SUMIFS('Source Data'!$O$2:$O$268,'Source Data'!$F$2:$F$268,"Included",'Source Data'!$I$2:$I$268,"Fulfilled",'Source Data'!$A$2:$A$268,"Direct & Organic") -> 0 | I17: =SUMIFS('Source Data'!$Q$2:$Q$268,'Source Data'!$F$2:$F$268,"Included",'Source Data'!$I$2:$I$268,"Fulfilled",'Source Data'!$A$2:$A$268,"Direct & Organic") -> 0 | J17: =SUMIFS('Source Data'!$P$2:$P$268,'Source Data'!$F$2:$F$268,"Included",'Source Data'!$I$2:$I$268,"Fulfilled",'Source Data'!$A$2:$A$268,"Direct & Organic") -> 0 | K17: =SUMIFS('Source Data'!$R$2:$R$268,'Source Data'!$F$2:$F$268,"Included",'Source Data'!$I$2:$I$268,"Fulfilled",'Source Data'!$A$2:$A$268,"Direct & Organic") -> 0 | L17: =IFERROR(D17/C17,0) -> 17433.718 | M17: =IFERROR(F17/D17,0) -> 1
A18: Fulfilled | B18: Referral | C18: =COUNTIFS('Source Data'!$F$2:$F$268,"Included",'Source Data'!$I$2:$I$268,"Fulfilled",'Source Data'!$A$2:$A$268,"Referral") -> 10 | D18: =SUMIFS('Source Data'!$K$2:$K$268,'Source Data'!$F$2:$F$268,"Included",'Source Data'!$I$2:$I$268,"Fulfilled",'Source Data'!$A$2:$A$268,"Referral") -> 273228.94 | E18: =SUMIFS('Source Data'!$N$2:$N$268,'Source Data'!$F$2:$F$268,"Included",'Source Data'!$I$2:$I$268,"Fulfilled",'Source Data'!$A$2:$A$268,"Referral") -> 10 | F18: =SUMIFS('Source Data'!$L$2:$L$268,'Source Data'!$F$2:$F$268,"Included",'Source Data'!$I$2:$I$268,"Fulfilled",'Source Data'!$A$2:$A$268,"Referral") -> 273228.94 | G18: =IFERROR(E18/C18,0) -> 1 | H18: =SUMIFS('Source Data'!$O$2:$O$268,'Source Data'!$F$2:$F$268,"Included",'Source Data'!$I$2:$I$268,"Fulfilled",'Source Data'!$A$2:$A$268,"Referral") -> 0 | I18: =SUMIFS('Source Data'!$Q$2:$Q$268,'Source Data'!$F$2:$F$268,"Included",'Source Data'!$I$2:$I$268,"Fulfilled",'Source Data'!$A$2:$A$268,"Referral") -> 0 | J18: =SUMIFS('Source Data'!$P$2:$P$268,'Source Data'!$F$2:$F$268,"Included",'Source Data'!$I$2:$I$268,"Fulfilled",'Source Data'!$A$2:$A$268,"Referral") -> 0 | K18: =SUMIFS('Source Data'!$R$2:$R$268,'Source Data'!$F$2:$F$268,"Included",'Source Data'!$I$2:$I$268,"Fulfilled",'Source Data'!$A$2:$A$268,"Referral") -> 0 | L18: =IFERROR(D18/C18,0) -> 27322.894 | M18: =IFERROR(F18/D18,0) -> 1
A19: New | B19: Google Ads | C19: =COUNTIFS('Source Data'!$F$2:$F$268,"Included",'Source Data'!$I$2:$I$268,"New",'Source Data'!$A$2:$A$268,"Google Ads") -> 13 | D19: =SUMIFS('Source Data'!$K$2:$K$268,'Source Data'!$F$2:$F$268,"Included",'Source Data'!$I$2:$I$268,"New",'Source Data'!$A$2:$A$268,"Google Ads") -> 429307.34 | E19: =SUMIFS('Source Data'!$N$2:$N$268,'Source Data'!$F$2:$F$268,"Included",'Source Data'!$I$2:$I$268,"New",'Source Data'!$A$2:$A$268,"Google Ads") -> 0 | F19: =SUMIFS('Source Data'!$L$2:$L$268,'Source Data'!$F$2:$F$268,"Included",'Source Data'!$I$2:$I$268,"New",'Source Data'!$A$2:$A$268,"Google Ads") -> 0 | G19: =IFERROR(E19/C19,0) -> 0 | H19: =SUMIFS('Source Data'!$O$2:$O$268,'Source Data'!$F$2:$F$268,"Included",'Source Data'!$I$2:$I$268,"New",'Source Data'!$A$2:$A$268,"Google Ads") -> 0 | I19: =SUMIFS('Source Data'!$Q$2:$Q$268,'Source Data'!$F$2:$F$268,"Included",'Source Data'!$I$2:$I$268,"New",'Source Data'!$A$2:$A$268,"Google Ads") -> 0 | J19: =SUMIFS('Source Data'!$P$2:$P$268,'Source Data'!$F$2:$F$268,"Included",'Source Data'!$I$2:$I$268,"New",'Source Data'!$A$2:$A$268,"Google Ads") -> 429307.34 | K19: =SUMIFS('Source Data'!$R$2:$R$268,'Source Data'!$F$2:$F$268,"Included",'Source Data'!$I$2:$I$268,"New",'Source Data'!$A$2:$A$268,"Google Ads") -> 0 | L19: =IFERROR(D19/C19,0) -> 33023.642 | M19: =IFERROR(F19/D19,0) -> 0
A20: New | B20: Direct & Organic | C20: =COUNTIFS('Source Data'!$F$2:$F$268,"Included",'Source Data'!$I$2:$I$268,"New",'Source Data'!$A$2:$A$268,"Direct & Organic") -> 17 | D20: =SUMIFS('Source Data'!$K$2:$K$268,'Source Data'!$F$2:$F$268,"Included",'Source Data'!$I$2:$I$268,"New",'Source Data'!$A$2:$A$268,"Direct & Organic") -> 270588.46 | E20: =SUMIFS('Source Data'!$N$2:$N$268,'Source Data'!$F$2:$F$268,"Included",'Source Data'!$I$2:$I$268,"New",'Source Data'!$A$2:$A$268,"Direct & Organic") -> 0 | F20: =SUMIFS('Source Data'!$L$2:$L$268,'Source Data'!$F$2:$F$268,"Included",'Source Data'!$I$2:$I$268,"New",'Source Data'!$A$2:$A$268,"Direct & Organic") -> 0 | G20: =IFERROR(E20/C20,0) -> 0 | H20: =SUMIFS('Source Data'!$O$2:$O$268,'Source Data'!$F$2:$F$268,"Included",'Source Data'!$I$2:$I$268,"New",'Source Data'!$A$2:$A$268,"Direct & Organic") -> 0 | I20: =SUMIFS('Source Data'!$Q$2:$Q$268,'Source Data'!$F$2:$F$268,"Included",'Source Data'!$I$2:$I$268,"New",'Source Data'!$A$2:$A$268,"Direct & Organic") -> 0 | J20: =SUMIFS('Source Data'!$P$2:$P$268,'Source Data'!$F$2:$F$268,"Included",'Source Data'!$I$2:$I$268,"New",'Source Data'!$A$2:$A$268,"Direct & Organic") -> 270588.46 | K20: =SUMIFS('Source Data'!$R$2:$R$268,'Source Data'!$F$2:$F$268,"Included",'Source Data'!$I$2:$I$268,"New",'Source Data'!$A$2:$A$268,"Direct & Organic") -> 0 | L20: =IFERROR(D20/C20,0) -> 15916.968 | M20: =IFERROR(F20/D20,0) -> 0
A21: New | B21: Referral | C21: =COUNTIFS('Source Data'!$F$2:$F$268,"Included",'Source Data'!$I$2:$I$268,"New",'Source Data'!$A$2:$A$268,"Referral") -> 5 | D21: =SUMIFS('Source Data'!$K$2:$K$268,'Source Data'!$F$2:$F$268,"Included",'Source Data'!$I$2:$I$268,"New",'Source Data'!$A$2:$A$268,"Referral") -> 34435.54 | E21: =SUMIFS('Source Data'!$N$2:$N$268,'Source Data'!$F$2:$F$268,"Included",'Source Data'!$I$2:$I$268,"New",'Source Data'!$A$2:$A$268,"Referral") -> 0 | F21: =SUMIFS('Source Data'!$L$2:$L$268,'Source Data'!$F$2:$F$268,"Included",'Source Data'!$I$2:$I$268,"New",'Source Data'!$A$2:$A$268,"Referral") -> 0 | G21: =IFERROR(E21/C21,0) -> 0 | H21: =SUMIFS('Source Data'!$O$2:$O$268,'Source Data'!$F$2:$F$268,"Included",'Source Data'!$I$2:$I$268,"New",'Source Data'!$A$2:$A$268,"Referral") -> 0 | I21: =SUMIFS('Source Data'!$Q$2:$Q$268,'Source Data'!$F$2:$F$268,"Included",'Source Data'!$I$2:$I$268,"New",'Source Data'!$A$2:$A$268,"Referral") -> 0 | J21: =SUMIFS('Source Data'!$P$2:$P$268,'Source Data'!$F$2:$F$268,"Included",'Source Data'!$I$2:$I$268,"New",'Source Data'!$A$2:$A$268,"Referral") -> 34435.54 | K21: =SUMIFS('Source Data'!$R$2:$R$268,'Source Data'!$F$2:$F$268,"Included",'Source Data'!$I$2:$I$268,"New",'Source Data'!$A$2:$A$268,"Referral") -> 0 | L21: =IFERROR(D21/C21,0) -> 6887.108 | M21: =IFERROR(F21/D21,0) -> 0
A22: Pending | B22: Google Ads | C22: =COUNTIFS('Source Data'!$F$2:$F$268,"Included",'Source Data'!$I$2:$I$268,"Pending",'Source Data'!$A$2:$A$268,"Google Ads") -> 5 | D22: =SUMIFS('Source Data'!$K$2:$K$268,'Source Data'!$F$2:$F$268,"Included",'Source Data'!$I$2:$I$268,"Pending",'Source Data'!$A$2:$A$268,"Google Ads") -> 80720.91 | E22: =SUMIFS('Source Data'!$N$2:$N$268,'Source Data'!$F$2:$F$268,"Included",'Source Data'!$I$2:$I$268,"Pending",'Source Data'!$A$2:$A$268,"Google Ads") -> 0 | F22: =SUMIFS('Source Data'!$L$2:$L$268,'Source Data'!$F$2:$F$268,"Included",'Source Data'!$I$2:$I$268,"Pending",'Source Data'!$A$2:$A$268,"Google Ads") -> 0 | G22: =IFERROR(E22/C22,0) -> 0 | H22: =SUMIFS('Source Data'!$O$2:$O$268,'Source Data'!$F$2:$F$268,"Included",'Source Data'!$I$2:$I$268,"Pending",'Source Data'!$A$2:$A$268,"Google Ads") -> 0 | I22: =SUMIFS('Source Data'!$Q$2:$Q$268,'Source Data'!$F$2:$F$268,"Included",'Source Data'!$I$2:$I$268,"Pending",'Source Data'!$A$2:$A$268,"Google Ads") -> 0 | J22: =SUMIFS('Source Data'!$P$2:$P$268,'Source Data'!$F$2:$F$268,"Included",'Source Data'!$I$2:$I$268,"Pending",'Source Data'!$A$2:$A$268,"Google Ads") -> 80720.91 | K22: =SUMIFS('Source Data'!$R$2:$R$268,'Source Data'!$F$2:$F$268,"Included",'Source Data'!$I$2:$I$268,"Pending",'Source Data'!$A$2:$A$268,"Google Ads") -> 0 | L22: =IFERROR(D22/C22,0) -> 16144.182 | M22: =IFERROR(F22/D22,0) -> 0
A23: Pending | B23: Direct & Organic | C23: =COUNTIFS('Source Data'!$F$2:$F$268,"Included",'Source Data'!$I$2:$I$268,"Pending",'Source Data'!$A$2:$A$268,"Direct & Organic") -> 6 | D23: =SUMIFS('Source Data'!$K$2:$K$268,'Source Data'!$F$2:$F$268,"Included",'Source Data'!$I$2:$I$268,"Pending",'Source Data'!$A$2:$A$268,"Direct & Organic") -> 108685.01 | E23: =SUMIFS('Source Data'!$N$2:$N$268,'Source Data'!$F$2:$F$268,"Included",'Source Data'!$I$2:$I$268,"Pending",'Source Data'!$A$2:$A$268,"Direct & Organic") -> 0 | F23: =SUMIFS('Source Data'!$L$2:$L$268,'Source Data'!$F$2:$F$268,"Included",'Source Data'!$I$2:$I$268,"Pending",'Source Data'!$A$2:$A$268,"Direct & Organic") -> 0 | G23: =IFERROR(E23/C23,0) -> 0 | H23: =SUMIFS('Source Data'!$O$2:$O$268,'Source Data'!$F$2:$F$268,"Included",'Source Data'!$I$2:$I$268,"Pending",'Source Data'!$A$2:$A$268,"Direct & Organic") -> 0 | I23: =SUMIFS('Source Data'!$Q$2:$Q$268,'Source Data'!$F$2:$F$268,"Included",'Source Data'!$I$2:$I$268,"Pending",'Source Data'!$A$2:$A$268,"Direct & Organic") -> 0 | J23: =SUMIFS('Source Data'!$P$2:$P$268,'Source Data'!$F$2:$F$268,"Included",'Source Data'!$I$2:$I$268,"Pending",'Source Data'!$A$2:$A$268,"Direct & Organic") -> 108685.01 | K23: =SUMIFS('Source Data'!$R$2:$R$268,'Source Data'!$F$2:$F$268,"Included",'Source Data'!$I$2:$I$268,"Pending",'Source Data'!$A$2:$A$268,"Direct & Organic") -> 0 | L23: =IFERROR(D23/C23,0) -> 18114.168 | M23: =IFERROR(F23/D23,0) -> 0
A24: Pending | B24: Referral | C24: =COUNTIFS('Source Data'!$F$2:$F$268,"Included",'Source Data'!$I$2:$I$268,"Pending",'Source Data'!$A$2:$A$268,"Referral") -> 0 | D24: =SUMIFS('Source Data'!$K$2:$K$268,'Source Data'!$F$2:$F$268,"Included",'Source Data'!$I$2:$I$268,"Pending",'Source Data'!$A$2:$A$268,"Referral") -> 0 | E24: =SUMIFS('Source Data'!$N$2:$N$268,'Source Data'!$F$2:$F$268,"Included",'Source Data'!$I$2:$I$268,"Pending",'Source Data'!$A$2:$A$268,"Referral") -> 0 | F24: =SUMIFS('Source Data'!$L$2:$L$268,'Source Data'!$F$2:$F$268,"Included",'Source Data'!$I$2:$I$268,"Pending",'Source Data'!$A$2:$A$268,"Referral") -> 0 | G24: =IFERROR(E24/C24,0) -> 0 | H24: =SUMIFS('Source Data'!$O$2:$O$268,'Source Data'!$F$2:$F$268,"Included",'Source Data'!$I$2:$I$268,"Pending",'Source Data'!$A$2:$A$268,"Referral") -> 0 | I24: =SUMIFS('Source Data'!$Q$2:$Q$268,'Source Data'!$F$2:$F$268,"Included",'Source Data'!$I$2:$I$268,"Pending",'Source Data'!$A$2:$A$268,"Referral") -> 0 | J24: =SUMIFS('Source Data'!$P$2:$P$268,'Source Data'!$F$2:$F$268,"Included",'Source Data'!$I$2:$I$268,"Pending",'Source Data'!$A$2:$A$268,"Referral") -> 0 | K24: =SUMIFS('Source Data'!$R$2:$R$268,'Source Data'!$F$2:$F$268,"Included",'Source Data'!$I$2:$I$268,"Pending",'Source Data'!$A$2:$A$268,"Referral") -> 0 | L24: =IFERROR(D24/C24,0) -> 0 | M24: =IFERROR(F24/D24,0) -> 0
A25: Processing | B25: Google Ads | C25: =COUNTIFS('Source Data'!$F$2:$F$268,"Included",'Source Data'!$I$2:$I$268,"Processing",'Source Data'!$A$2:$A$268,"Google Ads") -> 4 | D25: =SUMIFS('Source Data'!$K$2:$K$268,'Source Data'!$F$2:$F$268,"Included",'Source Data'!$I$2:$I$268,"Processing",'Source Data'!$A$2:$A$268,"Google Ads") -> 113241.25 | E25: =SUMIFS('Source Data'!$N$2:$N$268,'Source Data'!$F$2:$F$268,"Included",'Source Data'!$I$2:$I$268,"Processing",'Source Data'!$A$2:$A$268,"Google Ads") -> 0 | F25: =SUMIFS('Source Data'!$L$2:$L$268,'Source Data'!$F$2:$F$268,"Included",'Source Data'!$I$2:$I$268,"Processing",'Source Data'!$A$2:$A$268,"Google Ads") -> 0 | G25: =IFERROR(E25/C25,0) -> 0 | H25: =SUMIFS('Source Data'!$O$2:$O$268,'Source Data'!$F$2:$F$268,"Included",'Source Data'!$I$2:$I$268,"Processing",'Source Data'!$A$2:$A$268,"Google Ads") -> 0 | I25: =SUMIFS('Source Data'!$Q$2:$Q$268,'Source Data'!$F$2:$F$268,"Included",'Source Data'!$I$2:$I$268,"Processing",'Source Data'!$A$2:$A$268,"Google Ads") -> 0 | J25: =SUMIFS('Source Data'!$P$2:$P$268,'Source Data'!$F$2:$F$268,"Included",'Source Data'!$I$2:$I$268,"Processing",'Source Data'!$A$2:$A$268,"Google Ads") -> 113241.25 | K25: =SUMIFS('Source Data'!$R$2:$R$268,'Source Data'!$F$2:$F$268,"Included",'Source Data'!$I$2:$I$268,"Processing",'Source Data'!$A$2:$A$268,"Google Ads") -> 0 | L25: =IFERROR(D25/C25,0) -> 28310.312 | M25: =IFERROR(F25/D25,0) -> 0
A26: Processing | B26: Direct & Organic | C26: =COUNTIFS('Source Data'!$F$2:$F$268,"Included",'Source Data'!$I$2:$I$268,"Processing",'Source Data'!$A$2:$A$268,"Direct & Organic") -> 16 | D26: =SUMIFS('Source Data'!$K$2:$K$268,'Source Data'!$F$2:$F$268,"Included",'Source Data'!$I$2:$I$268,"Processing",'Source Data'!$A$2:$A$268,"Direct & Organic") -> 281703.13 | E26: =SUMIFS('Source Data'!$N$2:$N$268,'Source Data'!$F$2:$F$268,"Included",'Source Data'!$I$2:$I$268,"Processing",'Source Data'!$A$2:$A$268,"Direct & Organic") -> 0 | F26: =SUMIFS('Source Data'!$L$2:$L$268,'Source Data'!$F$2:$F$268,"Included",'Source Data'!$I$2:$I$268,"Processing",'Source Data'!$A$2:$A$268,"Direct & Organic") -> 0 | G26: =IFERROR(E26/C26,0) -> 0 | H26: =SUMIFS('Source Data'!$O$2:$O$268,'Source Data'!$F$2:$F$268,"Included",'Source Data'!$I$2:$I$268,"Processing",'Source Data'!$A$2:$A$268,"Direct & Organic") -> 0 | I26: =SUMIFS('Source Data'!$Q$2:$Q$268,'Source Data'!$F$2:$F$268,"Included",'Source Data'!$I$2:$I$268,"Processing",'Source Data'!$A$2:$A$268,"Direct & Organic") -> 0 | J26: =SUMIFS('Source Data'!$P$2:$P$268,'Source Data'!$F$2:$F$268,"Included",'Source Data'!$I$2:$I$268,"Processing",'Source Data'!$A$2:$A$268,"Direct & Organic") -> 281703.13 | K26: =SUMIFS('Source Data'!$R$2:$R$268,'Source Data'!$F$2:$F$268,"Included",'Source Data'!$I$2:$I$268,"Processing",'Source Data'!$A$2:$A$268,"Direct & Organic") -> 0 | L26: =IFERROR(D26/C26,0) -> 17606.446 | M26: =IFERROR(F26/D26,0) -> 0
A27: Processing | B27: Referral | C27: =COUNTIFS('Source Data'!$F$2:$F$268,"Included",'Source Data'!$I$2:$I$268,"Processing",'Source Data'!$A$2:$A$268,"Referral") -> 1 | D27: =SUMIFS('Source Data'!$K$2:$K$268,'Source Data'!$F$2:$F$268,"Included",'Source Data'!$I$2:$I$268,"Processing",'Source Data'!$A$2:$A$268,"Referral") -> 13735.18 | E27: =SUMIFS('Source Data'!$N$2:$N$268,'Source Data'!$F$2:$F$268,"Included",'Source Data'!$I$2:$I$268,"Processing",'Source Data'!$A$2:$A$268,"Referral") -> 0 | F27: =SUMIFS('Source Data'!$L$2:$L$268,'Source Data'!$F$2:$F$268,"Included",'Source Data'!$I$2:$I$268,"Processing",'Source Data'!$A$2:$A$268,"Referral") -> 0 | G27: =IFERROR(E27/C27,0) -> 0 | H27: =SUMIFS('Source Data'!$O$2:$O$268,'Source Data'!$F$2:$F$268,"Included",'Source Data'!$I$2:$I$268,"Processing",'Source Data'!$A$2:$A$268,"Referral") -> 0 | I27: =SUMIFS('Source Data'!$Q$2:$Q$268,'Source Data'!$F$2:$F$268,"Included",'Source Data'!$I$2:$I$268,"Processing",'Source Data'!$A$2:$A$268,"Referral") -> 0 | J27: =SUMIFS('Source Data'!$P$2:$P$268,'Source Data'!$F$2:$F$268,"Included",'Source Data'!$I$2:$I$268,"Processing",'Source Data'!$A$2:$A$268,"Referral") -> 13735.18 | K27: =SUMIFS('Source Data'!$R$2:$R$268,'Source Data'!$F$2:$F$268,"Included",'Source Data'!$I$2:$I$268,"Processing",'Source Data'!$A$2:$A$268,"Referral") -> 0 | L27: =IFERROR(D27/C27,0) -> 13735.18 | M27: =IFERROR(F27/D27,0) -> 0

Sheet Campaign Breakdown
A1: Campaign Breakdown
A3: September 1–24 only. Order values are counted once; status reflects the backend snapshot.
A6: Session campaign | B6: Orders | C6: Net sales | D6: Fulfilled orders | E6: Fulfilled net revenue | F6: Fulfillment rate | G6: Cancelled orders | H6: Cancelled net value | I6: Open net value | J6: Return refund net value | K6: Net value per order | L6: Fulfilled value share
A7: (cross-network) | B7: =COUNTIFS('Source Data'!$F$2:$F$268,"Included",'Source Data'!$B$2:$B$268,"(cross-network)") -> 1 | C7: =SUMIFS('Source Data'!$K$2:$K$268,'Source Data'!$F$2:$F$268,"Included",'Source Data'!$B$2:$B$268,"(cross-network)") -> 8613.66 | D7: =SUMIFS('Source Data'!$N$2:$N$268,'Source Data'!$F$2:$F$268,"Included",'Source Data'!$B$2:$B$268,"(cross-network)") -> 1 | E7: =SUMIFS('Source Data'!$L$2:$L$268,'Source Data'!$F$2:$F$268,"Included",'Source Data'!$B$2:$B$268,"(cross-network)") -> 8613.66 | F7: =IFERROR(D7/B7,0) -> 1 | G7: =SUMIFS('Source Data'!$O$2:$O$268,'Source Data'!$F$2:$F$268,"Included",'Source Data'!$B$2:$B$268,"(cross-network)") -> 0 | H7: =SUMIFS('Source Data'!$Q$2:$Q$268,'Source Data'!$F$2:$F$268,"Included",'Source Data'!$B$2:$B$268,"(cross-network)") -> 0 | I7: =SUMIFS('Source Data'!$P$2:$P$268,'Source Data'!$F$2:$F$268,"Included",'Source Data'!$B$2:$B$268,"(cross-network)") -> 0 | J7: =SUMIFS('Source Data'!$R$2:$R$268,'Source Data'!$F$2:$F$268,"Included",'Source Data'!$B$2:$B$268,"(cross-network)") -> 0 | K7: =IFERROR(C7/B7,0) -> 8613.66 | L7: =IFERROR(E7/C7,0) -> 1
A8: (direct) | B8: =COUNTIFS('Source Data'!$F$2:$F$268,"Included",'Source Data'!$B$2:$B$268,"(direct)") -> 93 | C8: =SUMIFS('Source Data'!$K$2:$K$268,'Source Data'!$F$2:$F$268,"Included",'Source Data'!$B$2:$B$268,"(direct)") -> 1587411.4 | D8: =SUMIFS('Source Data'!$N$2:$N$268,'Source Data'!$F$2:$F$268,"Included",'Source Data'!$B$2:$B$268,"(direct)") -> 41 | E8: =SUMIFS('Source Data'!$L$2:$L$268,'Source Data'!$F$2:$F$268,"Included",'Source Data'!$B$2:$B$268,"(direct)") -> 691574.65 | F8: =IFERROR(D8/B8,0) -> 0.44086022 | G8: =SUMIFS('Source Data'!$O$2:$O$268,'Source Data'!$F$2:$F$268,"Included",'Source Data'!$B$2:$B$268,"(direct)") -> 26 | H8: =SUMIFS('Source Data'!$Q$2:$Q$268,'Source Data'!$F$2:$F$268,"Included",'Source Data'!$B$2:$B$268,"(direct)") -> 452018.2 | I8: =SUMIFS('Source Data'!$P$2:$P$268,'Source Data'!$F$2:$F$268,"Included",'Source Data'!$B$2:$B$268,"(direct)") -> 443818.58 | J8: =SUMIFS('Source Data'!$R$2:$R$268,'Source Data'!$F$2:$F$268,"Included",'Source Data'!$B$2:$B$268,"(direct)") -> 0 | K8: =IFERROR(C8/B8,0) -> 17068.94 | L8: =IFERROR(E8/C8,0) -> 0.43566188
A9: (organic) | B9: =COUNTIFS('Source Data'!$F$2:$F$268,"Included",'Source Data'!$B$2:$B$268,"(organic)") -> 74 | C9: =SUMIFS('Source Data'!$K$2:$K$268,'Source Data'!$F$2:$F$268,"Included",'Source Data'!$B$2:$B$268,"(organic)") -> 1274711.2 | D9: =SUMIFS('Source Data'!$N$2:$N$268,'Source Data'!$F$2:$F$268,"Included",'Source Data'!$B$2:$B$268,"(organic)") -> 34 | E9: =SUMIFS('Source Data'!$L$2:$L$268,'Source Data'!$F$2:$F$268,"Included",'Source Data'!$B$2:$B$268,"(organic)") -> 615954.2 | F9: =IFERROR(D9/B9,0) -> 0.45945946 | G9: =SUMIFS('Source Data'!$O$2:$O$268,'Source Data'!$F$2:$F$268,"Included",'Source Data'!$B$2:$B$268,"(organic)") -> 24 | H9: =SUMIFS('Source Data'!$Q$2:$Q$268,'Source Data'!$F$2:$F$268,"Included",'Source Data'!$B$2:$B$268,"(organic)") -> 381322.94 | I9: =SUMIFS('Source Data'!$P$2:$P$268,'Source Data'!$F$2:$F$268,"Included",'Source Data'!$B$2:$B$268,"(organic)") -> 217158.02 | J9: =SUMIFS('Source Data'!$R$2:$R$268,'Source Data'!$F$2:$F$268,"Included",'Source Data'!$B$2:$B$268,"(organic)") -> 60276.07 | K9: =IFERROR(C9/B9,0) -> 17225.827 | L9: =IFERROR(E9/C9,0) -> 0.48321077
A10: (referral) | B10: =COUNTIFS('Source Data'!$F$2:$F$268,"Included",'Source Data'!$B$2:$B$268,"(referral)") -> 28 | C10: =SUMIFS('Source Data'!$K$2:$K$268,'Source Data'!$F$2:$F$268,"Included",'Source Data'!$B$2:$B$268,"(referral)") -> 464584.11 | D10: =SUMIFS('Source Data'!$N$2:$N$268,'Source Data'!$F$2:$F$268,"Included",'Source Data'!$B$2:$B$268,"(referral)") -> 10 | E10: =SUMIFS('Source Data'!$L$2:$L$268,'Source Data'!$F$2:$F$268,"Included",'Source Data'!$B$2:$B$268,"(referral)") -> 273228.94 | F10: =IFERROR(D10/B10,0) -> 0.35714286 | G10: =SUMIFS('Source Data'!$O$2:$O$268,'Source Data'!$F$2:$F$268,"Included",'Source Data'!$B$2:$B$268,"(referral)") -> 11 | H10: =SUMIFS('Source Data'!$Q$2:$Q$268,'Source Data'!$F$2:$F$268,"Included",'Source Data'!$B$2:$B$268,"(referral)") -> 132243.91 | I10: =SUMIFS('Source Data'!$P$2:$P$268,'Source Data'!$F$2:$F$268,"Included",'Source Data'!$B$2:$B$268,"(referral)") -> 48170.72 | J10: =SUMIFS('Source Data'!$R$2:$R$268,'Source Data'!$F$2:$F$268,"Included",'Source Data'!$B$2:$B$268,"(referral)") -> 10940.54 | K10: =IFERROR(C10/B10,0) -> 16592.29 | L10: =IFERROR(E10/C10,0) -> 0.58811512
A11: All Brand - PMax PH | B11: =COUNTIFS('Source Data'!$F$2:$F$268,"Included",'Source Data'!$B$2:$B$268,"All Brand - PMax PH") -> 13 | C11: =SUMIFS('Source Data'!$K$2:$K$268,'Source Data'!$F$2:$F$268,"Included",'Source Data'!$B$2:$B$268,"All Brand - PMax PH") -> 235238.03 | D11: =SUMIFS('Source Data'!$N$2:$N$268,'Source Data'!$F$2:$F$268,"Included",'Source Data'!$B$2:$B$268,"All Brand - PMax PH") -> 4 | E11: =SUMIFS('Source Data'!$L$2:$L$268,'Source Data'!$F$2:$F$268,"Included",'Source Data'!$B$2:$B$268,"All Brand - PMax PH") -> 101345.98 | F11: =IFERROR(D11/B11,0) -> 0.30769231 | G11: =SUMIFS('Source Data'!$O$2:$O$268,'Source Data'!$F$2:$F$268,"Included",'Source Data'!$B$2:$B$268,"All Brand - PMax PH") -> 4 | H11: =SUMIFS('Source Data'!$Q$2:$Q$268,'Source Data'!$F$2:$F$268,"Included",'Source Data'!$B$2:$B$268,"All Brand - PMax PH") -> 51644.99 | I11: =SUMIFS('Source Data'!$P$2:$P$268,'Source Data'!$F$2:$F$268,"Included",'Source Data'!$B$2:$B$268,"All Brand - PMax PH") -> 82247.06 | J11: =SUMIFS('Source Data'!$R$2:$R$268,'Source Data'!$F$2:$F$268,"Included",'Source Data'!$B$2:$B$268,"All Brand - PMax PH") -> 0 | K11: =IFERROR(C11/B11,0) -> 18095.233 | L11: =IFERROR(E11/C11,0) -> 0.43082311
A12: BFG - PMax (Traffic) | B12: =COUNTIFS('Source Data'!$F$2:$F$268,"Included",'Source Data'!$B$2:$B$268,"BFG - PMax (Traffic)") -> 4 | C12: =SUMIFS('Source Data'!$K$2:$K$268,'Source Data'!$F$2:$F$268,"Included",'Source Data'!$B$2:$B$268,"BFG - PMax (Traffic)") -> 64256.79 | D12: =SUMIFS('Source Data'!$N$2:$N$268,'Source Data'!$F$2:$F$268,"Included",'Source Data'!$B$2:$B$268,"BFG - PMax (Traffic)") -> 0 | E12: =SUMIFS('Source Data'!$L$2:$L$268,'Source Data'!$F$2:$F$268,"Included",'Source Data'!$B$2:$B$268,"BFG - PMax (Traffic)") -> 0 | F12: =IFERROR(D12/B12,0) -> 0 | G12: =SUMIFS('Source Data'!$O$2:$O$268,'Source Data'!$F$2:$F$268,"Included",'Source Data'!$B$2:$B$268,"BFG - PMax (Traffic)") -> 3 | H12: =SUMIFS('Source Data'!$Q$2:$Q$268,'Source Data'!$F$2:$F$268,"Included",'Source Data'!$B$2:$B$268,"BFG - PMax (Traffic)") -> 39372.86 | I12: =SUMIFS('Source Data'!$P$2:$P$268,'Source Data'!$F$2:$F$268,"Included",'Source Data'!$B$2:$B$268,"BFG - PMax (Traffic)") -> 24883.93 | J12: =SUMIFS('Source Data'!$R$2:$R$268,'Source Data'!$F$2:$F$268,"Included",'Source Data'!$B$2:$B$268,"BFG - PMax (Traffic)") -> 0 | K12: =IFERROR(C12/B12,0) -> 16064.198 | L12: =IFERROR(E12/C12,0) -> 0
A13: BFG Advantage Touring – PMax PH | B13: =COUNTIFS('Source Data'!$F$2:$F$268,"Included",'Source Data'!$B$2:$B$268,"BFG Advantage Touring – PMax PH") -> 14 | C13: =SUMIFS('Source Data'!$K$2:$K$268,'Source Data'!$F$2:$F$268,"Included",'Source Data'!$B$2:$B$268,"BFG Advantage Touring – PMax PH") -> 261844.11 | D13: =SUMIFS('Source Data'!$N$2:$N$268,'Source Data'!$F$2:$F$268,"Included",'Source Data'!$B$2:$B$268,"BFG Advantage Touring – PMax PH") -> 4 | E13: =SUMIFS('Source Data'!$L$2:$L$268,'Source Data'!$F$2:$F$268,"Included",'Source Data'!$B$2:$B$268,"BFG Advantage Touring – PMax PH") -> 62467.05 | F13: =IFERROR(D13/B13,0) -> 0.28571429 | G13: =SUMIFS('Source Data'!$O$2:$O$268,'Source Data'!$F$2:$F$268,"Included",'Source Data'!$B$2:$B$268,"BFG Advantage Touring – PMax PH") -> 3 | H13: =SUMIFS('Source Data'!$Q$2:$Q$268,'Source Data'!$F$2:$F$268,"Included",'Source Data'!$B$2:$B$268,"BFG Advantage Touring – PMax PH") -> 47300 | I13: =SUMIFS('Source Data'!$P$2:$P$268,'Source Data'!$F$2:$F$268,"Included",'Source Data'!$B$2:$B$268,"BFG Advantage Touring – PMax PH") -> 152077.06 | J13: =SUMIFS('Source Data'!$R$2:$R$268,'Source Data'!$F$2:$F$268,"Included",'Source Data'!$B$2:$B$268,"BFG Advantage Touring – PMax PH") -> 0 | K13: =IFERROR(C13/B13,0) -> 18703.151 | L13: =IFERROR(E13/C13,0) -> 0.2385658
A14: Gulongph Branding - PMax | B14: =COUNTIFS('Source Data'!$F$2:$F$268,"Included",'Source Data'!$B$2:$B$268,"Gulongph Branding - PMax") -> 6 | C14: =SUMIFS('Source Data'!$K$2:$K$268,'Source Data'!$F$2:$F$268,"Included",'Source Data'!$B$2:$B$268,"Gulongph Branding - PMax") -> 118985.46 | D14: =SUMIFS('Source Data'!$N$2:$N$268,'Source Data'!$F$2:$F$268,"Included",'Source Data'!$B$2:$B$268,"Gulongph Branding - PMax") -> 3 | E14: =SUMIFS('Source Data'!$L$2:$L$268,'Source Data'!$F$2:$F$268,"Included",'Source Data'!$B$2:$B$268,"Gulongph Branding - PMax") -> 60447.95 | F14: =IFERROR(D14/B14,0) -> 0.5 | G14: =SUMIFS('Source Data'!$O$2:$O$268,'Source Data'!$F$2:$F$268,"Included",'Source Data'!$B$2:$B$268,"Gulongph Branding - PMax") -> 0 | H14: =SUMIFS('Source Data'!$Q$2:$Q$268,'Source Data'!$F$2:$F$268,"Included",'Source Data'!$B$2:$B$268,"Gulongph Branding - PMax") -> 0 | I14: =SUMIFS('Source Data'!$P$2:$P$268,'Source Data'!$F$2:$F$268,"Included",'Source Data'!$B$2:$B$268,"Gulongph Branding - PMax") -> 58537.51 | J14: =SUMIFS('Source Data'!$R$2:$R$268,'Source Data'!$F$2:$F$268,"Included",'Source Data'!$B$2:$B$268,"Gulongph Branding - PMax") -> 0 | K14: =IFERROR(C14/B14,0) -> 19830.91 | L14: =IFERROR(E14/C14,0) -> 0.50802804
A15: MICHELIN - PMAX (Traffic) | B15: =COUNTIFS('Source Data'!$F$2:$F$268,"Included",'Source Data'!$B$2:$B$268,"MICHELIN - PMAX (Traffic)") -> 1 | C15: =SUMIFS('Source Data'!$K$2:$K$268,'Source Data'!$F$2:$F$268,"Included",'Source Data'!$B$2:$B$268,"MICHELIN - PMAX (Traffic)") -> 7095.27 | D15: =SUMIFS('Source Data'!$N$2:$N$268,'Source Data'!$F$2:$F$268,"Included",'Source Data'!$B$2:$B$268,"MICHELIN - PMAX (Traffic)") -> 1 | E15: =SUMIFS('Source Data'!$L$2:$L$268,'Source Data'!$F$2:$F$268,"Included",'Source Data'!$B$2:$B$268,"MICHELIN - PMAX (Traffic)") -> 7095.27 | F15: =IFERROR(D15/B15,0) -> 1 | G15: =SUMIFS('Source Data'!$O$2:$O$268,'Source Data'!$F$2:$F$268,"Included",'Source Data'!$B$2:$B$268,"MICHELIN - PMAX (Traffic)") -> 0 | H15: =SUMIFS('Source Data'!$Q$2:$Q$268,'Source Data'!$F$2:$F$268,"Included",'Source Data'!$B$2:$B$268,"MICHELIN - PMAX (Traffic)") -> 0 | I15: =SUMIFS('Source Data'!$P$2:$P$268,'Source Data'!$F$2:$F$268,"Included",'Source Data'!$B$2:$B$268,"MICHELIN - PMAX (Traffic)") -> 0 | J15: =SUMIFS('Source Data'!$R$2:$R$268,'Source Data'!$F$2:$F$268,"Included",'Source Data'!$B$2:$B$268,"MICHELIN - PMAX (Traffic)") -> 0 | K15: =IFERROR(C15/B15,0) -> 7095.27 | L15: =IFERROR(E15/C15,0) -> 1
A16: Michelin - PMax PH | B16: =COUNTIFS('Source Data'!$F$2:$F$268,"Included",'Source Data'!$B$2:$B$268,"Michelin - PMax PH") -> 22 | C16: =SUMIFS('Source Data'!$K$2:$K$268,'Source Data'!$F$2:$F$268,"Included",'Source Data'!$B$2:$B$268,"Michelin - PMax PH") -> 562444.91 | D16: =SUMIFS('Source Data'!$N$2:$N$268,'Source Data'!$F$2:$F$268,"Included",'Source Data'!$B$2:$B$268,"Michelin - PMax PH") -> 10 | E16: =SUMIFS('Source Data'!$L$2:$L$268,'Source Data'!$F$2:$F$268,"Included",'Source Data'!$B$2:$B$268,"Michelin - PMax PH") -> 237374.56 | F16: =IFERROR(D16/B16,0) -> 0.45454545 | G16: =SUMIFS('Source Data'!$O$2:$O$268,'Source Data'!$F$2:$F$268,"Included",'Source Data'!$B$2:$B$268,"Michelin - PMax PH") -> 7 | H16: =SUMIFS('Source Data'!$Q$2:$Q$268,'Source Data'!$F$2:$F$268,"Included",'Source Data'!$B$2:$B$268,"Michelin - PMax PH") -> 168240.16 | I16: =SUMIFS('Source Data'!$P$2:$P$268,'Source Data'!$F$2:$F$268,"Included",'Source Data'!$B$2:$B$268,"Michelin - PMax PH") -> 145889.65 | J16: =SUMIFS('Source Data'!$R$2:$R$268,'Source Data'!$F$2:$F$268,"Included",'Source Data'!$B$2:$B$268,"Michelin - PMax PH") -> 10940.54 | K16: =IFERROR(C16/B16,0) -> 25565.678 | L16: =IFERROR(E16/C16,0) -> 0.42204055
A17: SRC | All Brands | PH | B17: =COUNTIFS('Source Data'!$F$2:$F$268,"Included",'Source Data'!$B$2:$B$268,"SRC | All Brands | PH") -> 6 | C17: =SUMIFS('Source Data'!$K$2:$K$268,'Source Data'!$F$2:$F$268,"Included",'Source Data'!$B$2:$B$268,"SRC | All Brands | PH") -> 214631.25 | D17: =SUMIFS('Source Data'!$N$2:$N$268,'Source Data'!$F$2:$F$268,"Included",'Source Data'!$B$2:$B$268,"SRC | All Brands | PH") -> 3 | E17: =SUMIFS('Source Data'!$L$2:$L$268,'Source Data'!$F$2:$F$268,"Included",'Source Data'!$B$2:$B$268,"SRC | All Brands | PH") -> 33363.03 | F17: =IFERROR(D17/B17,0) -> 0.5 | G17: =SUMIFS('Source Data'!$O$2:$O$268,'Source Data'!$F$2:$F$268,"Included",'Source Data'!$B$2:$B$268,"SRC | All Brands | PH") -> 1 | H17: =SUMIFS('Source Data'!$Q$2:$Q$268,'Source Data'!$F$2:$F$268,"Included",'Source Data'!$B$2:$B$268,"SRC | All Brands | PH") -> 21633.93 | I17: =SUMIFS('Source Data'!$P$2:$P$268,'Source Data'!$F$2:$F$268,"Included",'Source Data'!$B$2:$B$268,"SRC | All Brands | PH") -> 159634.29 | J17: =SUMIFS('Source Data'!$R$2:$R$268,'Source Data'!$F$2:$F$268,"Included",'Source Data'!$B$2:$B$268,"SRC | All Brands | PH") -> 0 | K17: =IFERROR(C17/B17,0) -> 35771.875 | L17: =IFERROR(E17/C17,0) -> 0.15544349

Sheet Chart Data
A1: Week | B1: Google Ads | C1: Direct & Organic | D1: Referral | E1: Total net | F1: Total fulfilled | G1: Days | H1: Net per day
A2: Week 1 | B2: ='Weekly Summary'!D7 -> 522608.31 | C2: ='Weekly Summary'!D8 -> 793046.8 | D2: ='Weekly Summary'!D9 -> 90845.09 | E2: =SUM(B2:D2) -> 1406500.2 | F2: 805398.16 | G2: 7 | H2: =E2/G2 -> 200928.6
A3: Week 2 | B3: ='Weekly Summary'!D10 -> 232561.16 | C3: ='Weekly Summary'!D11 -> 1071885 | D3: ='Weekly Summary'!D12 -> 208630.37 | E3: =SUM(B3:D3) -> 1513076.5 | F3: 812394.74 | G3: 7 | H3: =E3/G3 -> 216153.79
A4: Week 3 | B4: ='Weekly Summary'!D13 -> 552631.53 | C4: ='Weekly Summary'!D14 -> 684801.78 | D4: ='Weekly Summary'!D15 -> 134840.53 | E4: =SUM(B4:D4) -> 1372273.8 | F4: 473672.39 | G4: 7 | H4: =E4/G4 -> 196039.12
A5: Week 4 (partial) | B5: ='Weekly Summary'!D16 -> 165308.48 | C5: ='Weekly Summary'!D17 -> 312389.11 | D5: ='Weekly Summary'!D18 -> 30268.12 | E5: =SUM(B5:D5) -> 507965.71 | F5: 0 | G5: 3 | H5: =E5/G5 -> 169321.9

Sheet Read Me
A1: READ ME | Scope & methodology
A3: Reproducible analysis with source records and formula-based summaries.
A6: Period | B6: September 1–24, 2026 using backend order_date, not analytics event date. Dates are backend DATETIME values without timezone conversion.
A7: Weeks | B7: Week 1 Sep 1–7; Week 2 Sep 8–14; Week 3 Sep 15–21; Week 4 Sep 22–24 (3 days).
A8: Snapshot | B8: ['2026-09-25 02:00:22']
A9: Source mapping | B9: Google Ads = first supplied export, including its cross-network row. Direct & Organic combines two campaign labels; Campaign Breakdown keeps them separate. Referral = referral.csv.
A10: Net sales | B10: Existing gulong_core.orders_raw_deduped calculation: ROUND(total_amount_due / 1.12, 2). Source table is gulong_backend.orders_raw. Cancelled, unfinished, returns and refunds remain in all-order net sales.
A11: Fulfilled revenue | B11: is_fulfillment_success_order = true and is_excluded_test_order = false. Full order value is used even for partial payment. This is not cash collected or a formal accounting revenue-recognition schedule.
A12: Customer type | B12: customer_type_raw from backend, preserving the backend label. Unknown means no backend match. It does not describe new/returning status.
A13: Coverage | B13: 267 CSV records / distinct order IDs; 264 backend matches; 262 September orders; 5 exceptions. No duplicate or overlapping order IDs.
A14: Excluded orders | B14: August orders 38959 and 38805, plus unmatched IDs 39900, 39109, 39052. Source Data retains all records; dashboard includes only September 1–24.
A15: Event counts | B15: 437 purchase events across 267 unique IDs. Purchase events are not revenue multipliers.
A16: Summary formulas | B16: COUNTIFS and SUMIFS reference Source Data, with cached results for preview. Changes within existing source rows recalculate in Excel. New rows require rebuilding to extend formula ranges. Analyst findings are snapshot commentary.
A17: Source files | B17: Three Original tabs retain the input columns and values. Backend Extract retains the retrieved query result. Source Data contains the joined analysis fields. Exceptions lists excluded/unmatched records.
... A20: Refresh | B20: Run match_orders.sql via bq to replace backend_orders.json, then run build_dashboard.py with XlsxWriter available. Files saved in channel_revenue_excel.
