Workbook

Sheet Executive Analysis
A1: Tire Sales Executive Analysis | 2024–2026
A2: Fulfilled-sales view of volume, net sales, realized price, and category mix.
A3: REPORTING COVERAGE: 2024 and 2025 are complete January–December periods (12 months each). 2026 covers January–August only (8 months), with September–December (4 months) remaining. Therefore, 2026 totals are not directly comparable with the two complete full years.
A4: 3-Year Tires Sold | E4: 3-Year Net Sales | I4: Weighted Avg ₱/Tire
A5: 33661 | E5: 1.8795782e+08 | I5: 5583.8454
A7: 2024–26 Volume CAGR | E7: 2024–26 Sales CAGR | I7: Premium Revenue Share
A8: 0.089100602 | E8: 0.1256174 | I8: 0.64937694
A10: Key Findings
A11: • 2025 was the peak year: 13,566 tires and ₱75,125,404.25; volume rose 47.6% versus 2024.
A12: • 2024 and 2025 contain complete January–December results. The 2026 figures currently contain January–August only, so the apparent difference versus full-year 2025 is a partial-period comparison, not a final annual decline.
A13: • Premium contributed 64.9% of revenue and 47.9% of tires across the period, making it the main value driver.
A14: • Budget was the second-largest volume tier at 11,305 tires (33.6%), but only 18.6% of revenue because of its lower realized price.
A15: • Economy expanded from 126 tires in 2024 to 276 in 2026, but remained only 1.9% of three-year volume.
A17: Annual Trend
A18: Year | B18: Tires Sold | C18: Net Sales (₱) | D18: Avg ₱/Tire | E18: YoY Volume | F18: YoY Sales
A19: 2024 | B19: 9192 | C19: 49771369 | D19: 5414.6398 | E19: — | F19: —
A20: 2025 | B20: 13566 | C20: 75125404 | D20: 5537.7712 | E20: 0.47584856 | F20: 0.50941005
A21: 2026 | B21: 10903 | C21: 63061047 | D21: 5783.8253 | E21: -0.19629957 | F21: -0.16058958
A24: Three-Year Category Mix
A25: Category | B25: Tires Sold | C25: Volume Share | D25: Net Sales (₱) | E25: Revenue Share | F25: Avg ₱/Tire
A26: Premium | B26: 16124 | C26: 0.47901132 | D26: 1.2205547e+08 | E26: 0.64937694 | F26: 7569.8012
A27: Mid Range | B27: 5586 | C27: 0.16594872 | D27: 28087016 | E27: 0.14943255 | F27: 5028.1088
A28: Budget | B28: 11305 | C28: 0.33584861 | D28: 34980067 | E28: 0.18610594 | F28: 3094.212
A29: Economy | B29: 646 | C29: 0.019191349 | D29: 2835263.9 | E29: 0.015084575 | F29: 4388.9534

Sheet Tires Sold per Year
A1: Tires Sold per Year — Gulong.ph
A2: Fulfilled tire sales. Complete years and partial-year results are identified separately for fair interpretation.
A3: Coverage: 2024 and 2025 are complete January–December (12 months). 2026 is January–August only (8 months), with September–December remaining.
A5: Year | B5: Coverage | C5: Months | D5: Status | E5: Tires Sold | F5: Net Sales (₱) | G5: Avg ₱ / Tire | H5: Avg Tires / Month | I5: Avg Net Sales / Month | J5: Comparable YoY Tires
A6: 2024 | B6: Jan–Dec | C6: 12 | D6: Complete year | E6: 9192 | F6: 49771369 | G6: 5414.6398 | H6: 766 | I6: 4147614.1 | J6: —
A7: 2025 | B7: Jan–Dec | C7: 12 | D7: Complete year | E7: 13566 | F7: 75125404 | G7: 5537.7712 | H7: 1130.5 | I7: 6260450.4 | J7: 0.47584856
A8: 2026 | B8: Jan–Aug | C8: 8 | D8: Partial year | E8: 10903 | F8: 63061047 | G8: 5783.8253 | H8: 1362.875 | I8: 7882630.9 | J8: —
A10: Interpretation
A11: • 2025 versus 2024 is a valid full-year comparison because both periods contain 12 months.
A12: • 2026 total tires and net sales should not be treated as a full-year decline because only January–August is included.
A13: • Average-per-month figures normalize for the number of recorded months, but they are descriptive run rates—not forecasts for September–December.
A14: • Net Sales retains the source definition/label “Net Sales of VAT.” All figures represent fulfilled sales.

Sheet Price per Category
A1: Category Performance
A2: Average selling price, tires sold, and net sales by category. 2024 and 2025 cover January–December; 2026 covers January–August, with four months remaining.
A4: Category | B4: 2024 Avg ₱/Tire | C4: 2025 Avg ₱/Tire | D4: 2026 Avg ₱/Tire | E4: 3-Yr Avg ₱/Tire | F4: 3-Yr Tires | G4: 3-Yr Net Sales (₱) | H4: Revenue Share
A5: Premium | B5: =SUMIFS('Raw Data'!$E$5:$E$16,'Raw Data'!$B$5:$B$16,2024,'Raw Data'!$C$5:$C$16,$A5)/SUMIFS('Raw Data'!$D$5:$D$16,'Raw Data'!$B$5:$B$16,2024,'Raw Data'!$C$5:$C$16,$A5) | C5: =SUMIFS('Raw Data'!$E$5:$E$16,'Raw Data'!$B$5:$B$16,2025,'Raw Data'!$C$5:$C$16,$A5)/SUMIFS('Raw Data'!$D$5:$D$16,'Raw Data'!$B$5:$B$16,2025,'Raw Data'!$C$5:$C$16,$A5) | D5: =SUMIFS('Raw Data'!$E$5:$E$16,'Raw Data'!$B$5:$B$16,2026,'Raw Data'!$C$5:$C$16,$A5)/SUMIFS('Raw Data'!$D$5:$D$16,'Raw Data'!$B$5:$B$16,2026,'Raw Data'!$C$5:$C$16,$A5) | E5: =G5/F5 | F5: =SUMIF('Raw Data'!$C$5:$C$16,A5,'Raw Data'!$D$5:$D$16) | G5: =SUMIF('Raw Data'!$C$5:$C$16,A5,'Raw Data'!$E$5:$E$16) | H5: =G5/SUM($G$5:$G$8)
A6: Mid Range | B6: =SUMIFS('Raw Data'!$E$5:$E$16,'Raw Data'!$B$5:$B$16,2024,'Raw Data'!$C$5:$C$16,$A6)/SUMIFS('Raw Data'!$D$5:$D$16,'Raw Data'!$B$5:$B$16,2024,'Raw Data'!$C$5:$C$16,$A6) | C6: =SUMIFS('Raw Data'!$E$5:$E$16,'Raw Data'!$B$5:$B$16,2025,'Raw Data'!$C$5:$C$16,$A6)/SUMIFS('Raw Data'!$D$5:$D$16,'Raw Data'!$B$5:$B$16,2025,'Raw Data'!$C$5:$C$16,$A6) | D6: =SUMIFS('Raw Data'!$E$5:$E$16,'Raw Data'!$B$5:$B$16,2026,'Raw Data'!$C$5:$C$16,$A6)/SUMIFS('Raw Data'!$D$5:$D$16,'Raw Data'!$B$5:$B$16,2026,'Raw Data'!$C$5:$C$16,$A6) | E6: =G6/F6 | F6: =SUMIF('Raw Data'!$C$5:$C$16,A6,'Raw Data'!$D$5:$D$16) | G6: =SUMIF('Raw Data'!$C$5:$C$16,A6,'Raw Data'!$E$5:$E$16) | H6: =G6/SUM($G$5:$G$8)
A7: Budget | B7: =SUMIFS('Raw Data'!$E$5:$E$16,'Raw Data'!$B$5:$B$16,2024,'Raw Data'!$C$5:$C$16,$A7)/SUMIFS('Raw Data'!$D$5:$D$16,'Raw Data'!$B$5:$B$16,2024,'Raw Data'!$C$5:$C$16,$A7) | C7: =SUMIFS('Raw Data'!$E$5:$E$16,'Raw Data'!$B$5:$B$16,2025,'Raw Data'!$C$5:$C$16,$A7)/SUMIFS('Raw Data'!$D$5:$D$16,'Raw Data'!$B$5:$B$16,2025,'Raw Data'!$C$5:$C$16,$A7) | D7: =SUMIFS('Raw Data'!$E$5:$E$16,'Raw Data'!$B$5:$B$16,2026,'Raw Data'!$C$5:$C$16,$A7)/SUMIFS('Raw Data'!$D$5:$D$16,'Raw Data'!$B$5:$B$16,2026,'Raw Data'!$C$5:$C$16,$A7) | E7: =G7/F7 | F7: =SUMIF('Raw Data'!$C$5:$C$16,A7,'Raw Data'!$D$5:$D$16) | G7: =SUMIF('Raw Data'!$C$5:$C$16,A7,'Raw Data'!$E$5:$E$16) | H7: =G7/SUM($G$5:$G$8)
A8: Economy | B8: =SUMIFS('Raw Data'!$E$5:$E$16,'Raw Data'!$B$5:$B$16,2024,'Raw Data'!$C$5:$C$16,$A8)/SUMIFS('Raw Data'!$D$5:$D$16,'Raw Data'!$B$5:$B$16,2024,'Raw Data'!$C$5:$C$16,$A8) | C8: =SUMIFS('Raw Data'!$E$5:$E$16,'Raw Data'!$B$5:$B$16,2025,'Raw Data'!$C$5:$C$16,$A8)/SUMIFS('Raw Data'!$D$5:$D$16,'Raw Data'!$B$5:$B$16,2025,'Raw Data'!$C$5:$C$16,$A8) | D8: =SUMIFS('Raw Data'!$E$5:$E$16,'Raw Data'!$B$5:$B$16,2026,'Raw Data'!$C$5:$C$16,$A8)/SUMIFS('Raw Data'!$D$5:$D$16,'Raw Data'!$B$5:$B$16,2026,'Raw Data'!$C$5:$C$16,$A8) | E8: =G8/F8 | F8: =SUMIF('Raw Data'!$C$5:$C$16,A8,'Raw Data'!$D$5:$D$16) | G8: =SUMIF('Raw Data'!$C$5:$C$16,A8,'Raw Data'!$E$5:$E$16) | H8: =G8/SUM($G$5:$G$8)

Sheet Raw Data
A1: Raw Data — Fulfilled Tire Sales
A2: Normalized category-year records. 2024 and 2025 are complete January–December periods; 2026 covers January–August only, with September–December remaining.
A4: Record ID | B4: Year | C4: Category | D4: Tires Sold | E4: Net Sales (₱) | F4: Avg Net Sales / Tire (₱)
A5: 2024-PREMIUM | B5: 2024 | C5: Premium | D5: 5194 | E5: 35201435 | F5: =E5/D5
A6: 2024-MID_RANGE | B6: 2024 | C6: Mid Range | D6: 852 | E6: 4669559.3 | F6: =E6/D6
A7: 2024-BUDGET | B7: 2024 | C7: Budget | D7: 3020 | E7: 9449930.1 | F7: =E7/D7
A8: 2024-ECONOMY | B8: 2024 | C8: Economy | D8: 126 | E8: 450444.68 | F8: =E8/D8
A9: 2025-PREMIUM | B9: 2025 | C9: Premium | D9: 5957 | E9: 46635442 | F9: =E9/D9
A10: 2025-MID_RANGE | B10: 2025 | C10: Mid Range | D10: 2480 | E10: 12239379 | F10: =E10/D10
A11: 2025-BUDGET | B11: 2025 | C11: Budget | D11: 4885 | E11: 15025052 | F11: =E11/D11
A12: 2025-ECONOMY | B12: 2025 | C12: Economy | D12: 244 | E12: 1225530.9 | F12: =E12/D12
A13: 2026-PREMIUM | B13: 2026 | C13: Premium | D13: 4973 | E13: 40218597 | F13: =E13/D13
A14: 2026-MID_RANGE | B14: 2026 | C14: Mid Range | D14: 2254 | E14: 11178078 | F14: =E14/D14
A15: 2026-BUDGET | B15: 2026 | C15: Budget | D15: 3400 | E15: 10505084 | F15: =E15/D15
A16: 2026-ECONOMY | B16: 2026 | C16: Economy | D16: 276 | E16: 1159288.4 | F16: =E16/D16

Sheet Methodology
A1: Analysis & Methodology
A2: Definitions, calculations, controls, assumptions, and appropriate interpretation.
A4: Analysis Scope
A5: Population | B5: Fulfilled tire sales by year and price category. 2024 and 2025 are complete January–December periods (12 months); 2026 covers January–August only (8 months), with four months remaining.
A6: Grain | B6: One record per Year × Category; 12 unique records in total.
A7: Categories | B7: Premium, Mid Range, Budget, and Economy.
A8: Revenue measure | B8: Net Sales (₱), retaining the source definition/label “Net Sales of VAT.”
A9: Unit | B9: One tire sold; order count and customer count are not available in this workbook.
A11: Metric Definitions
A12: Metric | B12: Calculation | C12: Interpretation | D12: Caution
A13: Tires Sold | B13: Sum of Tires Sold | C13: Fulfilled unit volume. | D13: Does not represent orders; an order may contain multiple tires.
A14: Net Sales | B14: Sum of Net Sales (₱) | C14: Revenue measure supplied by the source. | D14: No gross sales, discounts, cost, or margin fields are available.
A15: Avg ₱ / Tire | B15: Net Sales ÷ Tires Sold | C15: Weighted realized average price per tire. | D15: Not a simple average of rows and not a SKU-level price.
A16: YoY Growth | B16: Current year ÷ prior year − 1 | C16: Annual change in volume or net sales. | D16: 2024 and 2025 are complete 12-month years, but 2026 is an incomplete January–August period. Full-year-to-partial-year totals are not directly comparable.
A17: CAGR | B17: (2026 ÷ 2024)^(1/2) − 1 | C17: Smoothed annual growth over two year-to-year intervals. | D17: Descriptive trend, not a forecast.
A18: Mix Share | B18: Category total ÷ all-category total | C18: Category contribution to volume or revenue. | D18: Mix can shift because of volume, realized price, or both.
A20: Data Quality & Controls
A21: • Completeness: 12 expected Year × Category records are present; no blank year, category, tires, or net-sales values.
A22: • Uniqueness: each Year × Category combination occurs once.
A23: • Arithmetic: annual and category summaries are derived from the Raw Data sheet; weighted averages use total sales divided by total tires.
A24: • Reconciliation: the raw records reproduce the values embedded in the original workbook's helper ranges.
A25: • Limitation: the available file does not include SKU, transaction, customer, discount, cost, margin, geography, or monthly detail.
A26: • Important: the analysis does not infer true unit-price minima/maxima; only category-year realized averages can be calculated.
A27: REPORTING COVERAGE: 2024 and 2025 are complete January–December periods (12 months each). 2026 covers January–August only (8 months), with September–December (4 months) remaining. No September–December results or full-year projection have been included.
A28: Refresh Process
A29: Append or replace records in Raw Data using the same columns and one-row-per-Year × Category structure. Extend the Excel table if new rows are added, then extend summary ranges/formulas and refresh charts. Validate uniqueness, positive tire counts, non-negative sales, and reconciliation before interpreting changes. The Executive Analysis values in this prepared file summarize the current 2024–2026 snapshot.
